Workbook

Sheet Estadísticas
A2: Total de sitios visitados | J2: Errores por tipo de sitio | V2: Sitio | W2: Calif 1 | X2: Calif 2 | Y2: Resultado
A3: Tipo de espacio | C3: León | D3: Silao | E3: Guanajuato | F3: Irapuato | G3: Salamanca | H3: Celaya | I3: Total | J3: Error visita 1 | K3: Error visita 2 | V3: 1 | W3: =VLOOKUP(V3,'BD1'!$A$2:$AF$1139,31,0) -> 8 | X3: =VLOOKUP(V3,'BD2'!$A$2:$AF$1139,31,0) -> 8 | Y3: =IF(X3>W3,"Mejoría",IF(X3<W3,"Pérdida","Se mantiene")) -> Se mantiene
A4: PLAZA PÚBLICA | C4: =COUNTIFS('BD1'!C:C,Estadísticas!A4,'BD1'!H:H,Estadísticas!$C$3,'BD1'!K:K,"ok") -> 4 | D4: =COUNTIFS('BD1'!C:C,Estadísticas!A4,'BD1'!H:H,Estadísticas!$D$3,'BD1'!K:K,"ok") -> 8 | E4: =COUNTIFS('BD1'!C:C,Estadísticas!A4,'BD1'!H:H,Estadísticas!$E$3,'BD1'!K:K,"ok") -> 13 | F4: =COUNTIFS('BD1'!C:C,Estadísticas!A4,'BD1'!H:H,Estadísticas!$F$3,'BD1'!K:K,"ok") -> 28 | G4: =COUNTIFS('BD1'!C:C,Estadísticas!A4,'BD1'!H:H,Estadísticas!$G$3,'BD1'!K:K,"ok") -> 0 | H4: =COUNTIFS('BD1'!C:C,Estadísticas!A4,'BD1'!H:H,Estadísticas!$H$3,'BD1'!K:K,"ok") -> 11 | I4: =SUM(C4:H4) -> 64 | J4: =SUM(COUNTIFS('BD1'!C:C, Estadísticas!A4, 'BD1'!AE:AE,"7"),COUNTIFS('BD1'!C:C, Estadísticas!A4, 'BD1'!AE:AE,"6"),COUNTIFS('BD1'!C:C, Estadísticas!A4, 'BD1'!AE:AE,"5"),COUNTIFS('BD1'!C:C, Estadísticas!A4, 'BD1'!AE:AE,"4"),COUNTIFS('BD1'!C:C, Estadísticas!A4, 'BD1'!AE:AE,"3"),COUNTIFS('BD1'!C:C, Estadísticas!A4, 'BD1'!AE:AE,"2"),COUNTIFS('BD1'!C:C, Estadísticas!A4, 'BD1'!AE:AE,"1"),COUNTIFS('BD1'!C:C, Estadísticas!A4, 'BD1'!AE:AE,"0")) -> 8 | K4: =SUM(COUNTIFS('BD2'!C:C, Estadísticas!A4, 'BD2'!AE:AE,"7"),COUNTIFS('BD2'!C:C, Estadísticas!A4, 'BD2'!AE:AE,"6"),COUNTIFS('BD2'!C:C, Estadísticas!A4, 'BD2'!AE:AE,"5"),COUNTIFS('BD2'!C:C, Estadísticas!A4, 'BD2'!AE:AE,"4"),COUNTIFS('BD2'!C:C, Estadísticas!A4, 'BD2'!AE:AE,"3"),COUNTIFS('BD2'!C:C, Estadísticas!A4, 'BD2'!AE:AE,"2"),COUNTIFS('BD2'!C:C, Estadísticas!A4, 'BD2'!AE:AE,"1"),COUNTIFS('BD2'!C:C, Estadísticas!A4, 'BD2'!AE:AE,"0")) -> 38 | V4: 2 | W4: =VLOOKUP(V4,'BD1'!$A$2:$AF$1139,31,0) -> 8 | X4: =VLOOKUP(V4,'BD2'!$A$2:$AF$1139,31,0) -> 8 | Y4: =IF(X4>W4,"Mejoría",IF(X4<W4,"Pérdida","Se mantiene")) -> Se mantiene
A5: ESPACIO DEPORTIVO | C5: =COUNTIFS('BD1'!C:C,Estadísticas!A5,'BD1'!H:H,Estadísticas!$C$3,'BD1'!K:K,"ok") -> 15 | D5: =COUNTIFS('BD1'!C:C,Estadísticas!A5,'BD1'!H:H,Estadísticas!$D$3,'BD1'!K:K,"ok") -> 3 | E5: =COUNTIFS('BD1'!C:C,Estadísticas!A5,'BD1'!H:H,Estadísticas!$E$3,'BD1'!K:K,"ok") -> 7 | F5: =COUNTIFS('BD1'!C:C,Estadísticas!A5,'BD1'!H:H,Estadísticas!$F$3,'BD1'!K:K,"ok") -> 5 | G5: =COUNTIFS('BD1'!C:C,Estadísticas!A5,'BD1'!H:H,Estadísticas!$G$3,'BD1'!K:K,"ok") -> 0 | H5: =COUNTIFS('BD1'!C:C,Estadísticas!A5,'BD1'!H:H,Estadísticas!$H$3,'BD1'!K:K,"ok") -> 4 | I5: =SUM(C5:H5) -> 34 | J5: =SUM(COUNTIFS('BD1'!C:C, Estadísticas!A5, 'BD1'!AE:AE,"7"),COUNTIFS('BD1'!C:C, Estadísticas!A5, 'BD1'!AE:AE,"6"),COUNTIFS('BD1'!C:C, Estadísticas!A5, 'BD1'!AE:AE,"5"),COUNTIFS('BD1'!C:C, Estadísticas!A5, 'BD1'!AE:AE,"4"),COUNTIFS('BD1'!C:C, Estadísticas!A5, 'BD1'!AE:AE,"3"),COUNTIFS('BD1'!C:C, Estadísticas!A5, 'BD1'!AE:AE,"2"),COUNTIFS('BD1'!C:C, Estadísticas!A5, 'BD1'!AE:AE,"1"),COUNTIFS('BD1'!C:C, Estadísticas!A5, 'BD1'!AE:AE,"0")) -> 4 | K5: =SUM(COUNTIFS('BD2'!C:C, Estadísticas!A5, 'BD2'!AE:AE,"7"),COUNTIFS('BD2'!C:C, Estadísticas!A5, 'BD2'!AE:AE,"6"),COUNTIFS('BD2'!C:C, Estadísticas!A5, 'BD2'!AE:AE,"5"),COUNTIFS('BD2'!C:C, Estadísticas!A5, 'BD2'!AE:AE,"4"),COUNTIFS('BD2'!C:C, Estadísticas!A5, 'BD2'!AE:AE,"3"),COUNTIFS('BD2'!C:C, Estadísticas!A5, 'BD2'!AE:AE,"2"),COUNTIFS('BD2'!C:C, Estadísticas!A5, 'BD2'!AE:AE,"1"),COUNTIFS('BD2'!C:C, Estadísticas!A5, 'BD2'!AE:AE,"0")) -> 13 | O5: Mejoría | Q5: Se mantiene | S5: Pérdida | V5: 3 | W5: =VLOOKUP(V5,'BD1'!$A$2:$AF$1139,31,0) -> 8 | X5: =VLOOKUP(V5,'BD2'!$A$2:$AF$1139,31,0) -> 0 | Y5: =IF(X5>W5,"Mejoría",IF(X5<W5,"Pérdida","Se mantiene")) -> Pérdida
A6: PRESIDENCIA | C6: =COUNTIFS('BD1'!C:C,Estadísticas!A6,'BD1'!H:H,Estadísticas!$C$3,'BD1'!K:K,"ok") -> 1 | D6: =COUNTIFS('BD1'!C:C,Estadísticas!A6,'BD1'!H:H,Estadísticas!$D$3,'BD1'!K:K,"ok") -> 0 | E6: =COUNTIFS('BD1'!C:C,Estadísticas!A6,'BD1'!H:H,Estadísticas!$E$3,'BD1'!K:K,"ok") -> 1 | F6: =COUNTIFS('BD1'!C:C,Estadísticas!A6,'BD1'!H:H,Estadísticas!$F$3,'BD1'!K:K,"ok") -> 0 | G6: =COUNTIFS('BD1'!C:C,Estadísticas!A6,'BD1'!H:H,Estadísticas!$G$3,'BD1'!K:K,"ok") -> 0 | H6: =COUNTIFS('BD1'!C:C,Estadísticas!A6,'BD1'!H:H,Estadísticas!$H$3,'BD1'!K:K,"ok") -> 1 | I6: =SUM(C6:H6) -> 3 | J6: =SUM(COUNTIFS('BD1'!C:C, Estadísticas!A6, 'BD1'!AE:AE,"7"),COUNTIFS('BD1'!C:C, Estadísticas!A6, 'BD1'!AE:AE,"6"),COUNTIFS('BD1'!C:C, Estadísticas!A6, 'BD1'!AE:AE,"5"),COUNTIFS('BD1'!C:C, Estadísticas!A6, 'BD1'!AE:AE,"4"),COUNTIFS('BD1'!C:C, Estadísticas!A6, 'BD1'!AE:AE,"3"),COUNTIFS('BD1'!C:C, Estadísticas!A6, 'BD1'!AE:AE,"2"),COUNTIFS('BD1'!C:C, Estadísticas!A6, 'BD1'!AE:AE,"1"),COUNTIFS('BD1'!C:C, Estadísticas!A6, 'BD1'!AE:AE,"0")) -> 1 | K6: =SUM(COUNTIFS('BD2'!C:C, Estadísticas!A6, 'BD2'!AE:AE,"7"),COUNTIFS('BD2'!C:C, Estadísticas!A6, 'BD2'!AE:AE,"6"),COUNTIFS('BD2'!C:C, Estadísticas!A6, 'BD2'!AE:AE,"5"),COUNTIFS('BD2'!C:C, Estadísticas!A6, 'BD2'!AE:AE,"4"),COUNTIFS('BD2'!C:C, Estadísticas!A6, 'BD2'!AE:AE,"3"),COUNTIFS('BD2'!C:C, Estadísticas!A6, 'BD2'!AE:AE,"2"),COUNTIFS('BD2'!C:C, Estadísticas!A6, 'BD2'!AE:AE,"1"),COUNTIFS('BD2'!C:C, Estadísticas!A6, 'BD2'!AE:AE,"0")) -> 2 | O6: =COUNTIF(Y:Y,O5) -> 75 | Q6: =COUNTIF(Y:Y,Q5) -> 192 | S6: =COUNTIF(Y:Y,S5) -> 147 | V6: 4 | W6: =VLOOKUP(V6,'BD1'!$A$2:$AF$1139,31,0) -> 8 | X6: =VLOOKUP(V6,'BD2'!$A$2:$AF$1139,31,0) -> 8 | Y6: =IF(X6>W6,"Mejoría",IF(X6<W6,"Pérdida","Se mantiene")) -> Se mantiene
A7: CENTRO DE INVESTIGACIÓN | C7: =COUNTIFS('BD1'!C:C,Estadísticas!A7,'BD1'!H:H,Estadísticas!$C$3,'BD1'!K:K,"ok") -> 1 | D7: =COUNTIFS('BD1'!C:C,Estadísticas!A7,'BD1'!H:H,Estadísticas!$D$3,'BD1'!K:K,"ok") -> 0 | E7: =COUNTIFS('BD1'!C:C,Estadísticas!A7,'BD1'!H:H,Estadísticas!$E$3,'BD1'!K:K,"ok") -> 1 | F7: =COUNTIFS('BD1'!C:C,Estadísticas!A7,'BD1'!H:H,Estadísticas!$F$3,'BD1'!K:K,"ok") -> 0 | G7: =COUNTIFS('BD1'!C:C,Estadísticas!A7,'BD1'!H:H,Estadísticas!$G$3,'BD1'!K:K,"ok") -> 0 | H7: =COUNTIFS('BD1'!C:C,Estadísticas!A7,'BD1'!H:H,Estadísticas!$H$3,'BD1'!K:K,"ok") -> 0 | I7: =SUM(C7:H7) -> 2 | J7: =SUM(COUNTIFS('BD1'!C:C, Estadísticas!A7, 'BD1'!AE:AE,"7"),COUNTIFS('BD1'!C:C, Estadísticas!A7, 'BD1'!AE:AE,"6"),COUNTIFS('BD1'!C:C, Estadísticas!A7, 'BD1'!AE:AE,"5"),COUNTIFS('BD1'!C:C, Estadísticas!A7, 'BD1'!AE:AE,"4"),COUNTIFS('BD1'!C:C, Estadísticas!A7, 'BD1'!AE:AE,"3"),COUNTIFS('BD1'!C:C, Estadísticas!A7, 'BD1'!AE:AE,"2"),COUNTIFS('BD1'!C:C, Estadísticas!A7, 'BD1'!AE:AE,"1"),COUNTIFS('BD1'!C:C, Estadísticas!A7, 'BD1'!AE:AE,"0")) -> 1 | K7: =SUM(COUNTIFS('BD2'!C:C, Estadísticas!A7, 'BD2'!AE:AE,"7"),COUNTIFS('BD2'!C:C, Estadísticas!A7, 'BD2'!AE:AE,"6"),COUNTIFS('BD2'!C:C, Estadísticas!A7, 'BD2'!AE:AE,"5"),COUNTIFS('BD2'!C:C, Estadísticas!A7, 'BD2'!AE:AE,"4"),COUNTIFS('BD2'!C:C, Estadísticas!A7, 'BD2'!AE:AE,"3"),COUNTIFS('BD2'!C:C, Estadísticas!A7, 'BD2'!AE:AE,"2"),COUNTIFS('BD2'!C:C, Estadísticas!A7, 'BD2'!AE:AE,"1"),COUNTIFS('BD2'!C:C, Estadísticas!A7, 'BD2'!AE:AE,"0")) -> 0 | V7: 5 | W7: =VLOOKUP(V7,'BD1'!$A$2:$AF$1139,31,0) -> 8 | X7: =VLOOKUP(V7,'BD2'!$A$2:$AF$1139,31,0) -> 8 | Y7: =IF(X7>W7,"Mejoría",IF(X7<W7,"Pérdida","Se mantiene")) -> Se mantiene
A8: ESCUELA | C8: =COUNTIFS('BD1'!C:C,Estadísticas!A8,'BD1'!H:H,Estadísticas!$C$3,'BD1'!K:K,"ok") -> 153 | D8: =COUNTIFS('BD1'!C:C,Estadísticas!A8,'BD1'!H:H,Estadísticas!$D$3,'BD1'!K:K,"ok") -> 0 | E8: =COUNTIFS('BD1'!C:C,Estadísticas!A8,'BD1'!H:H,Estadísticas!$E$3,'BD1'!K:K,"ok") -> 10 | F8: =COUNTIFS('BD1'!C:C,Estadísticas!A8,'BD1'!H:H,Estadísticas!$F$3,'BD1'!K:K,"ok") -> 12 | G8: =COUNTIFS('BD1'!C:C,Estadísticas!A8,'BD1'!H:H,Estadísticas!$G$3,'BD1'!K:K,"ok") -> 13 | H8: =COUNTIFS('BD1'!C:C,Estadísticas!A8,'BD1'!H:H,Estadísticas!$H$3,'BD1'!K:K,"ok") -> 4 | I8: =SUM(C8:H8) -> 192 | J8: =SUM(COUNTIFS('BD1'!C:C, Estadísticas!A8, 'BD1'!AE:AE,"7"),COUNTIFS('BD1'!C:C, Estadísticas!A8, 'BD1'!AE:AE,"6"),COUNTIFS('BD1'!C:C, Estadísticas!A8, 'BD1'!AE:AE,"5"),COUNTIFS('BD1'!C:C, Estadísticas!A8, 'BD1'!AE:AE,"4"),COUNTIFS('BD1'!C:C, Estadísticas!A8, 'BD1'!AE:AE,"3"),COUNTIFS('BD1'!C:C, Estadísticas!A8, 'BD1'!AE:AE,"2"),COUNTIFS('BD1'!C:C, Estadísticas!A8, 'BD1'!AE:AE,"1"),COUNTIFS('BD1'!C:C, Estadísticas!A8, 'BD1'!AE:AE,"0")) -> 64 | K8: =SUM(COUNTIFS('BD2'!C:C, Estadísticas!A8, 'BD2'!AE:AE,"7"),COUNTIFS('BD2'!C:C, Estadísticas!A8, 'BD2'!AE:AE,"6"),COUNTIFS('BD2'!C:C, Estadísticas!A8, 'BD2'!AE:AE,"5"),COUNTIFS('BD2'!C:C, Estadísticas!A8, 'BD2'!AE:AE,"4"),COUNTIFS('BD2'!C:C, Estadísticas!A8, 'BD2'!AE:AE,"3"),COUNTIFS('BD2'!C:C, Estadísticas!A8, 'BD2'!AE:AE,"2"),COUNTIFS('BD2'!C:C, Estadísticas!A8, 'BD2'!AE:AE,"1"),COUNTIFS('BD2'!C:C, Estadísticas!A8, 'BD2'!AE:AE,"0")) -> 76 | N8: Visita 1 | V8: 6 | W8: =VLOOKUP(V8,'BD1'!$A$2:$AF$1139,31,0) -> 8 | X8: =VLOOKUP(V8,'BD2'!$A$2:$AF$1139,31,0) -> 8 | Y8: =IF(X8>W8,"Mejoría",IF(X8<W8,"Pérdida","Se mantiene")) -> Se mantiene
A9: OFICINA GUBERNAMENTAL | C9: =COUNTIFS('BD1'!C:C,Estadísticas!A9,'BD1'!H:H,Estadísticas!$C$3,'BD1'!K:K,"ok") -> 10 | D9: =COUNTIFS('BD1'!C:C,Estadísticas!A9,'BD1'!H:H,Estadísticas!$D$3,'BD1'!K:K,"ok") -> 6 | E9: =COUNTIFS('BD1'!C:C,Estadísticas!A9,'BD1'!H:H,Estadísticas!$E$3,'BD1'!K:K,"ok") -> 11 | F9: =COUNTIFS('BD1'!C:C,Estadísticas!A9,'BD1'!H:H,Estadísticas!$F$3,'BD1'!K:K,"ok") -> 4 | G9: =COUNTIFS('BD1'!C:C,Estadísticas!A9,'BD1'!H:H,Estadísticas!$G$3,'BD1'!K:K,"ok") -> 3 | H9: =COUNTIFS('BD1'!C:C,Estadísticas!A9,'BD1'!H:H,Estadísticas!$H$3,'BD1'!K:K,"ok") -> 4 | I9: =SUM(C9:H9) -> 38 | J9: =SUM(COUNTIFS('BD1'!C:C, Estadísticas!A9, 'BD1'!AE:AE,"7"),COUNTIFS('BD1'!C:C, Estadísticas!A9, 'BD1'!AE:AE,"6"),COUNTIFS('BD1'!C:C, Estadísticas!A9, 'BD1'!AE:AE,"5"),COUNTIFS('BD1'!C:C, Estadísticas!A9, 'BD1'!AE:AE,"4"),COUNTIFS('BD1'!C:C, Estadísticas!A9, 'BD1'!AE:AE,"3"),COUNTIFS('BD1'!C:C, Estadísticas!A9, 'BD1'!AE:AE,"2"),COUNTIFS('BD1'!C:C, Estadísticas!A9, 'BD1'!AE:AE,"1"),COUNTIFS('BD1'!C:C, Estadísticas!A9, 'BD1'!AE:AE,"0")) -> 17 | K9: =SUM(COUNTIFS('BD2'!C:C, Estadísticas!A9, 'BD2'!AE:AE,"7"),COUNTIFS('BD2'!C:C, Estadísticas!A9, 'BD2'!AE:AE,"6"),COUNTIFS('BD2'!C:C, Estadísticas!A9, 'BD2'!AE:AE,"5"),COUNTIFS('BD2'!C:C, Estadísticas!A9, 'BD2'!AE:AE,"4"),COUNTIFS('BD2'!C:C, Estadísticas!A9, 'BD2'!AE:AE,"3"),COUNTIFS('BD2'!C:C, Estadísticas!A9, 'BD2'!AE:AE,"2"),COUNTIFS('BD2'!C:C, Estadísticas!A9, 'BD2'!AE:AE,"1"),COUNTIFS('BD2'!C:C, Estadísticas!A9, 'BD2'!AE:AE,"0")) -> 20 | N9: Estable | T9: =COUNTIF('BD1'!AF:AF,Estadísticas!N9) -> 303 | V9: 7 | W9: =VLOOKUP(V9,'BD1'!$A$2:$AF$1139,31,0) -> 8 | X9: =VLOOKUP(V9,'BD2'!$A$2:$AF$1139,31,0) -> 0 | Y9: =IF(X9>W9,"Mejoría",IF(X9<W9,"Pérdida","Se mantiene")) -> Pérdida
A10: SECTOR SALUD | C10: =COUNTIFS('BD1'!C:C,Estadísticas!A10,'BD1'!H:H,Estadísticas!$C$3,'BD1'!K:K,"ok") -> 28 | D10: =COUNTIFS('BD1'!C:C,Estadísticas!A10,'BD1'!H:H,Estadísticas!$D$3,'BD1'!K:K,"ok") -> 0 | E10: =COUNTIFS('BD1'!C:C,Estadísticas!A10,'BD1'!H:H,Estadísticas!$E$3,'BD1'!K:K,"ok") -> 7 | F10: =COUNTIFS('BD1'!C:C,Estadísticas!A10,'BD1'!H:H,Estadísticas!$F$3,'BD1'!K:K,"ok") -> 4 | G10: =COUNTIFS('BD1'!C:C,Estadísticas!A10,'BD1'!H:H,Estadísticas!$G$3,'BD1'!K:K,"ok") -> 2 | H10: =COUNTIFS('BD1'!C:C,Estadísticas!A10,'BD1'!H:H,Estadísticas!$H$3,'BD1'!K:K,"ok") -> 0 | I10: =SUM(C10:H10) -> 41 | J10: =SUM(COUNTIFS('BD1'!C:C, Estadísticas!A10, 'BD1'!AE:AE,"7"),COUNTIFS('BD1'!C:C, Estadísticas!A10, 'BD1'!AE:AE,"6"),COUNTIFS('BD1'!C:C, Estadísticas!A10, 'BD1'!AE:AE,"5"),COUNTIFS('BD1'!C:C, Estadísticas!A10, 'BD1'!AE:AE,"4"),COUNTIFS('BD1'!C:C, Estadísticas!A10, 'BD1'!AE:AE,"3"),COUNTIFS('BD1'!C:C, Estadísticas!A10, 'BD1'!AE:AE,"2"),COUNTIFS('BD1'!C:C, Estadísticas!A10, 'BD1'!AE:AE,"1"),COUNTIFS('BD1'!C:C, Estadísticas!A10, 'BD1'!AE:AE,"0")) -> 8 | K10: =SUM(COUNTIFS('BD2'!C:C, Estadísticas!A10, 'BD2'!AE:AE,"7"),COUNTIFS('BD2'!C:C, Estadísticas!A10, 'BD2'!AE:AE,"6"),COUNTIFS('BD2'!C:C, Estadísticas!A10, 'BD2'!AE:AE,"5"),COUNTIFS('BD2'!C:C, Estadísticas!A10, 'BD2'!AE:AE,"4"),COUNTIFS('BD2'!C:C, Estadísticas!A10, 'BD2'!AE:AE,"3"),COUNTIFS('BD2'!C:C, Estadísticas!A10, 'BD2'!AE:AE,"2"),COUNTIFS('BD2'!C:C, Estadísticas!A10, 'BD2'!AE:AE,"1"),COUNTIFS('BD2'!C:C, Estadísticas!A10, 'BD2'!AE:AE,"0")) -> 12 | N10: Funcional con observaciones | T10: =COUNTIF('BD1'!AF:AF,Estadísticas!N10) -> 76 | V10: 8 | W10: =VLOOKUP(V10,'BD1'!$A$2:$AF$1139,31,0) -> 8 | X10: =VLOOKUP(V10,'BD2'!$A$2:$AF$1139,31,0) -> 8 | Y10: =IF(X10>W10,"Mejoría",IF(X10<W10,"Pérdida","Se mantiene")) -> Se mantiene
A11: FARMACIA | C11: =COUNTIFS('BD1'!C:C,Estadísticas!A11,'BD1'!H:H,Estadísticas!$C$3,'BD1'!K:K,"ok") -> 0 | D11: =COUNTIFS('BD1'!C:C,Estadísticas!A11,'BD1'!H:H,Estadísticas!$D$3,'BD1'!K:K,"ok") -> 0 | E11: =COUNTIFS('BD1'!C:C,Estadísticas!A11,'BD1'!H:H,Estadísticas!$E$3,'BD1'!K:K,"ok") -> 1 | F11: =COUNTIFS('BD1'!C:C,Estadísticas!A11,'BD1'!H:H,Estadísticas!$F$3,'BD1'!K:K,"ok") -> 0 | G11: =COUNTIFS('BD1'!C:C,Estadísticas!A11,'BD1'!H:H,Estadísticas!$G$3,'BD1'!K:K,"ok") -> 2 | H11: =COUNTIFS('BD1'!C:C,Estadísticas!A11,'BD1'!H:H,Estadísticas!$H$3,'BD1'!K:K,"ok") -> 0 | I11: =SUM(C11:H11) -> 3 | J11: =SUM(COUNTIFS('BD1'!C:C, Estadísticas!A11, 'BD1'!AE:AE,"7"),COUNTIFS('BD1'!C:C, Estadísticas!A11, 'BD1'!AE:AE,"6"),COUNTIFS('BD1'!C:C, Estadísticas!A11, 'BD1'!AE:AE,"5"),COUNTIFS('BD1'!C:C, Estadísticas!A11, 'BD1'!AE:AE,"4"),COUNTIFS('BD1'!C:C, Estadísticas!A11, 'BD1'!AE:AE,"3"),COUNTIFS('BD1'!C:C, Estadísticas!A11, 'BD1'!AE:AE,"2"),COUNTIFS('BD1'!C:C, Estadísticas!A11, 'BD1'!AE:AE,"1"),COUNTIFS('BD1'!C:C, Estadísticas!A11, 'BD1'!AE:AE,"0")) -> 2 | K11: =SUM(COUNTIFS('BD2'!C:C, Estadísticas!A11, 'BD2'!AE:AE,"7"),COUNTIFS('BD2'!C:C, Estadísticas!A11, 'BD2'!AE:AE,"6"),COUNTIFS('BD2'!C:C, Estadísticas!A11, 'BD2'!AE:AE,"5"),COUNTIFS('BD2'!C:C, Estadísticas!A11, 'BD2'!AE:AE,"4"),COUNTIFS('BD2'!C:C, Estadísticas!A11, 'BD2'!AE:AE,"3"),COUNTIFS('BD2'!C:C, Estadísticas!A11, 'BD2'!AE:AE,"2"),COUNTIFS('BD2'!C:C, Estadísticas!A11, 'BD2'!AE:AE,"1"),COUNTIFS('BD2'!C:C, Estadísticas!A11, 'BD2'!AE:AE,"0")) -> 1 | N11: Rendimiento bajo | T11: =COUNTIF('BD1'!AF:AF,Estadísticas!N11) -> 7 | V11: 9 | W11: =VLOOKUP(V11,'BD1'!$A$2:$AF$1139,31,0) -> 7 | X11: =VLOOKUP(V11,'BD2'!$A$2:$AF$1139,31,0) -> 8 | Y11: =IF(X11>W11,"Mejoría",IF(X11<W11,"Pérdida","Se mantiene")) -> Mejoría
A12: SECUNDARIA | C12: =COUNTIFS('BD1'!C:C,Estadísticas!A12,'BD1'!H:H,Estadísticas!$C$3,'BD1'!K:K,"ok") -> 0 | D12: =COUNTIFS('BD1'!C:C,Estadísticas!A12,'BD1'!H:H,Estadísticas!$D$3,'BD1'!K:K,"ok") -> 5 | E12: =COUNTIFS('BD1'!C:C,Estadísticas!A12,'BD1'!H:H,Estadísticas!$E$3,'BD1'!K:K,"ok") -> 0 | F12: =COUNTIFS('BD1'!C:C,Estadísticas!A12,'BD1'!H:H,Estadísticas!$F$3,'BD1'!K:K,"ok") -> 0 | G12: =COUNTIFS('BD1'!C:C,Estadísticas!A12,'BD1'!H:H,Estadísticas!$G$3,'BD1'!K:K,"ok") -> 0 | H12: =COUNTIFS('BD1'!C:C,Estadísticas!A12,'BD1'!H:H,Estadísticas!$H$3,'BD1'!K:K,"ok") -> 0 | I12: =SUM(C12:H12) -> 5 | J12: =SUM(COUNTIFS('BD1'!C:C, Estadísticas!A12, 'BD1'!AE:AE,"7"),COUNTIFS('BD1'!C:C, Estadísticas!A12, 'BD1'!AE:AE,"6"),COUNTIFS('BD1'!C:C, Estadísticas!A12, 'BD1'!AE:AE,"5"),COUNTIFS('BD1'!C:C, Estadísticas!A12, 'BD1'!AE:AE,"4"),COUNTIFS('BD1'!C:C, Estadísticas!A12, 'BD1'!AE:AE,"3"),COUNTIFS('BD1'!C:C, Estadísticas!A12, 'BD1'!AE:AE,"2"),COUNTIFS('BD1'!C:C, Estadísticas!A12, 'BD1'!AE:AE,"1"),COUNTIFS('BD1'!C:C, Estadísticas!A12, 'BD1'!AE:AE,"0")) -> 2 | K12: =SUM(COUNTIFS('BD2'!C:C, Estadísticas!A12, 'BD2'!AE:AE,"7"),COUNTIFS('BD2'!C:C, Estadísticas!A12, 'BD2'!AE:AE,"6"),COUNTIFS('BD2'!C:C, Estadísticas!A12, 'BD2'!AE:AE,"5"),COUNTIFS('BD2'!C:C, Estadísticas!A12, 'BD2'!AE:AE,"4"),COUNTIFS('BD2'!C:C, Estadísticas!A12, 'BD2'!AE:AE,"3"),COUNTIFS('BD2'!C:C, Estadísticas!A12, 'BD2'!AE:AE,"2"),COUNTIFS('BD2'!C:C, Estadísticas!A12, 'BD2'!AE:AE,"1"),COUNTIFS('BD2'!C:C, Estadísticas!A12, 'BD2'!AE:AE,"0")) -> 5 | N12: Parcialmente funcional | T12: =COUNTIF('BD1'!AF:AF,Estadísticas!N12) -> 10 | V12: 10 | W12: =VLOOKUP(V12,'BD1'!$A$2:$AF$1139,31,0) -> 8 | X12: =VLOOKUP(V12,'BD2'!$A$2:$AF$1139,31,0) -> 8 | Y12: =IF(X12>W12,"Mejoría",IF(X12<W12,"Pérdida","Se mantiene")) -> Se mantiene
A13: PREESCOLAR | C13: =COUNTIFS('BD1'!C:C,Estadísticas!A13,'BD1'!H:H,Estadísticas!$C$3,'BD1'!K:K,"ok") -> 0 | D13: =COUNTIFS('BD1'!C:C,Estadísticas!A13,'BD1'!H:H,Estadísticas!$D$3,'BD1'!K:K,"ok") -> 9 | E13: =COUNTIFS('BD1'!C:C,Estadísticas!A13,'BD1'!H:H,Estadísticas!$E$3,'BD1'!K:K,"ok") -> 0 | F13: =COUNTIFS('BD1'!C:C,Estadísticas!A13,'BD1'!H:H,Estadísticas!$F$3,'BD1'!K:K,"ok") -> 0 | G13: =COUNTIFS('BD1'!C:C,Estadísticas!A13,'BD1'!H:H,Estadísticas!$G$3,'BD1'!K:K,"ok") -> 0 | H13: =COUNTIFS('BD1'!C:C,Estadísticas!A13,'BD1'!H:H,Estadísticas!$H$3,'BD1'!K:K,"ok") -> 0 | I13: =SUM(C13:H13) -> 9 | J13: =SUM(COUNTIFS('BD1'!C:C, Estadísticas!A13, 'BD1'!AE:AE,"7"),COUNTIFS('BD1'!C:C, Estadísticas!A13, 'BD1'!AE:AE,"6"),COUNTIFS('BD1'!C:C, Estadísticas!A13, 'BD1'!AE:AE,"5"),COUNTIFS('BD1'!C:C, Estadísticas!A13, 'BD1'!AE:AE,"4"),COUNTIFS('BD1'!C:C, Estadísticas!A13, 'BD1'!AE:AE,"3"),COUNTIFS('BD1'!C:C, Estadísticas!A13, 'BD1'!AE:AE,"2"),COUNTIFS('BD1'!C:C, Estadísticas!A13, 'BD1'!AE:AE,"1"),COUNTIFS('BD1'!C:C, Estadísticas!A13, 'BD1'!AE:AE,"0")) -> 3 | K13: =SUM(COUNTIFS('BD2'!C:C, Estadísticas!A13, 'BD2'!AE:AE,"7"),COUNTIFS('BD2'!C:C, Estadísticas!A13, 'BD2'!AE:AE,"6"),COUNTIFS('BD2'!C:C, Estadísticas!A13, 'BD2'!AE:AE,"5"),COUNTIFS('BD2'!C:C, Estadísticas!A13, 'BD2'!AE:AE,"4"),COUNTIFS('BD2'!C:C, Estadísticas!A13, 'BD2'!AE:AE,"3"),COUNTIFS('BD2'!C:C, Estadísticas!A13, 'BD2'!AE:AE,"2"),COUNTIFS('BD2'!C:C, Estadísticas!A13, 'BD2'!AE:AE,"1"),COUNTIFS('BD2'!C:C, Estadísticas!A13, 'BD2'!AE:AE,"0")) -> 9 | N13: Inoperativo | T13: =COUNTIF('BD1'!AF:AF,Estadísticas!N13) -> 2 | V13: 11 | W13: =VLOOKUP(V13,'BD1'!$A$2:$AF$1139,31,0) -> 8 | X13: =VLOOKUP(V13,'BD2'!$A$2:$AF$1139,31,0) -> 8 | Y13: =IF(X13>W13,"Mejoría",IF(X13<W13,"Pérdida","Se mantiene")) -> Se mantiene
A14: PRIMARIA | C14: =COUNTIFS('BD1'!C:C,Estadísticas!A14,'BD1'!H:H,Estadísticas!$C$3,'BD1'!K:K,"ok") -> 0 | D14: =COUNTIFS('BD1'!C:C,Estadísticas!A14,'BD1'!H:H,Estadísticas!$D$3,'BD1'!K:K,"ok") -> 14 | E14: =COUNTIFS('BD1'!C:C,Estadísticas!A14,'BD1'!H:H,Estadísticas!$E$3,'BD1'!K:K,"ok") -> 0 | F14: =COUNTIFS('BD1'!C:C,Estadísticas!A14,'BD1'!H:H,Estadísticas!$F$3,'BD1'!K:K,"ok") -> 0 | G14: =COUNTIFS('BD1'!C:C,Estadísticas!A14,'BD1'!H:H,Estadísticas!$G$3,'BD1'!K:K,"ok") -> 0 | H14: =COUNTIFS('BD1'!C:C,Estadísticas!A14,'BD1'!H:H,Estadísticas!$H$3,'BD1'!K:K,"ok") -> 0 | I14: =SUM(C14:H14) -> 14 | J14: =SUM(COUNTIFS('BD1'!C:C, Estadísticas!A14, 'BD1'!AE:AE,"7"),COUNTIFS('BD1'!C:C, Estadísticas!A14, 'BD1'!AE:AE,"6"),COUNTIFS('BD1'!C:C, Estadísticas!A14, 'BD1'!AE:AE,"5"),COUNTIFS('BD1'!C:C, Estadísticas!A14, 'BD1'!AE:AE,"4"),COUNTIFS('BD1'!C:C, Estadísticas!A14, 'BD1'!AE:AE,"3"),COUNTIFS('BD1'!C:C, Estadísticas!A14, 'BD1'!AE:AE,"2"),COUNTIFS('BD1'!C:C, Estadísticas!A14, 'BD1'!AE:AE,"1"),COUNTIFS('BD1'!C:C, Estadísticas!A14, 'BD1'!AE:AE,"0")) -> 4 | K14: =SUM(COUNTIFS('BD2'!C:C, Estadísticas!A14, 'BD2'!AE:AE,"7"),COUNTIFS('BD2'!C:C, Estadísticas!A14, 'BD2'!AE:AE,"6"),COUNTIFS('BD2'!C:C, Estadísticas!A14, 'BD2'!AE:AE,"5"),COUNTIFS('BD2'!C:C, Estadísticas!A14, 'BD2'!AE:AE,"4"),COUNTIFS('BD2'!C:C, Estadísticas!A14, 'BD2'!AE:AE,"3"),COUNTIFS('BD2'!C:C, Estadísticas!A14, 'BD2'!AE:AE,"2"),COUNTIFS('BD2'!C:C, Estadísticas!A14, 'BD2'!AE:AE,"1"),COUNTIFS('BD2'!C:C, Estadísticas!A14, 'BD2'!AE:AE,"0")) -> 14 | N14: Crítico | T14: =COUNTIF('BD1'!AF:AF,Estadísticas!N14) -> 20 | V14: 12 | W14: =VLOOKUP(V14,'BD1'!$A$2:$AF$1139,31,0) -> 8 | X14: =VLOOKUP(V14,'BD2'!$A$2:$AF$1139,31,0) -> 8 | Y14: =IF(X14>W14,"Mejoría",IF(X14<W14,"Pérdida","Se mantiene")) -> Se mantiene
A15: ESPACIO CULTURAL | C15: =COUNTIFS('BD1'!C:C,Estadísticas!A15,'BD1'!H:H,Estadísticas!$C$3,'BD1'!K:K,"ok") -> 0 | D15: =COUNTIFS('BD1'!C:C,Estadísticas!A15,'BD1'!H:H,Estadísticas!$D$3,'BD1'!K:K,"ok") -> 2 | E15: =COUNTIFS('BD1'!C:C,Estadísticas!A15,'BD1'!H:H,Estadísticas!$E$3,'BD1'!K:K,"ok") -> 0 | F15: =COUNTIFS('BD1'!C:C,Estadísticas!A15,'BD1'!H:H,Estadísticas!$F$3,'BD1'!K:K,"ok") -> 0 | G15: =COUNTIFS('BD1'!C:C,Estadísticas!A15,'BD1'!H:H,Estadísticas!$G$3,'BD1'!K:K,"ok") -> 0 | H15: =COUNTIFS('BD1'!C:C,Estadísticas!A15,'BD1'!H:H,Estadísticas!$H$3,'BD1'!K:K,"ok") -> 0 | I15: =SUM(C15:H15) -> 2 | J15: =SUM(COUNTIFS('BD1'!C:C, Estadísticas!A15, 'BD1'!AE:AE,"7"),COUNTIFS('BD1'!C:C, Estadísticas!A15, 'BD1'!AE:AE,"6"),COUNTIFS('BD1'!C:C, Estadísticas!A15, 'BD1'!AE:AE,"5"),COUNTIFS('BD1'!C:C, Estadísticas!A15, 'BD1'!AE:AE,"4"),COUNTIFS('BD1'!C:C, Estadísticas!A15, 'BD1'!AE:AE,"3"),COUNTIFS('BD1'!C:C, Estadísticas!A15, 'BD1'!AE:AE,"2"),COUNTIFS('BD1'!C:C, Estadísticas!A15, 'BD1'!AE:AE,"1"),COUNTIFS('BD1'!C:C, Estadísticas!A15, 'BD1'!AE:AE,"0")) -> 1 | K15: =SUM(COUNTIFS('BD2'!C:C, Estadísticas!A15, 'BD2'!AE:AE,"7"),COUNTIFS('BD2'!C:C, Estadísticas!A15, 'BD2'!AE:AE,"6"),COUNTIFS('BD2'!C:C, Estadísticas!A15, 'BD2'!AE:AE,"5"),COUNTIFS('BD2'!C:C, Estadísticas!A15, 'BD2'!AE:AE,"4"),COUNTIFS('BD2'!C:C, Estadísticas!A15, 'BD2'!AE:AE,"3"),COUNTIFS('BD2'!C:C, Estadísticas!A15, 'BD2'!AE:AE,"2"),COUNTIFS('BD2'!C:C, Estadísticas!A15, 'BD2'!AE:AE,"1"),COUNTIFS('BD2'!C:C, Estadísticas!A15, 'BD2'!AE:AE,"0")) -> 2 | V15: 13a | W15: =VLOOKUP(V15,'BD1'!$A$2:$AF$1139,31,0) -> 8 | X15: =VLOOKUP(V15,'BD2'!$A$2:$AF$1139,31,0) -> 8 | Y15: =IF(X15>W15,"Mejoría",IF(X15<W15,"Pérdida","Se mantiene")) -> Se mantiene
A16: CENTRO DE CAPACITACIÓN | C16: =COUNTIFS('BD1'!C:C,Estadísticas!A16,'BD1'!H:H,Estadísticas!$C$3,'BD1'!K:K,"ok") -> 0 | D16: =COUNTIFS('BD1'!C:C,Estadísticas!A16,'BD1'!H:H,Estadísticas!$D$3,'BD1'!K:K,"ok") -> 0 | E16: =COUNTIFS('BD1'!C:C,Estadísticas!A16,'BD1'!H:H,Estadísticas!$E$3,'BD1'!K:K,"ok") -> 0 | F16: =COUNTIFS('BD1'!C:C,Estadísticas!A16,'BD1'!H:H,Estadísticas!$F$3,'BD1'!K:K,"ok") -> 0 | G16: =COUNTIFS('BD1'!C:C,Estadísticas!A16,'BD1'!H:H,Estadísticas!$G$3,'BD1'!K:K,"ok") -> 0 | H16: =COUNTIFS('BD1'!C:C,Estadísticas!A16,'BD1'!H:H,Estadísticas!$H$3,'BD1'!K:K,"ok") -> 0 | I16: =SUM(C16:H16) -> 0 | J16: =SUM(COUNTIFS('BD1'!C:C, Estadísticas!A16, 'BD1'!AE:AE,"7"),COUNTIFS('BD1'!C:C, Estadísticas!A16, 'BD1'!AE:AE,"6"),COUNTIFS('BD1'!C:C, Estadísticas!A16, 'BD1'!AE:AE,"5"),COUNTIFS('BD1'!C:C, Estadísticas!A16, 'BD1'!AE:AE,"4"),COUNTIFS('BD1'!C:C, Estadísticas!A16, 'BD1'!AE:AE,"3"),COUNTIFS('BD1'!C:C, Estadísticas!A16, 'BD1'!AE:AE,"2"),COUNTIFS('BD1'!C:C, Estadísticas!A16, 'BD1'!AE:AE,"1"),COUNTIFS('BD1'!C:C, Estadísticas!A16, 'BD1'!AE:AE,"0")) -> 0 | K16: =SUM(COUNTIFS('BD2'!C:C, Estadísticas!A16, 'BD2'!AE:AE,"7"),COUNTIFS('BD2'!C:C, Estadísticas!A16, 'BD2'!AE:AE,"6"),COUNTIFS('BD2'!C:C, Estadísticas!A16, 'BD2'!AE:AE,"5"),COUNTIFS('BD2'!C:C, Estadísticas!A16, 'BD2'!AE:AE,"4"),COUNTIFS('BD2'!C:C, Estadísticas!A16, 'BD2'!AE:AE,"3"),COUNTIFS('BD2'!C:C, Estadísticas!A16, 'BD2'!AE:AE,"2"),COUNTIFS('BD2'!C:C, Estadísticas!A16, 'BD2'!AE:AE,"1"),COUNTIFS('BD2'!C:C, Estadísticas!A16, 'BD2'!AE:AE,"0")) -> 0 | N16: Visita 2 | V16: 13b | W16: =VLOOKUP(V16,'BD1'!$A$2:$AF$1139,31,0) -> 7 | X16: =VLOOKUP(V16,'BD2'!$A$2:$AF$1139,31,0) -> 8 | Y16: =IF(X16>W16,"Mejoría",IF(X16<W16,"Pérdida","Se mantiene")) -> Mejoría
A17: SUPERIOR | C17: =COUNTIFS('BD1'!C:C,Estadísticas!A17,'BD1'!H:H,Estadísticas!$C$3,'BD1'!K:K,"ok") -> 0 | D17: =COUNTIFS('BD1'!C:C,Estadísticas!A17,'BD1'!H:H,Estadísticas!$D$3,'BD1'!K:K,"ok") -> 0 | E17: =COUNTIFS('BD1'!C:C,Estadísticas!A17,'BD1'!H:H,Estadísticas!$E$3,'BD1'!K:K,"ok") -> 0 | F17: =COUNTIFS('BD1'!C:C,Estadísticas!A17,'BD1'!H:H,Estadísticas!$F$3,'BD1'!K:K,"ok") -> 0 | G17: =COUNTIFS('BD1'!C:C,Estadísticas!A17,'BD1'!H:H,Estadísticas!$G$3,'BD1'!K:K,"ok") -> 0 | H17: =COUNTIFS('BD1'!C:C,Estadísticas!A17,'BD1'!H:H,Estadísticas!$H$3,'BD1'!K:K,"ok") -> 0 | I17: =SUM(C17:H17) -> 0 | J17: =SUM(COUNTIFS('BD1'!C:C, Estadísticas!A17, 'BD1'!AE:AE,"7"),COUNTIFS('BD1'!C:C, Estadísticas!A17, 'BD1'!AE:AE,"6"),COUNTIFS('BD1'!C:C, Estadísticas!A17, 'BD1'!AE:AE,"5"),COUNTIFS('BD1'!C:C, Estadísticas!A17, 'BD1'!AE:AE,"4"),COUNTIFS('BD1'!C:C, Estadísticas!A17, 'BD1'!AE:AE,"3"),COUNTIFS('BD1'!C:C, Estadísticas!A17, 'BD1'!AE:AE,"2"),COUNTIFS('BD1'!C:C, Estadísticas!A17, 'BD1'!AE:AE,"1"),COUNTIFS('BD1'!C:C, Estadísticas!A17, 'BD1'!AE:AE,"0")) -> 0 | K17: =SUM(COUNTIFS('BD2'!C:C, Estadísticas!A17, 'BD2'!AE:AE,"7"),COUNTIFS('BD2'!C:C, Estadísticas!A17, 'BD2'!AE:AE,"6"),COUNTIFS('BD2'!C:C, Estadísticas!A17, 'BD2'!AE:AE,"5"),COUNTIFS('BD2'!C:C, Estadísticas!A17, 'BD2'!AE:AE,"4"),COUNTIFS('BD2'!C:C, Estadísticas!A17, 'BD2'!AE:AE,"3"),COUNTIFS('BD2'!C:C, Estadísticas!A17, 'BD2'!AE:AE,"2"),COUNTIFS('BD2'!C:C, Estadísticas!A17, 'BD2'!AE:AE,"1"),COUNTIFS('BD2'!C:C, Estadísticas!A17, 'BD2'!AE:AE,"0")) -> 0 | N17: Estable | T17: =COUNTIF('BD2'!AF:AF,Estadísticas!N17) -> 226 | V17: 14 | W17: =VLOOKUP(V17,'BD1'!$A$2:$AF$1139,31,0) -> 8 | X17: =VLOOKUP(V17,'BD2'!$A$2:$AF$1139,31,0) -> 8 | Y17: =IF(X17>W17,"Mejoría",IF(X17<W17,"Pérdida","Se mantiene")) -> Se mantiene
A18: MEDIA SUPERIOR | C18: =COUNTIFS('BD1'!C:C,Estadísticas!A18,'BD1'!H:H,Estadísticas!$C$3,'BD1'!K:K,"ok") -> 0 | D18: =COUNTIFS('BD1'!C:C,Estadísticas!A18,'BD1'!H:H,Estadísticas!$D$3,'BD1'!K:K,"ok") -> 0 | E18: =COUNTIFS('BD1'!C:C,Estadísticas!A18,'BD1'!H:H,Estadísticas!$E$3,'BD1'!K:K,"ok") -> 0 | F18: =COUNTIFS('BD1'!C:C,Estadísticas!A18,'BD1'!H:H,Estadísticas!$F$3,'BD1'!K:K,"ok") -> 0 | G18: =COUNTIFS('BD1'!C:C,Estadísticas!A18,'BD1'!H:H,Estadísticas!$G$3,'BD1'!K:K,"ok") -> 0 | H18: =COUNTIFS('BD1'!C:C,Estadísticas!A18,'BD1'!H:H,Estadísticas!$H$3,'BD1'!K:K,"ok") -> 0 | I18: =SUM(C18:H18) -> 0 | J18: =SUM(COUNTIFS('BD1'!C:C, Estadísticas!A18, 'BD1'!AE:AE,"7"),COUNTIFS('BD1'!C:C, Estadísticas!A18, 'BD1'!AE:AE,"6"),COUNTIFS('BD1'!C:C, Estadísticas!A18, 'BD1'!AE:AE,"5"),COUNTIFS('BD1'!C:C, Estadísticas!A18, 'BD1'!AE:AE,"4"),COUNTIFS('BD1'!C:C, Estadísticas!A18, 'BD1'!AE:AE,"3"),COUNTIFS('BD1'!C:C, Estadísticas!A18, 'BD1'!AE:AE,"2"),COUNTIFS('BD1'!C:C, Estadísticas!A18, 'BD1'!AE:AE,"1"),COUNTIFS('BD1'!C:C, Estadísticas!A18, 'BD1'!AE:AE,"0")) -> 0 | K18: =SUM(COUNTIFS('BD2'!C:C, Estadísticas!A18, 'BD2'!AE:AE,"7"),COUNTIFS('BD2'!C:C, Estadísticas!A18, 'BD2'!AE:AE,"6"),COUNTIFS('BD2'!C:C, Estadísticas!A18, 'BD2'!AE:AE,"5"),COUNTIFS('BD2'!C:C, Estadísticas!A18, 'BD2'!AE:AE,"4"),COUNTIFS('BD2'!C:C, Estadísticas!A18, 'BD2'!AE:AE,"3"),COUNTIFS('BD2'!C:C, Estadísticas!A18, 'BD2'!AE:AE,"2"),COUNTIFS('BD2'!C:C, Estadísticas!A18, 'BD2'!AE:AE,"1"),COUNTIFS('BD2'!C:C, Estadísticas!A18, 'BD2'!AE:AE,"0")) -> 0 | N18: Funcional con observaciones | T18: =COUNTIF('BD2'!AF:AF,Estadísticas!N18) -> 135 | V18: 15 | W18: =VLOOKUP(V18,'BD1'!$A$2:$AF$1139,31,0) -> 8 | X18: =VLOOKUP(V18,'BD2'!$A$2:$AF$1139,31,0) -> 8 | Y18: =IF(X18>W18,"Mejoría",IF(X18<W18,"Pérdida","Se mantiene")) -> Se mantiene
A19: ESTACIONAMIENTO | C19: =COUNTIFS('BD1'!C:C,Estadísticas!A19,'BD1'!H:H,Estadísticas!$C$3,'BD1'!K:K,"ok") -> 0 | D19: =COUNTIFS('BD1'!C:C,Estadísticas!A19,'BD1'!H:H,Estadísticas!$D$3,'BD1'!K:K,"ok") -> 0 | E19: =COUNTIFS('BD1'!C:C,Estadísticas!A19,'BD1'!H:H,Estadísticas!$E$3,'BD1'!K:K,"ok") -> 0 | F19: =COUNTIFS('BD1'!C:C,Estadísticas!A19,'BD1'!H:H,Estadísticas!$F$3,'BD1'!K:K,"ok") -> 0 | G19: =COUNTIFS('BD1'!C:C,Estadísticas!A19,'BD1'!H:H,Estadísticas!$G$3,'BD1'!K:K,"ok") -> 0 | H19: =COUNTIFS('BD1'!C:C,Estadísticas!A19,'BD1'!H:H,Estadísticas!$H$3,'BD1'!K:K,"ok") -> 1 | I19: =SUM(C19:H19) -> 1 | J19: =SUM(COUNTIFS('BD1'!C:C, Estadísticas!A19, 'BD1'!AE:AE,"7"),COUNTIFS('BD1'!C:C, Estadísticas!A19, 'BD1'!AE:AE,"6"),COUNTIFS('BD1'!C:C, Estadísticas!A19, 'BD1'!AE:AE,"5"),COUNTIFS('BD1'!C:C, Estadísticas!A19, 'BD1'!AE:AE,"4"),COUNTIFS('BD1'!C:C, Estadísticas!A19, 'BD1'!AE:AE,"3"),COUNTIFS('BD1'!C:C, Estadísticas!A19, 'BD1'!AE:AE,"2"),COUNTIFS('BD1'!C:C, Estadísticas!A19, 'BD1'!AE:AE,"1"),COUNTIFS('BD1'!C:C, Estadísticas!A19, 'BD1'!AE:AE,"0")) -> 0 | K19: =SUM(COUNTIFS('BD2'!C:C, Estadísticas!A19, 'BD2'!AE:AE,"7"),COUNTIFS('BD2'!C:C, Estadísticas!A19, 'BD2'!AE:AE,"6"),COUNTIFS('BD2'!C:C, Estadísticas!A19, 'BD2'!AE:AE,"5"),COUNTIFS('BD2'!C:C, Estadísticas!A19, 'BD2'!AE:AE,"4"),COUNTIFS('BD2'!C:C, Estadísticas!A19, 'BD2'!AE:AE,"3"),COUNTIFS('BD2'!C:C, Estadísticas!A19, 'BD2'!AE:AE,"2"),COUNTIFS('BD2'!C:C, Estadísticas!A19, 'BD2'!AE:AE,"1"),COUNTIFS('BD2'!C:C, Estadísticas!A19, 'BD2'!AE:AE,"0")) -> 0 | N19: Rendimiento bajo | T19: =COUNTIF('BD2'!AF:AF,Estadísticas!N19) -> 4 | V19: 16 | W19: =VLOOKUP(V19,'BD1'!$A$2:$AF$1139,31,0) -> 8 | X19: =VLOOKUP(V19,'BD2'!$A$2:$AF$1139,31,0) -> 8 | Y19: =IF(X19>W19,"Mejoría",IF(X19<W19,"Pérdida","Se mantiene")) -> Se mantiene
C20: =SUM(C4:C19) -> 212 | D20: =SUM(D4:D19) -> 47 | E20: =SUM(E4:E19) -> 51 | F20: =SUM(F4:F19) -> 53 | G20: =SUM(G4:G19) -> 20 | H20: =SUM(H4:H19) -> 25 | I20: =SUM(I4:I19) -> 408 | N20: Parcialmente funcional | T20: =COUNTIF('BD2'!AF:AF,Estadísticas!N20) -> 19 | V20: 89 | W20: =VLOOKUP(V20,'BD1'!$A$2:$AF$1139,31,0) -> 6 | X20: =VLOOKUP(V20,'BD2'!$A$2:$AF$1139,31,0) -> 8 | Y20: =IF(X20>W20,"Mejoría",IF(X20<W20,"Pérdida","Se mantiene")) -> Mejoría
N21: Inoperativo | T21: =COUNTIF('BD2'!AF:AF,Estadísticas!N21) -> 10 | V21: 92 | W21: =VLOOKUP(V21,'BD1'!$A$2:$AF$1139,31,0) -> 8 | X21: =VLOOKUP(V21,'BD2'!$A$2:$AF$1139,31,0) -> 8 | Y21: =IF(X21>W21,"Mejoría",IF(X21<W21,"Pérdida","Se mantiene")) -> Se mantiene
A22: Hay 9 sitios que no cuentan con video dando un total de 417 sitios con reporte | N22: Crítico | T22: =COUNTIF('BD2'!AF:AF,Estadísticas!N22) -> 24 | V22: 96 | W22: =VLOOKUP(V22,'BD1'!$A$2:$AF$1139,31,0) -> 8 | X22: =VLOOKUP(V22,'BD2'!$A$2:$AF$1139,31,0) -> 8 | Y22: =IF(X22>W22,"Mejoría",IF(X22<W22,"Pérdida","Se mantiene")) -> Se mantiene
V23: 101 | W23: =VLOOKUP(V23,'BD1'!$A$2:$AF$1139,31,0) -> 7 | X23: =VLOOKUP(V23,'BD2'!$A$2:$AF$1139,31,0) -> 8 | Y23: =IF(X23>W23,"Mejoría",IF(X23<W23,"Pérdida","Se mantiene")) -> Mejoría
A24: Comparación de error en la primer y segunda visita | V24: 102 | W24: =VLOOKUP(V24,'BD1'!$A$2:$AF$1139,31,0) -> 5 | X24: =VLOOKUP(V24,'BD2'!$A$2:$AF$1139,31,0) -> 7 | Y24: =IF(X24>W24,"Mejoría",IF(X24<W24,"Pérdida","Se mantiene")) -> Mejoría
V25: 107 | W25: =VLOOKUP(V25,'BD1'!$A$2:$AF$1139,31,0) -> 8 | X25: =VLOOKUP(V25,'BD2'!$A$2:$AF$1139,31,0) -> 8 | Y25: =IF(X25>W25,"Mejoría",IF(X25<W25,"Pérdida","Se mantiene")) -> Se mantiene
A26: CONEXIÓN FÁCIL | V26: 109 | W26: =VLOOKUP(V26,'BD1'!$A$2:$AF$1139,31,0) -> 8 | X26: =VLOOKUP(V26,'BD2'!$A$2:$AF$1139,31,0) -> 8 | Y26: =IF(X26>W26,"Mejoría",IF(X26<W26,"Pérdida","Se mantiene")) -> Se mantiene
A27: MUNICIPIO | B27: ERROR 1 | C27: ERROR 2 | D27: TOTAL | E27: % ERROR 1 | F27: % ÉXITO 1 | G27: % ERROR 2 | H27: % ÉXITO 2 | V27: 112 | W27: =VLOOKUP(V27,'BD1'!$A$2:$AF$1139,31,0) -> 7 | X27: =VLOOKUP(V27,'BD2'!$A$2:$AF$1139,31,0) -> 8 | Y27: =IF(X27>W27,"Mejoría",IF(X27<W27,"Pérdida","Se mantiene")) -> Mejoría
A28: León | B28: =COUNTIFS('BD1'!H:H,Estadísticas!A28,'BD1'!S:S,"no") -> 12 | C28: =COUNTIFS('BD2'!H:H,Estadísticas!A28,'BD2'!S:S,"no") -> 9 | D28: =(COUNTIFS('BD1'!H:H,Estadísticas!A28,'BD1'!K:K,"ok") + COUNTIFS('BD1'!H:H,Estadísticas!A28,'BD1'!K:K,"sin video")) -> 217 | E28: =B28*100/D28 -> 5.5299539 | F28: =(D28-B28)*100/D28 -> 94.470046 | G28: =C28*100/D28 -> 4.1474654 | H28: =(D28-C28)*100/D28 -> 95.852535 | V28: 114 | W28: =VLOOKUP(V28,'BD1'!$A$2:$AF$1139,31,0) -> 8 | X28: =VLOOKUP(V28,'BD2'!$A$2:$AF$1139,31,0) -> 0 | Y28: =IF(X28>W28,"Mejoría",IF(X28<W28,"Pérdida","Se mantiene")) -> Pérdida
A29: Silao | B29: =COUNTIFS('BD1'!H:H,Estadísticas!A29,'BD1'!S:S,"no") -> 5 | C29: =COUNTIFS('BD2'!H:H,Estadísticas!A29,'BD2'!S:S,"no") -> 0 | D29: =(COUNTIFS('BD1'!H:H,Estadísticas!A29,'BD1'!K:K,"ok") + COUNTIFS('BD1'!H:H,Estadísticas!A29,'BD1'!K:K,"sin video")) -> 47 | E29: =B29*100/D29 -> 10.638298 | F29: =(D29-B29)*100/D29 -> 89.361702 | G29: =C29*100/D29 -> 0 | H29: =(D29-C29)*100/D29 -> 100 | V29: 123 | W29: =VLOOKUP(V29,'BD1'!$A$2:$AF$1139,31,0) -> 8 | X29: =VLOOKUP(V29,'BD2'!$A$2:$AF$1139,31,0) -> 8 | Y29: =IF(X29>W29,"Mejoría",IF(X29<W29,"Pérdida","Se mantiene")) -> Se mantiene
A30: Guanajuato | B30: =COUNTIFS('BD1'!H:H,Estadísticas!A30,'BD1'!S:S,"no") -> 5 | C30: =COUNTIFS('BD2'!H:H,Estadísticas!A30,'BD2'!S:S,"no") -> 4 | D30: =(COUNTIFS('BD1'!H:H,Estadísticas!A30,'BD1'!K:K,"ok") + COUNTIFS('BD1'!H:H,Estadísticas!A30,'BD1'!K:K,"sin video")) -> 55 | E30: =B30*100/D30 -> 9.0909091 | F30: =(D30-B30)*100/D30 -> 90.909091 | G30: =C30*100/D30 -> 7.2727273 | H30: =(D30-C30)*100/D30 -> 92.727273 | V30: 128 | W30: =VLOOKUP(V30,'BD1'!$A$2:$AF$1139,31,0) -> 8 | X30: =VLOOKUP(V30,'BD2'!$A$2:$AF$1139,31,0) -> 8 | Y30: =IF(X30>W30,"Mejoría",IF(X30<W30,"Pérdida","Se mantiene")) -> Se mantiene
A31: Irapuato | B31: =COUNTIFS('BD1'!H:H,Estadísticas!A31,'BD1'!S:S,"no") -> 1 | C31: =COUNTIFS('BD2'!H:H,Estadísticas!A31,'BD2'!S:S,"no") -> 0 | D31: =(COUNTIFS('BD1'!H:H,Estadísticas!A31,'BD1'!K:K,"ok") + COUNTIFS('BD1'!H:H,Estadísticas!A31,'BD1'!K:K,"sin video")) -> 54 | E31: =B31*100/D31 -> 1.8518519 | F31: =(D31-B31)*100/D31 -> 98.148148 | G31: =C31*100/D31 -> 0 | H31: =(D31-C31)*100/D31 -> 100 | V31: 131 | W31: =VLOOKUP(V31,'BD1'!$A$2:$AF$1139,31,0) -> 8 | X31: =VLOOKUP(V31,'BD2'!$A$2:$AF$1139,31,0) -> 8 | Y31: =IF(X31>W31,"Mejoría",IF(X31<W31,"Pérdida","Se mantiene")) -> Se mantiene
A32: Salamanca | B32: =COUNTIFS('BD1'!H:H,Estadísticas!A32,'BD1'!S:S,"no") -> 3 | C32: =COUNTIFS('BD2'!H:H,Estadísticas!A32,'BD2'!S:S,"no") -> 3 | D32: =(COUNTIFS('BD1'!H:H,Estadísticas!A32,'BD1'!K:K,"ok") + COUNTIFS('BD1'!H:H,Estadísticas!A32,'BD1'!K:K,"sin video")) -> 20 | E32: =B32*100/D32 -> 15 | F32: =(D32-B32)*100/D32 -> 85 | G32: =C32*100/D32 -> 15 | H32: =(D32-C32)*100/D32 -> 85 | V32: 136 | W32: =VLOOKUP(V32,'BD1'!$A$2:$AF$1139,31,0) -> 8 | X32: =VLOOKUP(V32,'BD2'!$A$2:$AF$1139,31,0) -> 8 | Y32: =IF(X32>W32,"Mejoría",IF(X32<W32,"Pérdida","Se mantiene")) -> Se mantiene
A33: Celaya | B33: =COUNTIFS('BD1'!H:H,Estadísticas!A33,'BD1'!S:S,"no") -> 2 | C33: =COUNTIFS('BD2'!H:H,Estadísticas!A33,'BD2'!S:S,"no") -> 1 | D33: =(COUNTIFS('BD1'!H:H,Estadísticas!A33,'BD1'!K:K,"ok") + COUNTIFS('BD1'!H:H,Estadísticas!A33,'BD1'!K:K,"sin video")) -> 25 | E33: =B33*100/D33 -> 8 | F33: =(D33-B33)*100/D33 -> 92 | G33: =C33*100/D33 -> 4 | H33: =(D33-C33)*100/D33 -> 96 | V33: 141 | W33: =VLOOKUP(V33,'BD1'!$A$2:$AF$1139,31,0) -> 8 | X33: =VLOOKUP(V33,'BD2'!$A$2:$AF$1139,31,0) -> 8 | Y33: =IF(X33>W33,"Mejoría",IF(X33<W33,"Pérdida","Se mantiene")) -> Se mantiene
V34: 142 | W34: =VLOOKUP(V34,'BD1'!$A$2:$AF$1139,31,0) -> 8 | X34: =VLOOKUP(V34,'BD2'!$A$2:$AF$1139,31,0) -> 8 | Y34: =IF(X34>W34,"Mejoría",IF(X34<W34,"Pérdida","Se mantiene")) -> Se mantiene
A35: MENSAJERO | V35: 144 | W35: =VLOOKUP(V35,'BD1'!$A$2:$AF$1139,31,0) -> 8 | X35: =VLOOKUP(V35,'BD2'!$A$2:$AF$1139,31,0) -> 8 | Y35: =IF(X35>W35,"Mejoría",IF(X35<W35,"Pérdida","Se mantiene")) -> Se mantiene
A36: MUNICIPIO | B36: ERROR 1 | C36: ERROR 2 | D36: TOTAL | E36: % ERROR 1 | F36: % ÉXITO 1 | G36: % ERROR 2 | H36: % ÉXITO 2 | V36: 147 | W36: =VLOOKUP(V36,'BD1'!$A$2:$AF$1139,31,0) -> 8 | X36: =VLOOKUP(V36,'BD2'!$A$2:$AF$1139,31,0) -> 8 | Y36: =IF(X36>W36,"Mejoría",IF(X36<W36,"Pérdida","Se mantiene")) -> Se mantiene
A37: León | B37: =COUNTIFS('BD1'!H:H,Estadísticas!A37,'BD1'!T:T,"no") -> 9 | C37: =COUNTIFS('BD2'!H:H,Estadísticas!A37,'BD2'!T:T,"no") -> 17 | D37: =(COUNTIFS('BD1'!H:H,Estadísticas!A37,'BD1'!K:K,"ok") + COUNTIFS('BD1'!H:H,Estadísticas!A37,'BD1'!K:K,"sin video")) -> 217 | E37: =B37*100/D37 -> 4.1474654 | F37: =(D37-B37)*100/D37 -> 95.852535 | G37: =C37*100/D37 -> 7.8341014 | H37: =(D37-C37)*100/D37 -> 92.165899 | V37: 148 | W37: =VLOOKUP(V37,'BD1'!$A$2:$AF$1139,31,0) -> 8 | X37: =VLOOKUP(V37,'BD2'!$A$2:$AF$1139,31,0) -> 0 | Y37: =IF(X37>W37,"Mejoría",IF(X37<W37,"Pérdida","Se mantiene")) -> Pérdida
A38: Silao | B38: =COUNTIFS('BD1'!H:H,Estadísticas!A38,'BD1'!T:T,"no") -> 3 | C38: =COUNTIFS('BD2'!H:H,Estadísticas!A38,'BD2'!T:T,"no") -> 0 | D38: =(COUNTIFS('BD1'!H:H,Estadísticas!A38,'BD1'!K:K,"ok") + COUNTIFS('BD1'!H:H,Estadísticas!A38,'BD1'!K:K,"sin video")) -> 47 | E38: =B38*100/D38 -> 6.3829787 | F38: =(D38-B38)*100/D38 -> 93.617021 | G38: =C38*100/D38 -> 0 | H38: =(D38-C38)*100/D38 -> 100 | V38: 163 | W38: =VLOOKUP(V38,'BD1'!$A$2:$AF$1139,31,0) -> 8 | X38: =VLOOKUP(V38,'BD2'!$A$2:$AF$1139,31,0) -> 8 | Y38: =IF(X38>W38,"Mejoría",IF(X38<W38,"Pérdida","Se mantiene")) -> Se mantiene
A39: Guanajuato | B39: =COUNTIFS('BD1'!H:H,Estadísticas!A39,'BD1'!T:T,"no") -> 10 | C39: =COUNTIFS('BD2'!H:H,Estadísticas!A39,'BD2'!T:T,"no") -> 11 | D39: =(COUNTIFS('BD1'!H:H,Estadísticas!A39,'BD1'!K:K,"ok") + COUNTIFS('BD1'!H:H,Estadísticas!A39,'BD1'!K:K,"sin video")) -> 55 | E39: =B39*100/D39 -> 18.181818 | F39: =(D39-B39)*100/D39 -> 81.818182 | G39: =C39*100/D39 -> 20 | H39: =(D39-C39)*100/D39 -> 80 | V39: 164 | W39: =VLOOKUP(V39,'BD1'!$A$2:$AF$1139,31,0) -> 8 | X39: =VLOOKUP(V39,'BD2'!$A$2:$AF$1139,31,0) -> 8 | Y39: =IF(X39>W39,"Mejoría",IF(X39<W39,"Pérdida","Se mantiene")) -> Se mantiene
A40: Irapuato | B40: =COUNTIFS('BD1'!H:H,Estadísticas!A40,'BD1'!T:T,"no") -> 1 | C40: =COUNTIFS('BD2'!H:H,Estadísticas!A40,'BD2'!T:T,"no") -> 1 | D40: =(COUNTIFS('BD1'!H:H,Estadísticas!A40,'BD1'!K:K,"ok") + COUNTIFS('BD1'!H:H,Estadísticas!A40,'BD1'!K:K,"sin video")) -> 54 | E40: =B40*100/D40 -> 1.8518519 | F40: =(D40-B40)*100/D40 -> 98.148148 | G40: =C40*100/D40 -> 1.8518519 | H40: =(D40-C40)*100/D40 -> 98.148148 | V40: 200 | W40: =VLOOKUP(V40,'BD1'!$A$2:$AF$1139,31,0) -> 8 | X40: =VLOOKUP(V40,'BD2'!$A$2:$AF$1139,31,0) -> 8 | Y40: =IF(X40>W40,"Mejoría",IF(X40<W40,"Pérdida","Se mantiene")) -> Se mantiene
A41: Salamanca | B41: =COUNTIFS('BD1'!H:H,Estadísticas!A41,'BD1'!T:T,"no") -> 3 | C41: =COUNTIFS('BD2'!H:H,Estadísticas!A41,'BD2'!T:T,"no") -> 5 | D41: =(COUNTIFS('BD1'!H:H,Estadísticas!A41,'BD1'!K:K,"ok") + COUNTIFS('BD1'!H:H,Estadísticas!A41,'BD1'!K:K,"sin video")) -> 20 | E41: =B41*100/D41 -> 15 | F41: =(D41-B41)*100/D41 -> 85 | G41: =C41*100/D41 -> 25 | H41: =(D41-C41)*100/D41 -> 75 | V41: 202 | W41: =VLOOKUP(V41,'BD1'!$A$2:$AF$1139,31,0) -> 8 | X41: =VLOOKUP(V41,'BD2'!$A$2:$AF$1139,31,0) -> 7 | Y41: =IF(X41>W41,"Mejoría",IF(X41<W41,"Pérdida","Se mantiene")) -> Pérdida
A42: Celaya | B42: =COUNTIFS('BD1'!H:H,Estadísticas!A42,'BD1'!T:T,"no") -> 2 | C42: =COUNTIFS('BD2'!H:H,Estadísticas!A42,'BD2'!T:T,"no") -> 3 | D42: =(COUNTIFS('BD1'!H:H,Estadísticas!A42,'BD1'!K:K,"ok") + COUNTIFS('BD1'!H:H,Estadísticas!A42,'BD1'!K:K,"sin video")) -> 25 | E42: =B42*100/D42 -> 8 | F42: =(D42-B42)*100/D42 -> 92 | G42: =C42*100/D42 -> 12 | H42: =(D42-C42)*100/D42 -> 88 | V42: 204 | W42: =VLOOKUP(V42,'BD1'!$A$2:$AF$1139,31,0) -> 8 | X42: =VLOOKUP(V42,'BD2'!$A$2:$AF$1139,31,0) -> 8 | Y42: =IF(X42>W42,"Mejoría",IF(X42<W42,"Pérdida","Se mantiene")) -> Se mantiene
V43: 211 | W43: =VLOOKUP(V43,'BD1'!$A$2:$AF$1139,31,0) -> 8 | X43: =VLOOKUP(V43,'BD2'!$A$2:$AF$1139,31,0) -> 7 | Y43: =IF(X43>W43,"Mejoría",IF(X43<W43,"Pérdida","Se mantiene")) -> Pérdida
A44: FACEBOOK | V44: 212 | W44: =VLOOKUP(V44,'BD1'!$A$2:$AF$1139,31,0) -> 5 | X44: =VLOOKUP(V44,'BD2'!$A$2:$AF$1139,31,0) -> 7 | Y44: =IF(X44>W44,"Mejoría",IF(X44<W44,"Pérdida","Se mantiene")) -> Mejoría
A45: MUNICIPIO | B45: ERROR 1 | C45: ERROR 2 | D45: TOTAL | E45: % ERROR 1 | F45: % ÉXITO 1 | G45: % ERROR 2 | H45: % ÉXITO 2 | V45: 214 | W45: =VLOOKUP(V45,'BD1'!$A$2:$AF$1139,31,0) -> 8 | X45: =VLOOKUP(V45,'BD2'!$A$2:$AF$1139,31,0) -> 0 | Y45: =IF(X45>W45,"Mejoría",IF(X45<W45,"Pérdida","Se mantiene")) -> Pérdida
A46: León | B46: =COUNTIFS('BD1'!H:H,Estadísticas!A46,'BD1'!U:U,"no") -> 6 | C46: =COUNTIFS('BD2'!H:H,Estadísticas!A46,'BD2'!U:U,"no") -> 10 | D46: =(COUNTIFS('BD1'!H:H,Estadísticas!A46,'BD1'!K:K,"ok") + COUNTIFS('BD1'!H:H,Estadísticas!A46,'BD1'!K:K,"sin video")) -> 217 | E46: =B46*100/D46 -> 2.764977 | F46: =(D46-B46)*100/D46 -> 97.235023 | G46: =C46*100/D46 -> 4.6082949 | H46: =(D46-C46)*100/D46 -> 95.391705 | V46: 215 | W46: =VLOOKUP(V46,'BD1'!$A$2:$AF$1139,31,0) -> 8 | X46: =VLOOKUP(V46,'BD2'!$A$2:$AF$1139,31,0) -> 7 | Y46: =IF(X46>W46,"Mejoría",IF(X46<W46,"Pérdida","Se mantiene")) -> Pérdida
A47: Silao | B47: =COUNTIFS('BD1'!H:H,Estadísticas!A47,'BD1'!U:U,"no") -> 4 | C47: =COUNTIFS('BD2'!H:H,Estadísticas!A47,'BD2'!U:U,"no") -> 0 | D47: =(COUNTIFS('BD1'!H:H,Estadísticas!A47,'BD1'!K:K,"ok") + COUNTIFS('BD1'!H:H,Estadísticas!A47,'BD1'!K:K,"sin video")) -> 47 | E47: =B47*100/D47 -> 8.5106383 | F47: =(D47-B47)*100/D47 -> 91.489362 | G47: =C47*100/D47 -> 0 | H47: =(D47-C47)*100/D47 -> 100 | V47: 216 | W47: =VLOOKUP(V47,'BD1'!$A$2:$AF$1139,31,0) -> 8 | X47: =VLOOKUP(V47,'BD2'!$A$2:$AF$1139,31,0) -> 8 | Y47: =IF(X47>W47,"Mejoría",IF(X47<W47,"Pérdida","Se mantiene")) -> Se mantiene
A48: Guanajuato | B48: =COUNTIFS('BD1'!H:H,Estadísticas!A48,'BD1'!U:U,"no") -> 7 | C48: =COUNTIFS('BD2'!H:H,Estadísticas!A48,'BD2'!U:U,"no") -> 7 | D48: =(COUNTIFS('BD1'!H:H,Estadísticas!A48,'BD1'!K:K,"ok") + COUNTIFS('BD1'!H:H,Estadísticas!A48,'BD1'!K:K,"sin video")) -> 55 | E48: =B48*100/D48 -> 12.727273 | F48: =(D48-B48)*100/D48 -> 87.272727 | G48: =C48*100/D48 -> 12.727273 | H48: =(D48-C48)*100/D48 -> 87.272727 | V48: 217 | W48: =VLOOKUP(V48,'BD1'!$A$2:$AF$1139,31,0) -> 8 | X48: =VLOOKUP(V48,'BD2'!$A$2:$AF$1139,31,0) -> 0 | Y48: =IF(X48>W48,"Mejoría",IF(X48<W48,"Pérdida","Se mantiene")) -> Pérdida
A49: Irapuato | B49: =COUNTIFS('BD1'!H:H,Estadísticas!A49,'BD1'!U:U,"no") -> 1 | C49: =COUNTIFS('BD2'!H:H,Estadísticas!A49,'BD2'!U:U,"no") -> 0 | D49: =(COUNTIFS('BD1'!H:H,Estadísticas!A49,'BD1'!K:K,"ok") + COUNTIFS('BD1'!H:H,Estadísticas!A49,'BD1'!K:K,"sin video")) -> 54 | E49: =B49*100/D49 -> 1.8518519 | F49: =(D49-B49)*100/D49 -> 98.148148 | G49: =C49*100/D49 -> 0 | H49: =(D49-C49)*100/D49 -> 100 | V49: 222 | W49: =VLOOKUP(V49,'BD1'!$A$2:$AF$1139,31,0) -> 8 | X49: =VLOOKUP(V49,'BD2'!$A$2:$AF$1139,31,0) -> 8 | Y49: =IF(X49>W49,"Mejoría",IF(X49<W49,"Pérdida","Se mantiene")) -> Se mantiene
A50: Salamanca | B50: =COUNTIFS('BD1'!H:H,Estadísticas!A50,'BD1'!U:U,"no") -> 3 | C50: =COUNTIFS('BD2'!H:H,Estadísticas!A50,'BD2'!U:U,"no") -> 4 | D50: =(COUNTIFS('BD1'!H:H,Estadísticas!A50,'BD1'!K:K,"ok") + COUNTIFS('BD1'!H:H,Estadísticas!A50,'BD1'!K:K,"sin video")) -> 20 | E50: =B50*100/D50 -> 15 | F50: =(D50-B50)*100/D50 -> 85 | G50: =C50*100/D50 -> 20 | H50: =(D50-C50)*100/D50 -> 80 | V50: 224 | W50: =VLOOKUP(V50,'BD1'!$A$2:$AF$1139,31,0) -> 8 | X50: =VLOOKUP(V50,'BD2'!$A$2:$AF$1139,31,0) -> 8 | Y50: =IF(X50>W50,"Mejoría",IF(X50<W50,"Pérdida","Se mantiene")) -> Se mantiene
A51: Celaya | B51: =COUNTIFS('BD1'!H:H,Estadísticas!A51,'BD1'!U:U,"no") -> 2 | C51: =COUNTIFS('BD2'!H:H,Estadísticas!A51,'BD2'!U:U,"no") -> 2 | D51: =(COUNTIFS('BD1'!H:H,Estadísticas!A51,'BD1'!K:K,"ok") + COUNTIFS('BD1'!H:H,Estadísticas!A51,'BD1'!K:K,"sin video")) -> 25 | E51: =B51*100/D51 -> 8 | F51: =(D51-B51)*100/D51 -> 92 | G51: =C51*100/D51 -> 8 | H51: =(D51-C51)*100/D51 -> 92 | V51: 231 | W51: =VLOOKUP(V51,'BD1'!$A$2:$AF$1139,31,0) -> 7 | X51: =VLOOKUP(V51,'BD2'!$A$2:$AF$1139,31,0) -> 7 | Y51: =IF(X51>W51,"Mejoría",IF(X51<W51,"Pérdida","Se mantiene")) -> Se mantiene
V52: 233 | W52: =VLOOKUP(V52,'BD1'!$A$2:$AF$1139,31,0) -> 8 | X52: =VLOOKUP(V52,'BD2'!$A$2:$AF$1139,31,0) -> 8 | Y52: =IF(X52>W52,"Mejoría",IF(X52<W52,"Pérdida","Se mantiene")) -> Se mantiene
A53: YOUTUBE | V53: 234 | W53: =VLOOKUP(V53,'BD1'!$A$2:$AF$1139,31,0) -> 8 | X53: =VLOOKUP(V53,'BD2'!$A$2:$AF$1139,31,0) -> 8 | Y53: =IF(X53>W53,"Mejoría",IF(X53<W53,"Pérdida","Se mantiene")) -> Se mantiene
A54: MUNICIPIO | B54: ERROR 1 | C54: ERROR 2 | D54: TOTAL | E54: % ERROR 1 | F54: % ÉXITO 1 | G54: % ERROR 2 | H54: % ÉXITO 2 | V54: 241 | W54: =VLOOKUP(V54,'BD1'!$A$2:$AF$1139,31,0) -> 8 | X54: =VLOOKUP(V54,'BD2'!$A$2:$AF$1139,31,0) -> 8 | Y54: =IF(X54>W54,"Mejoría",IF(X54<W54,"Pérdida","Se mantiene")) -> Se mantiene
A55: León | B55: =COUNTIFS('BD1'!H:H,Estadísticas!A55,'BD1'!V:V,"no") -> 16 | C55: =COUNTIFS('BD2'!H:H,Estadísticas!A55,'BD2'!V:V,"no") -> 29 | D55: =(COUNTIFS('BD1'!H:H,Estadísticas!A55,'BD1'!K:K,"ok") + COUNTIFS('BD1'!H:H,Estadísticas!A55,'BD1'!K:K,"sin video")) -> 217 | E55: =B55*100/D55 -> 7.3732719 | F55: =(D55-B55)*100/D55 -> 92.626728 | G55: =C55*100/D55 -> 13.364055 | H55: =(D55-C55)*100/D55 -> 86.635945 | V55: 242 | W55: =VLOOKUP(V55,'BD1'!$A$2:$AF$1139,31,0) -> 8 | X55: =VLOOKUP(V55,'BD2'!$A$2:$AF$1139,31,0) -> 8 | Y55: =IF(X55>W55,"Mejoría",IF(X55<W55,"Pérdida","Se mantiene")) -> Se mantiene
A56: Silao | B56: =COUNTIFS('BD1'!H:H,Estadísticas!A56,'BD1'!V:V,"no") -> 4 | C56: =COUNTIFS('BD2'!H:H,Estadísticas!A56,'BD2'!V:V,"no") -> 0 | D56: =(COUNTIFS('BD1'!H:H,Estadísticas!A56,'BD1'!K:K,"ok") + COUNTIFS('BD1'!H:H,Estadísticas!A56,'BD1'!K:K,"sin video")) -> 47 | E56: =B56*100/D56 -> 8.5106383 | F56: =(D56-B56)*100/D56 -> 91.489362 | G56: =C56*100/D56 -> 0 | H56: =(D56-C56)*100/D56 -> 100 | V56: 248 | W56: =VLOOKUP(V56,'BD1'!$A$2:$AF$1139,31,0) -> 7 | X56: =VLOOKUP(V56,'BD2'!$A$2:$AF$1139,31,0) -> 5 | Y56: =IF(X56>W56,"Mejoría",IF(X56<W56,"Pérdida","Se mantiene")) -> Pérdida
A57: Guanajuato | B57: =COUNTIFS('BD1'!H:H,Estadísticas!A57,'BD1'!V:V,"no") -> 13 | C57: =COUNTIFS('BD2'!H:H,Estadísticas!A57,'BD2'!V:V,"no") -> 13 | D57: =(COUNTIFS('BD1'!H:H,Estadísticas!A57,'BD1'!K:K,"ok") + COUNTIFS('BD1'!H:H,Estadísticas!A57,'BD1'!K:K,"sin video")) -> 55 | E57: =B57*100/D57 -> 23.636364 | F57: =(D57-B57)*100/D57 -> 76.363636 | G57: =C57*100/D57 -> 23.636364 | H57: =(D57-C57)*100/D57 -> 76.363636 | V57: 254 | W57: =VLOOKUP(V57,'BD1'!$A$2:$AF$1139,31,0) -> 7 | X57: =VLOOKUP(V57,'BD2'!$A$2:$AF$1139,31,0) -> 8 | Y57: =IF(X57>W57,"Mejoría",IF(X57<W57,"Pérdida","Se mantiene")) -> Mejoría
A58: Irapuato | B58: =COUNTIFS('BD1'!H:H,Estadísticas!A58,'BD1'!V:V,"no") -> 3 | C58: =COUNTIFS('BD2'!H:H,Estadísticas!A58,'BD2'!V:V,"no") -> 1 | D58: =(COUNTIFS('BD1'!H:H,Estadísticas!A58,'BD1'!K:K,"ok") + COUNTIFS('BD1'!H:H,Estadísticas!A58,'BD1'!K:K,"sin video")) -> 54 | E58: =B58*100/D58 -> 5.5555556 | F58: =(D58-B58)*100/D58 -> 94.444444 | G58: =C58*100/D58 -> 1.8518519 | H58: =(D58-C58)*100/D58 -> 98.148148 | V58: 256 | W58: =VLOOKUP(V58,'BD1'!$A$2:$AF$1139,31,0) -> 8 | X58: =VLOOKUP(V58,'BD2'!$A$2:$AF$1139,31,0) -> 8 | Y58: =IF(X58>W58,"Mejoría",IF(X58<W58,"Pérdida","Se mantiene")) -> Se mantiene
A59: Salamanca | B59: =COUNTIFS('BD1'!H:H,Estadísticas!A59,'BD1'!V:V,"no") -> 5 | C59: =COUNTIFS('BD2'!H:H,Estadísticas!A59,'BD2'!V:V,"no") -> 6 | D59: =(COUNTIFS('BD1'!H:H,Estadísticas!A59,'BD1'!K:K,"ok") + COUNTIFS('BD1'!H:H,Estadísticas!A59,'BD1'!K:K,"sin video")) -> 20 | E59: =B59*100/D59 -> 25 | F59: =(D59-B59)*100/D59 -> 75 | G59: =C59*100/D59 -> 30 | H59: =(D59-C59)*100/D59 -> 70 | V59: 257 | W59: =VLOOKUP(V59,'BD1'!$A$2:$AF$1139,31,0) -> 8 | X59: =VLOOKUP(V59,'BD2'!$A$2:$AF$1139,31,0) -> 8 | Y59: =IF(X59>W59,"Mejoría",IF(X59<W59,"Pérdida","Se mantiene")) -> Se mantiene
A60: Celaya | B60: =COUNTIFS('BD1'!H:H,Estadísticas!A60,'BD1'!V:V,"no") -> 2 | C60: =COUNTIFS('BD2'!H:H,Estadísticas!A60,'BD2'!V:V,"no") -> 2 | D60: =(COUNTIFS('BD1'!H:H,Estadísticas!A60,'BD1'!K:K,"ok") + COUNTIFS('BD1'!H:H,Estadísticas!A60,'BD1'!K:K,"sin video")) -> 25 | E60: =B60*100/D60 -> 8 | F60: =(D60-B60)*100/D60 -> 92 | G60: =C60*100/D60 -> 8 | H60: =(D60-C60)*100/D60 -> 92 | V60: 259 | W60: =VLOOKUP(V60,'BD1'!$A$2:$AF$1139,31,0) -> 8 | X60: =VLOOKUP(V60,'BD2'!$A$2:$AF$1139,31,0) -> 8 | Y60: =IF(X60>W60,"Mejoría",IF(X60<W60,"Pérdida","Se mantiene")) -> Se mantiene
V61: 266 | W61: =VLOOKUP(V61,'BD1'!$A$2:$AF$1139,31,0) -> 8 | X61: =VLOOKUP(V61,'BD2'!$A$2:$AF$1139,31,0) -> 8 | Y61: =IF(X61>W61,"Mejoría",IF(X61<W61,"Pérdida","Se mantiene")) -> Se mantiene
A62: GOOGLE MAPS | V62: 269 | W62: =VLOOKUP(V62,'BD1'!$A$2:$AF$1139,31,0) -> 8 | X62: =VLOOKUP(V62,'BD2'!$A$2:$AF$1139,31,0) -> 3 | Y62: =IF(X62>W62,"Mejoría",IF(X62<W62,"Pérdida","Se mantiene")) -> Pérdida
A63: MUNICIPIO | B63: ERROR 1 | C63: ERROR 2 | D63: TOTAL | E63: % ERROR 1 | F63: % ÉXITO 1 | G63: % ERROR 2 | H63: % ÉXITO 2 | V63: 274 | W63: =VLOOKUP(V63,'BD1'!$A$2:$AF$1139,31,0) -> 7 | X63: =VLOOKUP(V63,'BD2'!$A$2:$AF$1139,31,0) -> 8 | Y63: =IF(X63>W63,"Mejoría",IF(X63<W63,"Pérdida","Se mantiene")) -> Mejoría
A64: León | B64: =COUNTIFS('BD1'!H:H,Estadísticas!A64,'BD1'!W:W,"no") -> 6 | C64: =COUNTIFS('BD2'!H:H,Estadísticas!A64,'BD2'!W:W,"no") -> 11 | D64: =(COUNTIFS('BD1'!H:H,Estadísticas!A64,'BD1'!K:K,"ok") + COUNTIFS('BD1'!H:H,Estadísticas!A64,'BD1'!K:K,"sin video")) -> 217 | E64: =B64*100/D64 -> 2.764977 | F64: =(D64-B64)*100/D64 -> 97.235023 | G64: =C64*100/D64 -> 5.0691244 | H64: =(D64-C64)*100/D64 -> 94.930876 | V64: 275 | W64: =VLOOKUP(V64,'BD1'!$A$2:$AF$1139,31,0) -> 8 | X64: =VLOOKUP(V64,'BD2'!$A$2:$AF$1139,31,0) -> 8 | Y64: =IF(X64>W64,"Mejoría",IF(X64<W64,"Pérdida","Se mantiene")) -> Se mantiene
A65: Silao | B65: =COUNTIFS('BD1'!H:H,Estadísticas!A65,'BD1'!W:W,"no") -> 3 | C65: =COUNTIFS('BD2'!H:H,Estadísticas!A65,'BD2'!W:W,"no") -> 0 | D65: =(COUNTIFS('BD1'!H:H,Estadísticas!A65,'BD1'!K:K,"ok") + COUNTIFS('BD1'!H:H,Estadísticas!A65,'BD1'!K:K,"sin video")) -> 47 | E65: =B65*100/D65 -> 6.3829787 | F65: =(D65-B65)*100/D65 -> 93.617021 | G65: =C65*100/D65 -> 0 | H65: =(D65-C65)*100/D65 -> 100 | V65: 287 | W65: =VLOOKUP(V65,'BD1'!$A$2:$AF$1139,31,0) -> 8 | X65: =VLOOKUP(V65,'BD2'!$A$2:$AF$1139,31,0) -> 8 | Y65: =IF(X65>W65,"Mejoría",IF(X65<W65,"Pérdida","Se mantiene")) -> Se mantiene
A66: Guanajuato | B66: =COUNTIFS('BD1'!H:H,Estadísticas!A66,'BD1'!W:W,"no") -> 7 | C66: =COUNTIFS('BD2'!H:H,Estadísticas!A66,'BD2'!W:W,"no") -> 8 | D66: =(COUNTIFS('BD1'!H:H,Estadísticas!A66,'BD1'!K:K,"ok") + COUNTIFS('BD1'!H:H,Estadísticas!A66,'BD1'!K:K,"sin video")) -> 55 | E66: =B66*100/D66 -> 12.727273 | F66: =(D66-B66)*100/D66 -> 87.272727 | G66: =C66*100/D66 -> 14.545455 | H66: =(D66-C66)*100/D66 -> 85.454545 | V66: 295 | W66: =VLOOKUP(V66,'BD1'!$A$2:$AF$1139,31,0) -> 8 | X66: =VLOOKUP(V66,'BD2'!$A$2:$AF$1139,31,0) -> 2 | Y66: =IF(X66>W66,"Mejoría",IF(X66<W66,"Pérdida","Se mantiene")) -> Pérdida
A67: Irapuato | B67: =COUNTIFS('BD1'!H:H,Estadísticas!A67,'BD1'!W:W,"no") -> 1 | C67: =COUNTIFS('BD2'!H:H,Estadísticas!A67,'BD2'!W:W,"no") -> 0 | D67: =(COUNTIFS('BD1'!H:H,Estadísticas!A67,'BD1'!K:K,"ok") + COUNTIFS('BD1'!H:H,Estadísticas!A67,'BD1'!K:K,"sin video")) -> 54 | E67: =B67*100/D67 -> 1.8518519 | F67: =(D67-B67)*100/D67 -> 98.148148 | G67: =C67*100/D67 -> 0 | H67: =(D67-C67)*100/D67 -> 100 | V67: 298 | W67: =VLOOKUP(V67,'BD1'!$A$2:$AF$1139,31,0) -> 8 | X67: =VLOOKUP(V67,'BD2'!$A$2:$AF$1139,31,0) -> 3 | Y67: =IF(X67>W67,"Mejoría",IF(X67<W67,"Pérdida","Se mantiene")) -> Pérdida
A68: Salamanca | B68: =COUNTIFS('BD1'!H:H,Estadísticas!A68,'BD1'!W:W,"no") -> 3 | C68: =COUNTIFS('BD2'!H:H,Estadísticas!A68,'BD2'!W:W,"no") -> 5 | D68: =(COUNTIFS('BD1'!H:H,Estadísticas!A68,'BD1'!K:K,"ok") + COUNTIFS('BD1'!H:H,Estadísticas!A68,'BD1'!K:K,"sin video")) -> 20 | E68: =B68*100/D68 -> 15 | F68: =(D68-B68)*100/D68 -> 85 | G68: =C68*100/D68 -> 25 | H68: =(D68-C68)*100/D68 -> 75 | V68: 305 | W68: =VLOOKUP(V68,'BD1'!$A$2:$AF$1139,31,0) -> 6 | X68: =VLOOKUP(V68,'BD2'!$A$2:$AF$1139,31,0) -> 8 | Y68: =IF(X68>W68,"Mejoría",IF(X68<W68,"Pérdida","Se mantiene")) -> Mejoría
A69: Celaya | B69: =COUNTIFS('BD1'!H:H,Estadísticas!A69,'BD1'!W:W,"no") -> 2 | C69: =COUNTIFS('BD2'!H:H,Estadísticas!A69,'BD2'!W:W,"no") -> 2 | D69: =(COUNTIFS('BD1'!H:H,Estadísticas!A69,'BD1'!K:K,"ok") + COUNTIFS('BD1'!H:H,Estadísticas!A69,'BD1'!K:K,"sin video")) -> 25 | E69: =B69*100/D69 -> 8 | F69: =(D69-B69)*100/D69 -> 92 | G69: =C69*100/D69 -> 8 | H69: =(D69-C69)*100/D69 -> 92 | V69: 307 | W69: =VLOOKUP(V69,'BD1'!$A$2:$AF$1139,31,0) -> 8 | X69: =VLOOKUP(V69,'BD2'!$A$2:$AF$1139,31,0) -> 7 | Y69: =IF(X69>W69,"Mejoría",IF(X69<W69,"Pérdida","Se mantiene")) -> Pérdida
V70: 312 | W70: =VLOOKUP(V70,'BD1'!$A$2:$AF$1139,31,0) -> 7 | X70: =VLOOKUP(V70,'BD2'!$A$2:$AF$1139,31,0) -> 7 | Y70: =IF(X70>W70,"Mejoría",IF(X70<W70,"Pérdida","Se mantiene")) -> Se mantiene
A71: NAVEGACIÓN | V71: 313 | W71: =VLOOKUP(V71,'BD1'!$A$2:$AF$1139,31,0) -> 8 | X71: =VLOOKUP(V71,'BD2'!$A$2:$AF$1139,31,0) -> 7 | Y71: =IF(X71>W71,"Mejoría",IF(X71<W71,"Pérdida","Se mantiene")) -> Pérdida
A72: MUNICIPIO | B72: ERROR 1 | C72: ERROR 2 | D72: TOTAL | E72: % ERROR 1 | F72: % ÉXITO 1 | G72: % ERROR 2 | H72: % ÉXITO 2 | V72: 314 | W72: =VLOOKUP(V72,'BD1'!$A$2:$AF$1139,31,0) -> 6 | X72: =VLOOKUP(V72,'BD2'!$A$2:$AF$1139,31,0) -> 8 | Y72: =IF(X72>W72,"Mejoría",IF(X72<W72,"Pérdida","Se mantiene")) -> Mejoría
A73: León | B73: =COUNTIFS('BD1'!H:H,Estadísticas!A73,'BD1'!X:X,"no") -> 12 | C73: =COUNTIFS('BD2'!H:H,Estadísticas!A73,'BD2'!X:X,"no") -> 31 | D73: =(COUNTIFS('BD1'!H:H,Estadísticas!A73,'BD1'!K:K,"ok") + COUNTIFS('BD1'!H:H,Estadísticas!A73,'BD1'!K:K,"sin video")) -> 217 | E73: =B73*100/D73 -> 5.5299539 | F73: =(D73-B73)*100/D73 -> 94.470046 | G73: =C73*100/D73 -> 14.285714 | H73: =(D73-C73)*100/D73 -> 85.714286 | V73: 322 | W73: =VLOOKUP(V73,'BD1'!$A$2:$AF$1139,31,0) -> 7 | X73: =VLOOKUP(V73,'BD2'!$A$2:$AF$1139,31,0) -> 8 | Y73: =IF(X73>W73,"Mejoría",IF(X73<W73,"Pérdida","Se mantiene")) -> Mejoría
A74: Silao | B74: =COUNTIFS('BD1'!H:H,Estadísticas!A74,'BD1'!X:X,"no") -> 5 | C74: =COUNTIFS('BD2'!H:H,Estadísticas!A74,'BD2'!X:X,"no") -> 0 | D74: =(COUNTIFS('BD1'!H:H,Estadísticas!A74,'BD1'!K:K,"ok") + COUNTIFS('BD1'!H:H,Estadísticas!A74,'BD1'!K:K,"sin video")) -> 47 | E74: =B74*100/D74 -> 10.638298 | F74: =(D74-B74)*100/D74 -> 89.361702 | G74: =C74*100/D74 -> 0 | H74: =(D74-C74)*100/D74 -> 100 | V74: 333 | W74: =VLOOKUP(V74,'BD1'!$A$2:$AF$1139,31,0) -> 7 | X74: =VLOOKUP(V74,'BD2'!$A$2:$AF$1139,31,0) -> 8 | Y74: =IF(X74>W74,"Mejoría",IF(X74<W74,"Pérdida","Se mantiene")) -> Mejoría
A75: Guanajuato | B75: =COUNTIFS('BD1'!H:H,Estadísticas!A75,'BD1'!X:X,"no") -> 11 | C75: =COUNTIFS('BD2'!H:H,Estadísticas!A75,'BD2'!X:X,"no") -> 13 | D75: =(COUNTIFS('BD1'!H:H,Estadísticas!A75,'BD1'!K:K,"ok") + COUNTIFS('BD1'!H:H,Estadísticas!A75,'BD1'!K:K,"sin video")) -> 55 | E75: =B75*100/D75 -> 20 | F75: =(D75-B75)*100/D75 -> 80 | G75: =C75*100/D75 -> 23.636364 | H75: =(D75-C75)*100/D75 -> 76.363636 | V75: 335 | W75: =VLOOKUP(V75,'BD1'!$A$2:$AF$1139,31,0) -> 0 | X75: =VLOOKUP(V75,'BD2'!$A$2:$AF$1139,31,0) -> 6 | Y75: =IF(X75>W75,"Mejoría",IF(X75<W75,"Pérdida","Se mantiene")) -> Mejoría
A76: Irapuato | B76: =COUNTIFS('BD1'!H:H,Estadísticas!A76,'BD1'!X:X,"no") -> 2 | C76: =COUNTIFS('BD2'!H:H,Estadísticas!A76,'BD2'!X:X,"no") -> 1 | D76: =(COUNTIFS('BD1'!H:H,Estadísticas!A76,'BD1'!K:K,"ok") + COUNTIFS('BD1'!H:H,Estadísticas!A76,'BD1'!K:K,"sin video")) -> 54 | E76: =B76*100/D76 -> 3.7037037 | F76: =(D76-B76)*100/D76 -> 96.296296 | G76: =C76*100/D76 -> 1.8518519 | H76: =(D76-C76)*100/D76 -> 98.148148 | V76: 339 | W76: =VLOOKUP(V76,'BD1'!$A$2:$AF$1139,31,0) -> 6 | X76: =VLOOKUP(V76,'BD2'!$A$2:$AF$1139,31,0) -> 8 | Y76: =IF(X76>W76,"Mejoría",IF(X76<W76,"Pérdida","Se mantiene")) -> Mejoría
A77: Salamanca | B77: =COUNTIFS('BD1'!H:H,Estadísticas!A77,'BD1'!X:X,"no") -> 3 | C77: =COUNTIFS('BD2'!H:H,Estadísticas!A77,'BD2'!X:X,"no") -> 6 | D77: =(COUNTIFS('BD1'!H:H,Estadísticas!A77,'BD1'!K:K,"ok") + COUNTIFS('BD1'!H:H,Estadísticas!A77,'BD1'!K:K,"sin video")) -> 20 | E77: =B77*100/D77 -> 15 | F77: =(D77-B77)*100/D77 -> 85 | G77: =C77*100/D77 -> 30 | H77: =(D77-C77)*100/D77 -> 70 | V77: 342 | W77: =VLOOKUP(V77,'BD1'!$A$2:$AF$1139,31,0) -> 8 | X77: =VLOOKUP(V77,'BD2'!$A$2:$AF$1139,31,0) -> 8 | Y77: =IF(X77>W77,"Mejoría",IF(X77<W77,"Pérdida","Se mantiene")) -> Se mantiene
A78: Celaya | B78: =COUNTIFS('BD1'!H:H,Estadísticas!A78,'BD1'!X:X,"no") -> 2 | C78: =COUNTIFS('BD2'!H:H,Estadísticas!A78,'BD2'!X:X,"no") -> 3 | D78: =(COUNTIFS('BD1'!H:H,Estadísticas!A78,'BD1'!K:K,"ok") + COUNTIFS('BD1'!H:H,Estadísticas!A78,'BD1'!K:K,"sin video")) -> 25 | E78: =B78*100/D78 -> 8 | F78: =(D78-B78)*100/D78 -> 92 | G78: =C78*100/D78 -> 12 | H78: =(D78-C78)*100/D78 -> 88 | V78: 345 | W78: =VLOOKUP(V78,'BD1'!$A$2:$AF$1139,31,0) -> 7 | X78: =VLOOKUP(V78,'BD2'!$A$2:$AF$1139,31,0) -> 8 | Y78: =IF(X78>W78,"Mejoría",IF(X78<W78,"Pérdida","Se mantiene")) -> Mejoría
V79: 352 | W79: =VLOOKUP(V79,'BD1'!$A$2:$AF$1139,31,0) -> 8 | X79: =VLOOKUP(V79,'BD2'!$A$2:$AF$1139,31,0) -> 3 | Y79: =IF(X79>W79,"Mejoría",IF(X79<W79,"Pérdida","Se mantiene")) -> Pérdida
A80: NEVAGACIÓN CONSTANTE | V80: 354 | W80: =VLOOKUP(V80,'BD1'!$A$2:$AF$1139,31,0) -> 7 | X80: =VLOOKUP(V80,'BD2'!$A$2:$AF$1139,31,0) -> 8 | Y80: =IF(X80>W80,"Mejoría",IF(X80<W80,"Pérdida","Se mantiene")) -> Mejoría
A81: MUNICIPIO | B81: ERROR 1 | C81: ERROR 2 | D81: TOTAL | E81: % ERROR 1 | F81: % ÉXITO 1 | G81: % ERROR 2 | H81: % ÉXITO 2 | V81: 355 | W81: =VLOOKUP(V81,'BD1'!$A$2:$AF$1139,31,0) -> 6 | X81: =VLOOKUP(V81,'BD2'!$A$2:$AF$1139,31,0) -> 8 | Y81: =IF(X81>W81,"Mejoría",IF(X81<W81,"Pérdida","Se mantiene")) -> Mejoría
A82: León | B82: =COUNTIFS('BD1'!H:H,Estadísticas!A82,'BD1'!Y:Y,"no") -> 25 | C82: =COUNTIFS('BD2'!H:H,Estadísticas!A82,'BD2'!Y:Y,"no") -> 33 | D82: =(COUNTIFS('BD1'!H:H,Estadísticas!A82,'BD1'!K:K,"ok") + COUNTIFS('BD1'!H:H,Estadísticas!A82,'BD1'!K:K,"sin video")) -> 217 | E82: =B82*100/D82 -> 11.520737 | F82: =(D82-B82)*100/D82 -> 88.479263 | G82: =C82*100/D82 -> 15.207373 | H82: =(D82-C82)*100/D82 -> 84.792627 | V82: 358 | W82: =VLOOKUP(V82,'BD1'!$A$2:$AF$1139,31,0) -> 8 | X82: =VLOOKUP(V82,'BD2'!$A$2:$AF$1139,31,0) -> 7 | Y82: =IF(X82>W82,"Mejoría",IF(X82<W82,"Pérdida","Se mantiene")) -> Pérdida
A83: Silao | B83: =COUNTIFS('BD1'!H:H,Estadísticas!A83,'BD1'!Y:Y,"no") -> 6 | C83: =COUNTIFS('BD2'!H:H,Estadísticas!A83,'BD2'!Y:Y,"no") -> 0 | D83: =(COUNTIFS('BD1'!H:H,Estadísticas!A83,'BD1'!K:K,"ok") + COUNTIFS('BD1'!H:H,Estadísticas!A83,'BD1'!K:K,"sin video")) -> 47 | E83: =B83*100/D83 -> 12.765957 | F83: =(D83-B83)*100/D83 -> 87.234043 | G83: =C83*100/D83 -> 0 | H83: =(D83-C83)*100/D83 -> 100 | V83: 359 | W83: =VLOOKUP(V83,'BD1'!$A$2:$AF$1139,31,0) -> 7 | X83: =VLOOKUP(V83,'BD2'!$A$2:$AF$1139,31,0) -> 8 | Y83: =IF(X83>W83,"Mejoría",IF(X83<W83,"Pérdida","Se mantiene")) -> Mejoría
A84: Guanajuato | B84: =COUNTIFS('BD1'!H:H,Estadísticas!A84,'BD1'!Y:Y,"no") -> 17 | C84: =COUNTIFS('BD2'!H:H,Estadísticas!A84,'BD2'!Y:Y,"no") -> 13 | D84: =(COUNTIFS('BD1'!H:H,Estadísticas!A84,'BD1'!K:K,"ok") + COUNTIFS('BD1'!H:H,Estadísticas!A84,'BD1'!K:K,"sin video")) -> 55 | E84: =B84*100/D84 -> 30.909091 | F84: =(D84-B84)*100/D84 -> 69.090909 | G84: =C84*100/D84 -> 23.636364 | H84: =(D84-C84)*100/D84 -> 76.363636 | V84: 360 | W84: =VLOOKUP(V84,'BD1'!$A$2:$AF$1139,31,0) -> 8 | X84: =VLOOKUP(V84,'BD2'!$A$2:$AF$1139,31,0) -> 8 | Y84: =IF(X84>W84,"Mejoría",IF(X84<W84,"Pérdida","Se mantiene")) -> Se mantiene
A85: Irapuato | B85: =COUNTIFS('BD1'!H:H,Estadísticas!A85,'BD1'!Y:Y,"no") -> 4 | C85: =COUNTIFS('BD2'!H:H,Estadísticas!A85,'BD2'!Y:Y,"no") -> 1 | D85: =(COUNTIFS('BD1'!H:H,Estadísticas!A85,'BD1'!K:K,"ok") + COUNTIFS('BD1'!H:H,Estadísticas!A85,'BD1'!K:K,"sin video")) -> 54 | E85: =B85*100/D85 -> 7.4074074 | F85: =(D85-B85)*100/D85 -> 92.592593 | G85: =C85*100/D85 -> 1.8518519 | H85: =(D85-C85)*100/D85 -> 98.148148 | V85: 361 | W85: =VLOOKUP(V85,'BD1'!$A$2:$AF$1139,31,0) -> 8 | X85: =VLOOKUP(V85,'BD2'!$A$2:$AF$1139,31,0) -> 8 | Y85: =IF(X85>W85,"Mejoría",IF(X85<W85,"Pérdida","Se mantiene")) -> Se mantiene
A86: Salamanca | B86: =COUNTIFS('BD1'!H:H,Estadísticas!A86,'BD1'!Y:Y,"no") -> 3 | C86: =COUNTIFS('BD2'!H:H,Estadísticas!A86,'BD2'!Y:Y,"no") -> 7 | D86: =(COUNTIFS('BD1'!H:H,Estadísticas!A86,'BD1'!K:K,"ok") + COUNTIFS('BD1'!H:H,Estadísticas!A86,'BD1'!K:K,"sin video")) -> 20 | E86: =B86*100/D86 -> 15 | F86: =(D86-B86)*100/D86 -> 85 | G86: =C86*100/D86 -> 35 | H86: =(D86-C86)*100/D86 -> 65 | V86: 369 | W86: =VLOOKUP(V86,'BD1'!$A$2:$AF$1139,31,0) -> 6 | X86: =VLOOKUP(V86,'BD2'!$A$2:$AF$1139,31,0) -> 8 | Y86: =IF(X86>W86,"Mejoría",IF(X86<W86,"Pérdida","Se mantiene")) -> Mejoría
A87: Celaya | B87: =COUNTIFS('BD1'!H:H,Estadísticas!A87,'BD1'!Y:Y,"no") -> 2 | C87: =COUNTIFS('BD2'!H:H,Estadísticas!A87,'BD2'!Y:Y,"no") -> 2 | D87: =(COUNTIFS('BD1'!H:H,Estadísticas!A87,'BD1'!K:K,"ok") + COUNTIFS('BD1'!H:H,Estadísticas!A87,'BD1'!K:K,"sin video")) -> 25 | E87: =B87*100/D87 -> 8 | F87: =(D87-B87)*100/D87 -> 92 | G87: =C87*100/D87 -> 8 | H87: =(D87-C87)*100/D87 -> 92 | V87: 372 | W87: =VLOOKUP(V87,'BD1'!$A$2:$AF$1139,31,0) -> 8 | X87: =VLOOKUP(V87,'BD2'!$A$2:$AF$1139,31,0) -> 8 | Y87: =IF(X87>W87,"Mejoría",IF(X87<W87,"Pérdida","Se mantiene")) -> Se mantiene
V88: 380 | W88: =VLOOKUP(V88,'BD1'!$A$2:$AF$1139,31,0) -> 8 | X88: =VLOOKUP(V88,'BD2'!$A$2:$AF$1139,31,0) -> 1 | Y88: =IF(X88>W88,"Mejoría",IF(X88<W88,"Pérdida","Se mantiene")) -> Pérdida
A89: BUEN ANCHO DE BANDA | V89: 381 | W89: =VLOOKUP(V89,'BD1'!$A$2:$AF$1139,31,0) -> 8 | X89: =VLOOKUP(V89,'BD2'!$A$2:$AF$1139,31,0) -> 8 | Y89: =IF(X89>W89,"Mejoría",IF(X89<W89,"Pérdida","Se mantiene")) -> Se mantiene
A90: MUNICIPIO | B90: ERROR 1 | C90: ERROR 2 | D90: TOTAL | E90: % ERROR 1 | F90: % ÉXITO 1 | G90: % ERROR 2 | H90: % ÉXITO 2 | V90: 382 | W90: =VLOOKUP(V90,'BD1'!$A$2:$AF$1139,31,0) -> 8 | X90: =VLOOKUP(V90,'BD2'!$A$2:$AF$1139,31,0) -> 8 | Y90: =IF(X90>W90,"Mejoría",IF(X90<W90,"Pérdida","Se mantiene")) -> Se mantiene
A91: León | B91: =COUNTIFS('BD1'!H:H,Estadísticas!A91,'BD1'!Z:Z,"no") -> 45 | C91: =COUNTIFS('BD2'!H:H,Estadísticas!A91,'BD2'!Z:Z,"no") -> 55 | D91: =(COUNTIFS('BD1'!H:H,Estadísticas!A91,'BD1'!K:K,"ok") + COUNTIFS('BD1'!H:H,Estadísticas!A91,'BD1'!K:K,"sin video")) -> 217 | E91: =B91*100/D91 -> 20.737327 | F91: =(D91-B91)*100/D91 -> 79.262673 | G91: =C91*100/D91 -> 25.345622 | H91: =(D91-C91)*100/D91 -> 74.654378 | V91: 384 | W91: =VLOOKUP(V91,'BD1'!$A$2:$AF$1139,31,0) -> 8 | X91: =VLOOKUP(V91,'BD2'!$A$2:$AF$1139,31,0) -> 8 | Y91: =IF(X91>W91,"Mejoría",IF(X91<W91,"Pérdida","Se mantiene")) -> Se mantiene
A92: Silao | B92: =COUNTIFS('BD1'!H:H,Estadísticas!A92,'BD1'!Z:Z,"no") -> 11 | C92: =COUNTIFS('BD2'!H:H,Estadísticas!A92,'BD2'!Z:Z,"no") -> 47 | D92: =(COUNTIFS('BD1'!H:H,Estadísticas!A92,'BD1'!K:K,"ok") + COUNTIFS('BD1'!H:H,Estadísticas!A92,'BD1'!K:K,"sin video")) -> 47 | E92: =B92*100/D92 -> 23.404255 | F92: =(D92-B92)*100/D92 -> 76.595745 | G92: =C92*100/D92 -> 100 | H92: =(D92-C92)*100/D92 -> 0 | V92: 385 | W92: =VLOOKUP(V92,'BD1'!$A$2:$AF$1139,31,0) -> 8 | X92: =VLOOKUP(V92,'BD2'!$A$2:$AF$1139,31,0) -> 6 | Y92: =IF(X92>W92,"Mejoría",IF(X92<W92,"Pérdida","Se mantiene")) -> Pérdida
A93: Guanajuato | B93: =COUNTIFS('BD1'!H:H,Estadísticas!A93,'BD1'!Z:Z,"no") -> 13 | C93: =COUNTIFS('BD2'!H:H,Estadísticas!A93,'BD2'!Z:Z,"no") -> 21 | D93: =(COUNTIFS('BD1'!H:H,Estadísticas!A93,'BD1'!K:K,"ok") + COUNTIFS('BD1'!H:H,Estadísticas!A93,'BD1'!K:K,"sin video")) -> 55 | E93: =B93*100/D93 -> 23.636364 | F93: =(D93-B93)*100/D93 -> 76.363636 | G93: =C93*100/D93 -> 38.181818 | H93: =(D93-C93)*100/D93 -> 61.818182 | V93: 386 | W93: =VLOOKUP(V93,'BD1'!$A$2:$AF$1139,31,0) -> 5 | X93: =VLOOKUP(V93,'BD2'!$A$2:$AF$1139,31,0) -> 8 | Y93: =IF(X93>W93,"Mejoría",IF(X93<W93,"Pérdida","Se mantiene")) -> Mejoría
A94: Irapuato | B94: =COUNTIFS('BD1'!H:H,Estadísticas!A94,'BD1'!Z:Z,"no") -> 11 | C94: =COUNTIFS('BD2'!H:H,Estadísticas!A94,'BD2'!Z:Z,"no") -> 41 | D94: =(COUNTIFS('BD1'!H:H,Estadísticas!A94,'BD1'!K:K,"ok") + COUNTIFS('BD1'!H:H,Estadísticas!A94,'BD1'!K:K,"sin video")) -> 54 | E94: =B94*100/D94 -> 20.37037 | F94: =(D94-B94)*100/D94 -> 79.62963 | G94: =C94*100/D94 -> 75.925926 | H94: =(D94-C94)*100/D94 -> 24.074074 | V94: 387 | W94: =VLOOKUP(V94,'BD1'!$A$2:$AF$1139,31,0) -> 8 | X94: =VLOOKUP(V94,'BD2'!$A$2:$AF$1139,31,0) -> 4 | Y94: =IF(X94>W94,"Mejoría",IF(X94<W94,"Pérdida","Se mantiene")) -> Pérdida
A95: Salamanca | B95: =COUNTIFS('BD1'!H:H,Estadísticas!A95,'BD1'!Z:Z,"no") -> 8 | C95: =COUNTIFS('BD2'!H:H,Estadísticas!A95,'BD2'!Z:Z,"no") -> 9 | D95: =(COUNTIFS('BD1'!H:H,Estadísticas!A95,'BD1'!K:K,"ok") + COUNTIFS('BD1'!H:H,Estadísticas!A95,'BD1'!K:K,"sin video")) -> 20 | E95: =B95*100/D95 -> 40 | F95: =(D95-B95)*100/D95 -> 60 | G95: =C95*100/D95 -> 45 | H95: =(D95-C95)*100/D95 -> 55 | V95: 388 | W95: =VLOOKUP(V95,'BD1'!$A$2:$AF$1139,31,0) -> 8 | X95: =VLOOKUP(V95,'BD2'!$A$2:$AF$1139,31,0) -> 8 | Y95: =IF(X95>W95,"Mejoría",IF(X95<W95,"Pérdida","Se mantiene")) -> Se mantiene
A96: Celaya | B96: =COUNTIFS('BD1'!H:H,Estadísticas!A96,'BD1'!Z:Z,"no") -> 6 | C96: =COUNTIFS('BD2'!H:H,Estadísticas!A96,'BD2'!Z:Z,"no") -> 8 | D96: =(COUNTIFS('BD1'!H:H,Estadísticas!A96,'BD1'!K:K,"ok") + COUNTIFS('BD1'!H:H,Estadísticas!A96,'BD1'!K:K,"sin video")) -> 25 | E96: =B96*100/D96 -> 24 | F96: =(D96-B96)*100/D96 -> 76 | G96: =C96*100/D96 -> 32 | H96: =(D96-C96)*100/D96 -> 68 | V96: 389 | W96: =VLOOKUP(V96,'BD1'!$A$2:$AF$1139,31,0) -> 8 | X96: =VLOOKUP(V96,'BD2'!$A$2:$AF$1139,31,0) -> 8 | Y96: =IF(X96>W96,"Mejoría",IF(X96<W96,"Pérdida","Se mantiene")) -> Se mantiene
V97: 396 | W97: =VLOOKUP(V97,'BD1'!$A$2:$AF$1139,31,0) -> 8 | X97: =VLOOKUP(V97,'BD2'!$A$2:$AF$1139,31,0) -> 7 | Y97: =IF(X97>W97,"Mejoría",IF(X97<W97,"Pérdida","Se mantiene")) -> Pérdida
V98: 400 | W98: =VLOOKUP(V98,'BD1'!$A$2:$AF$1139,31,0) -> 8 | X98: =VLOOKUP(V98,'BD2'!$A$2:$AF$1139,31,0) -> 8 | Y98: =IF(X98>W98,"Mejoría",IF(X98<W98,"Pérdida","Se mantiene")) -> Se mantiene
V99: 401 | W99: =VLOOKUP(V99,'BD1'!$A$2:$AF$1139,31,0) -> 8 | X99: =VLOOKUP(V99,'BD2'!$A$2:$AF$1139,31,0) -> 8 | Y99: =IF(X99>W99,"Mejoría",IF(X99<W99,"Pérdida","Se mantiene")) -> Se mantiene
V100: 412 | W100: =VLOOKUP(V100,'BD1'!$A$2:$AF$1139,31,0) -> 0 | X100: =VLOOKUP(V100,'BD2'!$A$2:$AF$1139,31,0) -> 8 | Y100: =IF(X100>W100,"Mejoría",IF(X100<W100,"Pérdida","Se mantiene")) -> Mejoría
V101: 416 | W101: =VLOOKUP(V101,'BD1'!$A$2:$AF$1139,31,0) -> 7 | X101: =VLOOKUP(V101,'BD2'!$A$2:$AF$1139,31,0) -> 8 | Y101: =IF(X101>W101,"Mejoría",IF(X101<W101,"Pérdida","Se mantiene")) -> Mejoría
...

Sheet BD1
A1: Sitio | B1: Tipo de conexión | C1: Tipo de espacio | D1: Tipo | E1: Nombre | F1: Ubicación | G1: Colonia | H1: Municipio | I1: Latitud | J1: Longitud | K1: Visitado | L1: Liga | M1: Aps | N1: Fecha de rev | O1: Día | P1: Mes | Q1: Año | R1: Visita | S1: Conexión fácil | T1: Mensajero | U1: Facebook | V1: Youtube | W1: Maps | X1: Navegador | Y1: Nav Constante | Z1: Buen ancho de banda | AA1: Bajada | AB1: Subida | AC1: Observaciones | AD1: Supervisor | AE1: Calificación | AF1: Situación
A2: 1 | B2: Fibra Óptica | C2: PLAZA PÚBLICA | D2: N/A | E2: CRUZ DE CANTERA (JUNTO A LAS CANCHAS DEL MALECON) | F2: CRUZ DE CANTERA SANTA FE | G2: COLONIA SANTA FE | H2: LEÓN | I2: 21.127368 | J2: -101.67531 | K2: ok | L2: =HYPERLINK("https://www.google.com/maps?q=" & I2 & "," & J2, "Ver en Google Maps") -> Ver en Google Maps | M2: 1 | N2: 45929 | O2: =DAY('BD1'!$N2) -> 29 | P2: =MONTH('BD1'!$N2) -> 9 | Q2: =YEAR('BD1'!$N2) -> 2025 | R2: 1 | S2: si | T2: si | U2: si | V2: si | W2: si | X2: si | Y2: si | Z2: si | AA2: 38.58 | AB2: 99.83 | AC2: La conexión fue rápida y constante, la navegación fue fluida, no se observan anomalías, tiene buena señal | AD2: José Mosqueda | AE2: =COUNTIF(S2:Z2, "si") -> 8 | AF2: =IF('BD1'!$AE2=8,"Estable",(IF('BD1'!$AE2=7,"Funcional con observaciones", (IF('BD1'!$AE2=6,"Funcional con observaciones",(IF('BD1'!$AE2=5,"Rendimiento bajo",(IF('BD1'!$AE2=4,"Parcialmente funcional",(IF('BD1'!$AE2=3,"Parcialmente funcional",(IF('BD1'!$AE2=2,"Inoperativo",(IF('BD1'!$AE2=1,"Inoperativo","Crítico"))))))))))))))) -> Estable
A3: 2 | B3: Fibra Óptica | C3: PLAZA PÚBLICA | D3: N/A | E3: JARDINES DE SAN SEBASTIAN | F3: JARDINES DE SAN SEBASTIAN II | G3: COLONIA SAN SEBASTIAN | H3: LEÓN | I3: 21.099483 | J3: -101.6999 | K3: ok | L3: =HYPERLINK("https://www.google.com/maps?q=" & I3 & "," & J3, "Ver en Google Maps") -> Ver en Google Maps | M3: 1 | N3: 45932 | O3: =DAY('BD1'!$N3) -> 2 | P3: =MONTH('BD1'!$N3) -> 10 | Q3: =YEAR('BD1'!$N3) -> 2025 | R3: 1 | S3: si | T3: si | U3: si | V3: si | W3: si | X3: si | Y3: si | Z3: si | AA3: 15.85 | AB3: 11.85 | AC3: La conexión fue rápida y constante, la navegación fue fluida, no se observan anomalías, tiene buena señal | AD3: José Mosqueda | AE3: =COUNTIF(S3:Z3, "si") -> 8 | AF3: =IF('BD1'!$AE3=8,"Estable",(IF('BD1'!$AE3=7,"Funcional con observaciones", (IF('BD1'!$AE3=6,"Funcional con observaciones",(IF('BD1'!$AE3=5,"Rendimiento bajo",(IF('BD1'!$AE3=4,"Parcialmente funcional",(IF('BD1'!$AE3=3,"Parcialmente funcional",(IF('BD1'!$AE3=2,"Inoperativo",(IF('BD1'!$AE3=1,"Inoperativo","Crítico"))))))))))))))) -> Estable
A4: 3 | B4: Fibra Óptica | C4: PLAZA PÚBLICA | D4: N/A | E4: PLAZA COMUNITARIA VILLA DE LAS FLORES | F4: HEROES DE LA INDEPENDENCIA VILLA DE LAS FLORES | G4: COLONIA VILLA DE LAS FLORES | H4: LEÓN | I4: 21.122248 | J4: -101.6506 | K4: ok | L4: =HYPERLINK("https://www.google.com/maps?q=" & I4 & "," & J4, "Ver en Google Maps") -> Ver en Google Maps | M4: 1 | N4: 45931 | O4: =DAY('BD1'!$N4) -> 1 | P4: =MONTH('BD1'!$N4) -> 10 | Q4: =YEAR('BD1'!$N4) -> 2025 | R4: 1 | S4: si | T4: si | U4: si | V4: si | W4: si | X4: si | Y4: si | Z4: si | AA4: 22.41 | AB4: 29.07 | AC4: La conexión fue rápida y constante, la navegación fue fluida, no se observan anomalías, tiene buena señal | AD4: José Mosqueda | AE4: =COUNTIF(S4:Z4, "si") -> 8 | AF4: =IF('BD1'!$AE4=8,"Estable",(IF('BD1'!$AE4=7,"Funcional con observaciones", (IF('BD1'!$AE4=6,"Funcional con observaciones",(IF('BD1'!$AE4=5,"Rendimiento bajo",(IF('BD1'!$AE4=4,"Parcialmente funcional",(IF('BD1'!$AE4=3,"Parcialmente funcional",(IF('BD1'!$AE4=2,"Inoperativo",(IF('BD1'!$AE4=1,"Inoperativo","Crítico"))))))))))))))) -> Estable
A5: 4 | B5: Fibra Óptica | C5: PLAZA PÚBLICA | D5: N/A | E5: PLAZA PUBLICA EL LUCERO | F5: MARFIX EL LUCERO II | G5: COLONIA EL LUCERO | H5: LEÓN | I5: 21.136565 | J5: -101.66825 | K5: ok | L5: =HYPERLINK("https://www.google.com/maps?q=" & I5 & "," & J5, "Ver en Google Maps") -> Ver en Google Maps | M5: 1 | N5: 45930 | O5: =DAY('BD1'!$N5) -> 30 | P5: =MONTH('BD1'!$N5) -> 9 | Q5: =YEAR('BD1'!$N5) -> 2025 | R5: 1 | S5: si | T5: si | U5: si | V5: si | W5: si | X5: si | Y5: si | Z5: si | AA5: 16.96 | AB5: 20.38 | AC5: La conexión fue rápida y constante, la navegación fue fluida, no se observan anomalías, tiene buena señal | AD5: José Mosqueda | AE5: =COUNTIF(S5:Z5, "si") -> 8 | AF5: =IF('BD1'!$AE5=8,"Estable",(IF('BD1'!$AE5=7,"Funcional con observaciones", (IF('BD1'!$AE5=6,"Funcional con observaciones",(IF('BD1'!$AE5=5,"Rendimiento bajo",(IF('BD1'!$AE5=4,"Parcialmente funcional",(IF('BD1'!$AE5=3,"Parcialmente funcional",(IF('BD1'!$AE5=2,"Inoperativo",(IF('BD1'!$AE5=1,"Inoperativo","Crítico"))))))))))))))) -> Estable
A6: 5 | B6: Fibra Óptica | C6: ESPACIO DEPORTIVO | D6: N/A | E6: AGUA AZUL | F6: DELTA AGUA AZUL | G6: COLONIA AGUA AZUL | H6: LEÓN | I6: 21.103264 | J6: -101.61151 | K6: ok | L6: =HYPERLINK("https://www.google.com/maps?q=" & I6 & "," & J6, "Ver en Google Maps") -> Ver en Google Maps | M6: 1 | N6: 45931 | O6: =DAY('BD1'!$N6) -> 1 | P6: =MONTH('BD1'!$N6) -> 10 | Q6: =YEAR('BD1'!$N6) -> 2025 | R6: 1 | S6: si | T6: si | U6: si | V6: si | W6: si | X6: si | Y6: si | Z6: si | AA6: 24.05 | AB6: 33.33 | AC6: La conexión fue rápida y constante, la navegación fue fluida, no se observan anomalías, tiene buena señal | AD6: José Mosqueda | AE6: =COUNTIF(S6:Z6, "si") -> 8 | AF6: =IF('BD1'!$AE6=8,"Estable",(IF('BD1'!$AE6=7,"Funcional con observaciones", (IF('BD1'!$AE6=6,"Funcional con observaciones",(IF('BD1'!$AE6=5,"Rendimiento bajo",(IF('BD1'!$AE6=4,"Parcialmente funcional",(IF('BD1'!$AE6=3,"Parcialmente funcional",(IF('BD1'!$AE6=2,"Inoperativo",(IF('BD1'!$AE6=1,"Inoperativo","Crítico"))))))))))))))) -> Estable
A7: 6 | B7: Fibra Óptica | C7: ESPACIO DEPORTIVO | D7: N/A | E7: LOS ANGELES | F7: VALLE DE LOS NOGALES ANGELES, LOS | G7: COLONIA LOS ANGELES | H7: LEÓN | I7: 21.131813 | J7: -101.64046 | K7: ok | L7: =HYPERLINK("https://www.google.com/maps?q=" & I7 & "," & J7, "Ver en Google Maps") -> Ver en Google Maps | M7: 1 | N7: 45929 | O7: =DAY('BD1'!$N7) -> 29 | P7: =MONTH('BD1'!$N7) -> 9 | Q7: =YEAR('BD1'!$N7) -> 2025 | R7: 1 | S7: si | T7: si | U7: si | V7: si | W7: si | X7: si | Y7: si | Z7: si | AA7: 44.23 | AB7: 12.18 | AC7: La conexión fue rápida y constante, la navegación fue fluida, no se observan anomalías, tiene buena señal | AD7: José Mosqueda | AE7: =COUNTIF(S7:Z7, "si") -> 8 | AF7: =IF('BD1'!$AE7=8,"Estable",(IF('BD1'!$AE7=7,"Funcional con observaciones", (IF('BD1'!$AE7=6,"Funcional con observaciones",(IF('BD1'!$AE7=5,"Rendimiento bajo",(IF('BD1'!$AE7=4,"Parcialmente funcional",(IF('BD1'!$AE7=3,"Parcialmente funcional",(IF('BD1'!$AE7=2,"Inoperativo",(IF('BD1'!$AE7=1,"Inoperativo","Crítico"))))))))))))))) -> Estable
A8: 7 | B8: Fibra Óptica | C8: ESPACIO DEPORTIVO | D8: N/A | E8: CENTRO DEPORTIVO LAS JOYAS | F8: BALCÓN DE LOS RUISEÑORES 208, BALCONES DE LA JOYA, 37355 LEÓN, GTO. | G8: COLONIA BALCONES DE LA JOYA | H8: LEÓN | I8: 21.12784 | J8: -101.74435 | K8: ok | L8: =HYPERLINK("https://www.google.com/maps?q=" & I8 & "," & J8, "Ver en Google Maps") -> Ver en Google Maps | M8: 1 | N8: 45930 | O8: =DAY('BD1'!$N8) -> 30 | P8: =MONTH('BD1'!$N8) -> 9 | Q8: =YEAR('BD1'!$N8) -> 2025 | R8: 1 | S8: si | T8: si | U8: si | V8: si | W8: si | X8: si | Y8: si | Z8: si | AA8: 24.94 | AB8: 11.13 | AC8: La conexión fue rápida y constante, la navegación fue fluida, no se observan anomalías, tiene buena señal | AD8: José Mosqueda | AE8: =COUNTIF(S8:Z8, "si") -> 8 | AF8: =IF('BD1'!$AE8=8,"Estable",(IF('BD1'!$AE8=7,"Funcional con observaciones", (IF('BD1'!$AE8=6,"Funcional con observaciones",(IF('BD1'!$AE8=5,"Rendimiento bajo",(IF('BD1'!$AE8=4,"Parcialmente funcional",(IF('BD1'!$AE8=3,"Parcialmente funcional",(IF('BD1'!$AE8=2,"Inoperativo",(IF('BD1'!$AE8=1,"Inoperativo","Crítico"))))))))))))))) -> Estable
A9: 8 | B9: Fibra Óptica | C9: ESPACIO DEPORTIVO | D9: N/A | E9: DEPORTIVA I (UNIDAD DEPORTIVA I) | F9: TABLERO DEPORTIVA I | G9: COLONIA LEÓN I | H9: LEÓN | I9: 21.145551 | J9: -101.65661 | K9: ok | L9: =HYPERLINK("https://www.google.com/maps?q=" & I9 & "," & J9, "Ver en Google Maps") -> Ver en Google Maps | M9: 1 | N9: 45929 | O9: =DAY('BD1'!$N9) -> 29 | P9: =MONTH('BD1'!$N9) -> 9 | Q9: =YEAR('BD1'!$N9) -> 2025 | R9: 1 | S9: si | T9: si | U9: si | V9: si | W9: si | X9: si | Y9: si | Z9: si | AA9: 82.91 | AB9: 82.39 | AC9: La conexión fue rápida y constante, la navegación fue fluida, no se observan anomalías, tiene buena señal | AD9: José Mosqueda | AE9: =COUNTIF(S9:Z9, "si") -> 8 | AF9: =IF('BD1'!$AE9=8,"Estable",(IF('BD1'!$AE9=7,"Funcional con observaciones", (IF('BD1'!$AE9=6,"Funcional con observaciones",(IF('BD1'!$AE9=5,"Rendimiento bajo",(IF('BD1'!$AE9=4,"Parcialmente funcional",(IF('BD1'!$AE9=3,"Parcialmente funcional",(IF('BD1'!$AE9=2,"Inoperativo",(IF('BD1'!$AE9=1,"Inoperativo","Crítico"))))))))))))))) -> Estable
A10: 9 | B10: Fibra Óptica | C10: ESPACIO DEPORTIVO | D10: N/A | E10: ECHEVESTE 2000 | F10: NABO ECHEVESTE 2000 | G10: COLONIA ECHEVESTE 2000 | H10: LEÓN | I10: 21.179691 | J10: -101.67001 | K10: ok | L10: =HYPERLINK("https://www.google.com/maps?q=" & I10 & "," & J10, "Ver en Google Maps") -> Ver en Google Maps | M10: 1 | N10: 45929 | O10: =DAY('BD1'!$N10) -> 29 | P10: =MONTH('BD1'!$N10) -> 9 | Q10: =YEAR('BD1'!$N10) -> 2025 | R10: 1 | S10: si | T10: si | U10: si | V10: si | W10: si | X10: si | Y10: si | Z10: no | AA10: 10.92 | AB10: 11.86 | AC10: La conexión fue rápida y constante, la navegación fue fluida, no se observan anomalías, tiene buena señal, el ancho de banda es bajo sobre todo en la descarga | AD10: José Mosqueda | AE10: =COUNTIF(S10:Z10, "si") -> 7 | AF10: =IF('BD1'!$AE10=8,"Estable",(IF('BD1'!$AE10=7,"Funcional con observaciones", (IF('BD1'!$AE10=6,"Funcional con observaciones",(IF('BD1'!$AE10=5,"Rendimiento bajo",(IF('BD1'!$AE10=4,"Parcialmente funcional",(IF('BD1'!$AE10=3,"Parcialmente funcional",(IF('BD1'!$AE10=2,"Inoperativo",(IF('BD1'!$AE10=1,"Inoperativo","Crítico"))))))))))))))) -> Funcional con observaciones
A11: 10 | B11: Fibra Óptica | C11: ESPACIO DEPORTIVO | D11: N/A | E11: ECHEVESTE | F11: HERMENEGILDO BUSTOS HACIENDA ECHEVESTE | G11: COLONIA HACIENDA ECHEVESTE | H11: LEÓN | I11: 21.187876 | J11: -101.66685 | K11: ok | L11: =HYPERLINK("https://www.google.com/maps?q=" & I11 & "," & J11, "Ver en Google Maps") -> Ver en Google Maps | M11: 1 | N11: 45929 | O11: =DAY('BD1'!$N11) -> 29 | P11: =MONTH('BD1'!$N11) -> 9 | Q11: =YEAR('BD1'!$N11) -> 2025 | R11: 1 | S11: si | T11: si | U11: si | V11: si | W11: si | X11: si | Y11: si | Z11: si | AA11: 41.69 | AB11: 29.36 | AC11: La conexión fue rápida y constante, la navegación fue fluida, no se observan anomalías, tiene buena señal | AD11: José Mosqueda | AE11: =COUNTIF(S11:Z11, "si") -> 8 | AF11: =IF('BD1'!$AE11=8,"Estable",(IF('BD1'!$AE11=7,"Funcional con observaciones", (IF('BD1'!$AE11=6,"Funcional con observaciones",(IF('BD1'!$AE11=5,"Rendimiento bajo",(IF('BD1'!$AE11=4,"Parcialmente funcional",(IF('BD1'!$AE11=3,"Parcialmente funcional",(IF('BD1'!$AE11=2,"Inoperativo",(IF('BD1'!$AE11=1,"Inoperativo","Crítico"))))))))))))))) -> Estable
A12: 11 | B12: Fibra Óptica | C12: ESPACIO DEPORTIVO | D12: N/A | E12: PARQUE IV CENTENARIO | F12: MONTE DE LAS CRUCES HIDALGO | G12: COLONIA HIDALGO | H12: LEÓN | I12: 21.143558 | J12: -101.66958 | K12: ok | L12: =HYPERLINK("https://www.google.com/maps?q=" & I12 & "," & J12, "Ver en Google Maps") -> Ver en Google Maps | M12: 1 | N12: 45929 | O12: =DAY('BD1'!$N12) -> 29 | P12: =MONTH('BD1'!$N12) -> 9 | Q12: =YEAR('BD1'!$N12) -> 2025 | R12: 1 | S12: si | T12: si | U12: si | V12: si | W12: si | X12: si | Y12: si | Z12: si | AA12: 51.76 | AB12: 54.04 | AC12: La conexión fue rápida y constante, la navegación fue fluida, no se observan anomalías, tiene buena señal | AD12: José Mosqueda | AE12: =COUNTIF(S12:Z12, "si") -> 8 | AF12: =IF('BD1'!$AE12=8,"Estable",(IF('BD1'!$AE12=7,"Funcional con observaciones", (IF('BD1'!$AE12=6,"Funcional con observaciones",(IF('BD1'!$AE12=5,"Rendimiento bajo",(IF('BD1'!$AE12=4,"Parcialmente funcional",(IF('BD1'!$AE12=3,"Parcialmente funcional",(IF('BD1'!$AE12=2,"Inoperativo",(IF('BD1'!$AE12=1,"Inoperativo","Crítico"))))))))))))))) -> Estable
A13: 12 | B13: Fibra Óptica | C13: ESPACIO DEPORTIVO | D13: N/A | E13: PARQUE EXTREMO LAS HILAMAS | F13: MARIANO ESCOBEDO LOMAS DE LAS HILAMAS | G13: COLONIA LOMAS DE LAS HILAMAS | H13: LEÓN | I13: 21.110986 | J13: -101.72374 | K13: ok | L13: =HYPERLINK("https://www.google.com/maps?q=" & I13 & "," & J13, "Ver en Google Maps") -> Ver en Google Maps | M13: 2 | N13: 45933 | O13: =DAY('BD1'!$N13) -> 3 | P13: =MONTH('BD1'!$N13) -> 10 | Q13: =YEAR('BD1'!$N13) -> 2025 | R13: 1 | S13: si | T13: si | U13: si | V13: si | W13: si | X13: si | Y13: si | Z13: si | AA13: 26.73 | AB13: 46.48 | AC13: La conexión fue rápida y constante, la navegación fue fluida, no se observan anomalías, tiene buena señal | AD13: José Mosqueda | AE13: =COUNTIF(S13:Z13, "si") -> 8 | AF13: =IF('BD1'!$AE13=8,"Estable",(IF('BD1'!$AE13=7,"Funcional con observaciones", (IF('BD1'!$AE13=6,"Funcional con observaciones",(IF('BD1'!$AE13=5,"Rendimiento bajo",(IF('BD1'!$AE13=4,"Parcialmente funcional",(IF('BD1'!$AE13=3,"Parcialmente funcional",(IF('BD1'!$AE13=2,"Inoperativo",(IF('BD1'!$AE13=1,"Inoperativo","Crítico"))))))))))))))) -> Estable
A14: 13a | B14: Fibra Óptica | C14: ESPACIO DEPORTIVO | D14: N/A | E14: PARQUE DEL ARBOL | F14: TORRES LANDA, JUAN JOSE SAN NICOLAS | G14: COLONIA SAN NICOLAS | H14: LEÓN | I14: 21.102383 | J14: -101.67667 | K14: ok | L14: =HYPERLINK("https://www.google.com/maps?q=" & I14 & "," & J14, "Ver en Google Maps") -> Ver en Google Maps | M14: 3 | N14: 45932 | O14: =DAY('BD1'!$N14) -> 2 | P14: =MONTH('BD1'!$N14) -> 10 | Q14: =YEAR('BD1'!$N14) -> 2025 | R14: 1 | S14: si | T14: si | U14: si | V14: si | W14: si | X14: si | Y14: si | Z14: si | AA14: 19.33 | AB14: 4.61 | AC14: La conexión fue rápida y constante, la navegación fue fluida, no se observan anomalías, tiene buena señal | AD14: José Mosqueda | AE14: =COUNTIF(S14:Z14, "si") -> 8 | AF14: =IF('BD1'!$AE14=8,"Estable",(IF('BD1'!$AE14=7,"Funcional con observaciones", (IF('BD1'!$AE14=6,"Funcional con observaciones",(IF('BD1'!$AE14=5,"Rendimiento bajo",(IF('BD1'!$AE14=4,"Parcialmente funcional",(IF('BD1'!$AE14=3,"Parcialmente funcional",(IF('BD1'!$AE14=2,"Inoperativo",(IF('BD1'!$AE14=1,"Inoperativo","Crítico"))))))))))))))) -> Estable
A15: 13b | B15: Fibra Óptica | C15: ESPACIO DEPORTIVO | D15: N/A | E15: PARQUE DEL ARBOL | F15: TORRES LANDA, JUAN JOSE SAN NICOLAS | G15: COLONIA SAN NICOLAS | H15: LEÓN | I15: 21.103049 | J15: -101.67521 | K15: ok | L15: =HYPERLINK("https://www.google.com/maps?q=" & I15 & "," & J15, "Ver en Google Maps") -> Ver en Google Maps | M15: 3 | N15: 45932 | O15: =DAY('BD1'!$N15) -> 2 | P15: =MONTH('BD1'!$N15) -> 10 | Q15: =YEAR('BD1'!$N15) -> 2025 | R15: 1 | S15: si | T15: si | U15: si | V15: si | W15: si | X15: si | Y15: si | Z15: no | AA15: 13.7 | AB15: 13.82 | AC15: La conexión fue rápida y constante, la navegación fue fluida, no se observan anomalías, tiene buena señal aunque un poco bajo el ancho de banda | AD15: José Mosqueda | AE15: =COUNTIF(S15:Z15, "si") -> 7 | AF15: =IF('BD1'!$AE15=8,"Estable",(IF('BD1'!$AE15=7,"Funcional con observaciones", (IF('BD1'!$AE15=6,"Funcional con observaciones",(IF('BD1'!$AE15=5,"Rendimiento bajo",(IF('BD1'!$AE15=4,"Parcialmente funcional",(IF('BD1'!$AE15=3,"Parcialmente funcional",(IF('BD1'!$AE15=2,"Inoperativo",(IF('BD1'!$AE15=1,"Inoperativo","Crítico"))))))))))))))) -> Funcional con observaciones
A16: 14 | B16: Fibra Óptica | C16: ESPACIO DEPORTIVO | D16: N/A | E16: MINIDEPORTIVA LOMA DORADA | F16: BLVD. MINERAL DE LA JOYA TORRES DORADAS | G16: COLONIA LOMA DORADA | H16: LEÓN | I16: 21.137276 | J16: -101.76616 | K16: ok | L16: =HYPERLINK("https://www.google.com/maps?q=" & I16 & "," & J16, "Ver en Google Maps") -> Ver en Google Maps | M16: 1 | N16: 45930 | O16: =DAY('BD1'!$N16) -> 30 | P16: =MONTH('BD1'!$N16) -> 9 | Q16: =YEAR('BD1'!$N16) -> 2025 | R16: 1 | S16: si | T16: si | U16: si | V16: si | W16: si | X16: si | Y16: si | Z16: si | AA16: 24.28 | AB16: 8.78 | AC16: La conexión fue rápida y constante, la navegación fue fluida, no se observan anomalías, tiene buena señal | AD16: José Mosqueda | AE16: =COUNTIF(S16:Z16, "si") -> 8 | AF16: =IF('BD1'!$AE16=8,"Estable",(IF('BD1'!$AE16=7,"Funcional con observaciones", (IF('BD1'!$AE16=6,"Funcional con observaciones",(IF('BD1'!$AE16=5,"Rendimiento bajo",(IF('BD1'!$AE16=4,"Parcialmente funcional",(IF('BD1'!$AE16=3,"Parcialmente funcional",(IF('BD1'!$AE16=2,"Inoperativo",(IF('BD1'!$AE16=1,"Inoperativo","Crítico"))))))))))))))) -> Estable
A17: 15 | B17: Fibra Óptica | C17: ESPACIO DEPORTIVO | D17: N/A | E17: VALLE DE SEÑORA I | F17: AVOGADRO VALLE DE SEÑORA | G17: COLONIA VALLE DE SEÑORA | H17: LEÓN | I17: 21.15992 | J17: -101.65658 | K17: ok | L17: =HYPERLINK("https://www.google.com/maps?q=" & I17 & "," & J17, "Ver en Google Maps") -> Ver en Google Maps | M17: 1 | N17: 45931 | O17: =DAY('BD1'!$N17) -> 1 | P17: =MONTH('BD1'!$N17) -> 10 | Q17: =YEAR('BD1'!$N17) -> 2025 | R17: 1 | S17: si | T17: si | U17: si | V17: si | W17: si | X17: si | Y17: si | Z17: si | AA17: 42.29 | AB17: 25.19 | AC17: La conexión fue rápida y constante, la navegación fue fluida, no se observan anomalías, tiene buena señal | AD17: José Mosqueda | AE17: =COUNTIF(S17:Z17, "si") -> 8 | AF17: =IF('BD1'!$AE17=8,"Estable",(IF('BD1'!$AE17=7,"Funcional con observaciones", (IF('BD1'!$AE17=6,"Funcional con observaciones",(IF('BD1'!$AE17=5,"Rendimiento bajo",(IF('BD1'!$AE17=4,"Parcialmente funcional",(IF('BD1'!$AE17=3,"Parcialmente funcional",(IF('BD1'!$AE17=2,"Inoperativo",(IF('BD1'!$AE17=1,"Inoperativo","Crítico"))))))))))))))) -> Estable
A18: 16 | B18: Fibra Óptica | C18: PRESIDENCIA | D18: N/A | E18: PRESIDENCIA MUNICIPAL DE LEÓN DE LOS ALDAMA | F18: PLAZA PRINCIPAL | G18: COLONIA CENTRO | H18: LEÓN | I18: 21.12176 | J18: -101.68234 | K18: ok | L18: =HYPERLINK("https://www.google.com/maps?q=" & I18 & "," & J18, "Ver en Google Maps") -> Ver en Google Maps | M18: 3 | N18: 45929 | O18: =DAY('BD1'!$N18) -> 29 | P18: =MONTH('BD1'!$N18) -> 9 | Q18: =YEAR('BD1'!$N18) -> 2025 | R18: 1 | S18: si | T18: si | U18: si | V18: si | W18: si | X18: si | Y18: si | Z18: si | AA18: 32.22 | AB18: 42.12 | AC18: La conexión fue rápida y constante, la navegación fue fluida, no se observan anomalías, tiene buena señal | AD18: José Mosqueda | AE18: =COUNTIF(S18:Z18, "si") -> 8 | AF18: =IF('BD1'!$AE18=8,"Estable",(IF('BD1'!$AE18=7,"Funcional con observaciones", (IF('BD1'!$AE18=6,"Funcional con observaciones",(IF('BD1'!$AE18=5,"Rendimiento bajo",(IF('BD1'!$AE18=4,"Parcialmente funcional",(IF('BD1'!$AE18=3,"Parcialmente funcional",(IF('BD1'!$AE18=2,"Inoperativo",(IF('BD1'!$AE18=1,"Inoperativo","Crítico"))))))))))))))) -> Estable
A19: 88 | B19: Fibra Óptica | C19: CENTRO DE INVESTIGACIÓN | D19: N/A | E19: HUB-I CASA DEL EMPRENDEDOR LEÓN | F19: CALLE JULIÁN DE OBREGÓN 245, OBREGÓN, 37320 LEÓN DE LOS ALDAMA, GTO. | G19: COLONIA LA MARTINICA | H19: LEÓN | I19: 21.129923 | J19: -101.68584 | L19: =HYPERLINK("https://www.google.com/maps?q=" & I19 & "," & J19, "Ver en Google Maps") -> Ver en Google Maps | M19: 2
A20: 89 | B20: Fibra Óptica | C20: ESCUELA | D20: SECUNDARIA | E20: 11EPR0645S -SECUNDARIA ANEXA NORMAL OFICIAL | F20: MERCURIO S/N, EL LUCERO, 37249, LEON DE LOS ALDAMA | G20: COLONIA EL LUCERO | H20: LEÓN | I20: 21.13566 | J20: -101.66829 | K20: ok | L20: =HYPERLINK("https://www.google.com/maps?q=" & I20 & "," & J20, "Ver en Google Maps") -> Ver en Google Maps | M20: 1 | N20: 45929 | O20: =DAY('BD1'!$N20) -> 29 | P20: =MONTH('BD1'!$N20) -> 9 | Q20: =YEAR('BD1'!$N20) -> 2025 | R20: 1 | S20: si | T20: si | U20: si | V20: si | W20: si | X20: si | Y20: no | Z20: no | AA20: 8.78 | AB20: 37 | AC20: La conexión es intermitente y tiene pocos megas de bajada, puede deberse a que el acces point está lejos de la calle y no se nos permitió el ingreso al plantel | AD20: José Mosqueda | AE20: =COUNTIF(S20:Z20, "si") -> 6 | AF20: =IF('BD1'!$AE20=8,"Estable",(IF('BD1'!$AE20=7,"Funcional con observaciones", (IF('BD1'!$AE20=6,"Funcional con observaciones",(IF('BD1'!$AE20=5,"Rendimiento bajo",(IF('BD1'!$AE20=4,"Parcialmente funcional",(IF('BD1'!$AE20=3,"Parcialmente funcional",(IF('BD1'!$AE20=2,"Inoperativo",(IF('BD1'!$AE20=1,"Inoperativo","Crítico"))))))))))))))) -> Funcional con observaciones
A21: 92 | B21: Fibra Óptica | C21: ESCUELA | D21: PREESCOLAR | E21: 11DJN4405E - OVIDIO DECROLY | F21: CALLE CHIMALPOPOCA NUMERO EXTERIOR: 102 , COLONIA AZTECAS, CODIGO | G21: COLONIA AZTECAS | H21: LEÓN | I21: 21.10199 | J21: -101.65482 | K21: ok | L21: =HYPERLINK("https://www.google.com/maps?q=" & I21 & "," & J21, "Ver en Google Maps") -> Ver en Google Maps | M21: 1 | N21: 45934 | O21: =DAY('BD1'!$N21) -> 4 | P21: =MONTH('BD1'!$N21) -> 10 | Q21: =YEAR('BD1'!$N21) -> 2025 | R21: 1 | S21: si | T21: si | U21: si | V21: si | W21: si | X21: si | Y21: si | Z21: si | AA21: 21.54 | AB21: 10.94 | AC21: La conexión fue rápida y constante, la navegación fue fluida, no se observan anomalías, tiene buena señal | AD21: José Mosqueda | AE21: =COUNTIF(S21:Z21, "si") -> 8 | AF21: =IF('BD1'!$AE21=8,"Estable",(IF('BD1'!$AE21=7,"Funcional con observaciones", (IF('BD1'!$AE21=6,"Funcional con observaciones",(IF('BD1'!$AE21=5,"Rendimiento bajo",(IF('BD1'!$AE21=4,"Parcialmente funcional",(IF('BD1'!$AE21=3,"Parcialmente funcional",(IF('BD1'!$AE21=2,"Inoperativo",(IF('BD1'!$AE21=1,"Inoperativo","Crítico"))))))))))))))) -> Estable
A22: 96 | B22: Fibra Óptica | C22: ESCUELA | D22: SECUNDARIA | E22: 11DES0015Y - SECUNDARIA GENERAL DIEGO RIVERA | F22: AVENIDA PANORAMA Y VALLE DE OLIVO S/N | G22: COLONIA PANORAMA | H22: LEÓN | I22: 21.15465 | J22: -101.69157 | K22: ok | L22: =HYPERLINK("https://www.google.com/maps?q=" & I22 & "," & J22, "Ver en Google Maps") -> Ver en Google Maps | M22: 2 | N22: 45929 | O22: =DAY('BD1'!$N22) -> 29 | P22: =MONTH('BD1'!$N22) -> 9 | Q22: =YEAR('BD1'!$N22) -> 2025 | R22: 1 | S22: si | T22: si | U22: si | V22: si | W22: si | X22: si | Y22: si | Z22: si | AA22: 51 | AB22: 72.76 | AC22: La conexión fue rápida y constante, la navegación fue fluida, no se observan anomalías, tiene buena señal | AD22: José Mosqueda | AE22: =COUNTIF(S22:Z22, "si") -> 8 | AF22: =IF('BD1'!$AE22=8,"Estable",(IF('BD1'!$AE22=7,"Funcional con observaciones", (IF('BD1'!$AE22=6,"Funcional con observaciones",(IF('BD1'!$AE22=5,"Rendimiento bajo",(IF('BD1'!$AE22=4,"Parcialmente funcional",(IF('BD1'!$AE22=3,"Parcialmente funcional",(IF('BD1'!$AE22=2,"Inoperativo",(IF('BD1'!$AE22=1,"Inoperativo","Crítico"))))))))))))))) -> Estable
A23: 101 | B23: Fibra Óptica | C23: ESCUELA | D23: PREESCOLAR | E23: 11DJN0269Q - DR. D. FRANCISCO LEAL | F23: CALLE ALICIA NUMERO EXTERIOR: 305 , COLONIA ORIENTAL, CODIGO POST | G23: COLONIA ORIENTAL | H23: LEÓN | I23: 21.106586 | J23: -101.65309 | K23: ok | L23: =HYPERLINK("https://www.google.com/maps?q=" & I23 & "," & J23, "Ver en Google Maps") -> Ver en Google Maps | M23: 1 | N23: 45934 | O23: =DAY('BD1'!$N23) -> 4 | P23: =MONTH('BD1'!$N23) -> 10 | Q23: =YEAR('BD1'!$N23) -> 2025 | R23: 1 | S23: si | T23: si | U23: si | V23: si | W23: si | X23: si | Y23: no | Z23: si | AA23: 51.03 | AB23: 19.13 | AC23: La conexión fue rápida pero presentó pequeños cortes | AD23: José Mosqueda | AE23: =COUNTIF(S23:Z23, "si") -> 7 | AF23: =IF('BD1'!$AE23=8,"Estable",(IF('BD1'!$AE23=7,"Funcional con observaciones", (IF('BD1'!$AE23=6,"Funcional con observaciones",(IF('BD1'!$AE23=5,"Rendimiento bajo",(IF('BD1'!$AE23=4,"Parcialmente funcional",(IF('BD1'!$AE23=3,"Parcialmente funcional",(IF('BD1'!$AE23=2,"Inoperativo",(IF('BD1'!$AE23=1,"Inoperativo","Crítico"))))))))))))))) -> Funcional con observaciones
A24: 102 | B24: Fibra Óptica | C24: ESCUELA | D24: SECUNDARIA | E24: 11DES0028B - SECUNDARIA GENERAL HERMANOS FLORES MAGON | F24: CARRETERA LEON, SAN FRANCISCOSN KILOMETRO 1.5 | G24: COLONIA PORTALES DE SAN SEBASTIAN | H24: LEÓN | I24: 21.10182 | J24: -101.70554 | K24: ok | L24: =HYPERLINK("https://www.google.com/maps?q=" & I24 & "," & J24, "Ver en Google Maps") -> Ver en Google Maps | M24: 2 | N24: 45932 | O24: =DAY('BD1'!$N24) -> 2 | P24: =MONTH('BD1'!$N24) -> 10 | Q24: =YEAR('BD1'!$N24) -> 2025 | R24: 1 | S24: no | T24: si | U24: si | V24: si | W24: si | X24: si | Y24: no | Z24: no | AA24: 0 | AB24: 0 | AC24: No se pudo realizar el test de velocidad ya que la conexión es inestable, puede deberse a que el acces point está lejos de la calle, y no se nos permitió ingresar al plantel | AD24: Rafael Amaral | AE24: =COUNTIF(S24:Z24, "si") -> 5 | AF24: =IF('BD1'!$AE24=8,"Estable",(IF('BD1'!$AE24=7,"Funcional con observaciones", (IF('BD1'!$AE24=6,"Funcional con observaciones",(IF('BD1'!$AE24=5,"Rendimiento bajo",(IF('BD1'!$AE24=4,"Parcialmente funcional",(IF('BD1'!$AE24=3,"Parcialmente funcional",(IF('BD1'!$AE24=2,"Inoperativo",(IF('BD1'!$AE24=1,"Inoperativo","Crítico"))))))))))))))) -> Rendimiento bajo
A25: 106 | B25: Fibra Óptica | C25: ESCUELA | D25: SECUNDARIA | E25: 11DES0061J - SECUNDARIA GENERAL EMPERADOR CUAUHTEMOC | F25: BOULEVARD MANUEL DE AUSTRI Y CAMPECHE S/N | G25: COLONIA CHAPALITA | H25: LEÓN | I25: 21.12576 | J25: -101.70523 | L25: =HYPERLINK("https://www.google.com/maps?q=" & I25 & "," & J25, "Ver en Google Maps") -> Ver en Google Maps | M25: 2
A26: 107 | B26: Fibra Óptica | C26: ESCUELA | D26: SECUNDARIA | E26: 11DES0072P - SECUNDARIA GENERAL N° 7 "MARGARITA PAZ PAREDES" | F26: SEVILLA NUM. 2201 SEGUNDA SECCION PILETAS | G26: COLONIA PILETAS SEGUNDA SECCION | H26: LEÓN | I26: 21.1406 | J26: -101.70609 | K26: ok | L26: =HYPERLINK("https://www.google.com/maps?q=" & I26 & "," & J26, "Ver en Google Maps") -> Ver en Google Maps | M26: 2 | N26: 45933 | O26: =DAY('BD1'!$N26) -> 3 | P26: =MONTH('BD1'!$N26) -> 10 | Q26: =YEAR('BD1'!$N26) -> 2025 | R26: 1 | S26: si | T26: si | U26: si | V26: si | W26: si | X26: si | Y26: si | Z26: si | AA26: 37.34 | AB26: 36.29 | AC26: La conexión fue rápida y constante, la navegación fue fluida, no se observan anomalías, tiene buena señal | AD26: Rafael Amaral | AE26: =COUNTIF(S26:Z26, "si") -> 8 | AF26: =IF('BD1'!$AE26=8,"Estable",(IF('BD1'!$AE26=7,"Funcional con observaciones", (IF('BD1'!$AE26=6,"Funcional con observaciones",(IF('BD1'!$AE26=5,"Rendimiento bajo",(IF('BD1'!$AE26=4,"Parcialmente funcional",(IF('BD1'!$AE26=3,"Parcialmente funcional",(IF('BD1'!$AE26=2,"Inoperativo",(IF('BD1'!$AE26=1,"Inoperativo","Crítico"))))))))))))))) -> Estable
A27: 108 | B27: Fibra Óptica | C27: ESCUELA | D27: SECUNDARIA | E27: 11DES0080Y - FRANCISCO RAMIREZ MATA | F27: BOULEVARD SAN PEDRO NUM. SN Y LAUREL | G27: COLONIA JARDIN DE JEREZ SEGUNDA SECCION | H27: LEÓN | I27: 21.09137 | J27: -101.64844 | L27: =HYPERLINK("https://www.google.com/maps?q=" & I27 & "," & J27, "Ver en Google Maps") -> Ver en Google Maps | M27: 2
A28: 109 | B28: Fibra Óptica | C28: ESCUELA | D28: SECUNDARIA | E28: 11DES0084U - SECUNDARIA GENERAL HILARIO MEDINA | F28: BOULEVARD FRANCISCO VILLA Y EGIPTO S/N | G28: COLONIA LOS ANGELES | H28: LEÓN | I28: 21.13391 | J28: -101.64409 | K28: ok | L28: =HYPERLINK("https://www.google.com/maps?q=" & I28 & "," & J28, "Ver en Google Maps") -> Ver en Google Maps | M28: 2 | N28: 45931 | O28: =DAY('BD1'!$N28) -> 1 | P28: =MONTH('BD1'!$N28) -> 10 | Q28: =YEAR('BD1'!$N28) -> 2025 | R28: 1 | S28: si | T28: si | U28: si | V28: si | W28: si | X28: si | Y28: si | Z28: si | AA28: 23.73 | AB28: 25.45 | AC28: La conexión fue rápida y constante, la navegación fue fluida, no se observan anomalías, tiene buena señal | AD28: José Mosqueda | AE28: =COUNTIF(S28:Z28, "si") -> 8 | AF28: =IF('BD1'!$AE28=8,"Estable",(IF('BD1'!$AE28=7,"Funcional con observaciones", (IF('BD1'!$AE28=6,"Funcional con observaciones",(IF('BD1'!$AE28=5,"Rendimiento bajo",(IF('BD1'!$AE28=4,"Parcialmente funcional",(IF('BD1'!$AE28=3,"Parcialmente funcional",(IF('BD1'!$AE28=2,"Inoperativo",(IF('BD1'!$AE28=1,"Inoperativo","Crítico"))))))))))))))) -> Estable
A29: 112 | B29: Fibra Óptica | C29: ESCUELA | D29: SECUNDARIA | E29: 11DES0090E - ESCUELA SECUNDARIA N° 11"JUAN J.VARELA MAYORGA" | F29: SOFIA ALVAREZ NUM. 1503 | G29: COLONIA LOMAS DE LOS OLIVOS | H29: LEÓN | I29: 21.11342 | J29: -101.70892 | K29: ok | L29: =HYPERLINK("https://www.google.com/maps?q=" & I29 & "," & J29, "Ver en Google Maps") -> Ver en Google Maps | M29: 2 | N29: 45940 | O29: =DAY('BD1'!$N29) -> 10 | P29: =MONTH('BD1'!$N29) -> 10 | Q29: =YEAR('BD1'!$N29) -> 2025 | R29: 1 | S29: si | T29: si | U29: si | V29: no | W29: si | X29: si | Y29: si | Z29: si | AA29: 35 | AB29: 29.94 | AC29: La conexión fue rápida y constante, la navegación fue fluida, no permitió cargar videos en youtube, lo demás lo cargó sin problema | AD29: Rafael Amaral | AE29: =COUNTIF(S29:Z29, "si") -> 7 | AF29: =IF('BD1'!$AE29=8,"Estable",(IF('BD1'!$AE29=7,"Funcional con observaciones", (IF('BD1'!$AE29=6,"Funcional con observaciones",(IF('BD1'!$AE29=5,"Rendimiento bajo",(IF('BD1'!$AE29=4,"Parcialmente funcional",(IF('BD1'!$AE29=3,"Parcialmente funcional",(IF('BD1'!$AE29=2,"Inoperativo",(IF('BD1'!$AE29=1,"Inoperativo","Crítico"))))))))))))))) -> Funcional con observaciones
A30: 114 | B30: Fibra Óptica | C30: ESCUELA | D30: SECUNDARIA | E30: 11DES0097Y - PEDRO MORENO | F30: JOSEFINA CAMARENA NUM. 901 | G30: COLONIA LEON II | H30: LEÓN | I30: 21.10845 | J30: -101.7283 | K30: ok | L30: =HYPERLINK("https://www.google.com/maps?q=" & I30 & "," & J30, "Ver en Google Maps") -> Ver en Google Maps | M30: 2 | N30: 45933 | O30: =DAY('BD1'!$N30) -> 3 | P30: =MONTH('BD1'!$N30) -> 10 | Q30: =YEAR('BD1'!$N30) -> 2025 | R30: 1 | S30: si | T30: si | U30: si | V30: si | W30: si | X30: si | Y30: si | Z30: si | AA30: 21.33 | AB30: 34.35 | AC30: El Director de la institución comenta que el servicio se interrumpe demasiado, hay mucha población y no es suficiente, puede deberse a la cantidad de dispositivos que permiten los acces point puede que se resuelva aumentando la cantidad o en su defecto agregando otro acces point | AD30: José Mosqueda | AE30: =COUNTIF(S30:Z30, "si") -> 8 | AF30: =IF('BD1'!$AE30=8,"Estable",(IF('BD1'!$AE30=7,"Funcional con observaciones", (IF('BD1'!$AE30=6,"Funcional con observaciones",(IF('BD1'!$AE30=5,"Rendimiento bajo",(IF('BD1'!$AE30=4,"Parcialmente funcional",(IF('BD1'!$AE30=3,"Parcialmente funcional",(IF('BD1'!$AE30=2,"Inoperativo",(IF('BD1'!$AE30=1,"Inoperativo","Crítico"))))))))))))))) -> Estable
A31: 115 | B31: Fibra Óptica | C31: ESCUELA | D31: SECUNDARIA | E31: 11DES0099W - FRANCISCO PICHARDO | F31: CERRO DE LA BUFA ESQUINA VILLA DE REYES NUM. SN | G31: COLONIA LOMAS DE JEREZ | H31: LEÓN | I31: 21.08157 | J31: -101.63813 | L31: =HYPERLINK("https://www.google.com/maps?q=" & I31 & "," & J31, "Ver en Google Maps") -> Ver en Google Maps | M31: 2
A32: 116 | B32: Fibra Óptica | C32: ESCUELA | D32: SECUNDARIA | E32: 11DES0102T - SECUNDARIA GENERAL SOR JUANA INES DE LA CRUZ | F32: BOULEVARD EPSILON NUM. 1105 | G32: COLONIA VALLE VERDE | H32: LEÓN | I32: 21.08009 | J32: -101.62151 | L32: =HYPERLINK("https://www.google.com/maps?q=" & I32 & "," & J32, "Ver en Google Maps") -> Ver en Google Maps | M32: 2
A33: 117 | B33: Fibra Óptica | C33: ESCUELA | D33: SECUNDARIA | E33: 11DES0103S - GUADALUPE PEDROZA PIÑA | F33: CALLE AURORA DE SAN JUAN NUMERO EXTERIOR: SN, FRACCIONAMIENTO VIL | G33: COLONIA VILLAS DE SAN JUAN | H33: LEÓN | I33: 21.09255 | J33: -101.59189 | L33: =HYPERLINK("https://www.google.com/maps?q=" & I33 & "," & J33, "Ver en Google Maps") -> Ver en Google Maps | M33: 2
A34: 120 | B34: Fibra Óptica | C34: ESCUELA | D34: PREESCOLAR | E34: 11DJN0030G - MANUEL LOPEZ COTILLA | F34: BURGOS Y GALICIA S/N Y GALICIA S/N | G34: COLONIA ESPAÑA | H34: LEÓN | I34: 21.13291 | J34: -101.70179 | L34: =HYPERLINK("https://www.google.com/maps?q=" & I34 & "," & J34, "Ver en Google Maps") -> Ver en Google Maps | M34: 1
A35: 123 | B35: Fibra Óptica | C35: ESCUELA | D35: PREESCOLAR | E35: 11DJN0046H - OSCAR GONZALEZ BLACKALLER | F35: INMACULADA NUM. 108 | G35: COLONIA ESPAÑITA | H35: LEÓN | I35: 21.12063 | J35: -101.65833 | K35: ok | L35: =HYPERLINK("https://www.google.com/maps?q=" & I35 & "," & J35, "Ver en Google Maps") -> Ver en Google Maps | M35: 1 | N35: 45939 | O35: =DAY('BD1'!$N35) -> 9 | P35: =MONTH('BD1'!$N35) -> 10 | Q35: =YEAR('BD1'!$N35) -> 2025 | R35: 1 | S35: si | T35: si | U35: si | V35: si | W35: si | X35: si | Y35: si | Z35: si | AA35: 49.27 | AB35: 36.98 | AC35: La conexión fue rápida y constante, la navegación fue fluida, no se observan anomalías, tiene buena señal | AD35: Rafael Amaral | AE35: =COUNTIF(S35:Z35, "si") -> 8 | AF35: =IF('BD1'!$AE35=8,"Estable",(IF('BD1'!$AE35=7,"Funcional con observaciones", (IF('BD1'!$AE35=6,"Funcional con observaciones",(IF('BD1'!$AE35=5,"Rendimiento bajo",(IF('BD1'!$AE35=4,"Parcialmente funcional",(IF('BD1'!$AE35=3,"Parcialmente funcional",(IF('BD1'!$AE35=2,"Inoperativo",(IF('BD1'!$AE35=1,"Inoperativo","Crítico"))))))))))))))) -> Estable
A36: 128 | B36: Fibra Óptica | C36: ESCUELA | D36: PREESCOLAR | E36: 11DJN0060A - ZORAIDA PINEDA | F36: CALLE MANANTIAL NUMERO EXTERIOR: 203 , COLONIA FUTURAMA MONTERREY | G36: COLONIA FUTURAMA MONTERREY | H36: LEÓN | I36: 21.14996 | J36: -101.68824 | K36: ok | L36: =HYPERLINK("https://www.google.com/maps?q=" & I36 & "," & J36, "Ver en Google Maps") -> Ver en Google Maps | M36: 1 | N36: 45933 | O36: =DAY('BD1'!$N36) -> 3 | P36: =MONTH('BD1'!$N36) -> 10 | Q36: =YEAR('BD1'!$N36) -> 2025 | R36: 1 | S36: si | T36: si | U36: si | V36: si | W36: si | X36: si | Y36: si | Z36: si | AA36: 50.44 | AB36: 61.88 | AC36: La conexión fue rápida y constante, la navegación fue fluida, no se observan anomalías, tiene buena señal | AD36: José Mosqueda | AE36: =COUNTIF(S36:Z36, "si") -> 8 | AF36: =IF('BD1'!$AE36=8,"Estable",(IF('BD1'!$AE36=7,"Funcional con observaciones", (IF('BD1'!$AE36=6,"Funcional con observaciones",(IF('BD1'!$AE36=5,"Rendimiento bajo",(IF('BD1'!$AE36=4,"Parcialmente funcional",(IF('BD1'!$AE36=3,"Parcialmente funcional",(IF('BD1'!$AE36=2,"Inoperativo",(IF('BD1'!$AE36=1,"Inoperativo","Crítico"))))))))))))))) -> Estable
A37: 131 | B37: Fibra Óptica | C37: ESCUELA | D37: PREESCOLAR | E37: 11DJN0078Z - MANUEL DOBLADO | F37: CUITLAHUAC Y CHIMALPOPOCA S/N ESQUINA CHIMALPOPOCA | G37: COLONIA AZTECA | H37: LEÓN | I37: 21.10105 | J37: -101.65532 | K37: ok | L37: =HYPERLINK("https://www.google.com/maps?q=" & I37 & "," & J37, "Ver en Google Maps") -> Ver en Google Maps | M37: 1 | N37: 45934 | O37: =DAY('BD1'!$N37) -> 4 | P37: =MONTH('BD1'!$N37) -> 10 | Q37: =YEAR('BD1'!$N37) -> 2025 | R37: 1 | S37: si | T37: si | U37: si | V37: si | W37: si | X37: si | Y37: si | Z37: si | AA37: 50.28 | AB37: 53.99 | AC37: La conexión fue rápida y constante, la navegación fue fluida, no se observan anomalías, tiene buena señal | AD37: José Mosqueda | AE37: =COUNTIF(S37:Z37, "si") -> 8 | AF37: =IF('BD1'!$AE37=8,"Estable",(IF('BD1'!$AE37=7,"Funcional con observaciones", (IF('BD1'!$AE37=6,"Funcional con observaciones",(IF('BD1'!$AE37=5,"Rendimiento bajo",(IF('BD1'!$AE37=4,"Parcialmente funcional",(IF('BD1'!$AE37=3,"Parcialmente funcional",(IF('BD1'!$AE37=2,"Inoperativo",(IF('BD1'!$AE37=1,"Inoperativo","Crítico"))))))))))))))) -> Estable
A38: 136 | B38: Fibra Óptica | C38: ESCUELA | D38: PREESCOLAR | E38: 11DJN0114O - NICOLAS RANGEL | F38: PROLONGACION LA MERCED NUM. 1239 | G38: COLONIA SAN SEBASTIAN | H38: LEÓN | I38: 21.10363 | J38: -101.7011 | K38: ok | L38: =HYPERLINK("https://www.google.com/maps?q=" & I38 & "," & J38, "Ver en Google Maps") -> Ver en Google Maps | M38: 1 | N38: 45932 | O38: =DAY('BD1'!$N38) -> 2 | P38: =MONTH('BD1'!$N38) -> 10 | Q38: =YEAR('BD1'!$N38) -> 2025 | R38: 1 | S38: si | T38: si | U38: si | V38: si | W38: si | X38: si | Y38: si | Z38: si | AA38: 40.26 | AB38: 21.65 | AC38: La conexión fue rápida y constante, la navegación fue fluida, no se observan anomalías, tiene buena señal | AD38: Rafael Amaral | AE38: =COUNTIF(S38:Z38, "si") -> 8 | AF38: =IF('BD1'!$AE38=8,"Estable",(IF('BD1'!$AE38=7,"Funcional con observaciones", (IF('BD1'!$AE38=6,"Funcional con observaciones",(IF('BD1'!$AE38=5,"Rendimiento bajo",(IF('BD1'!$AE38=4,"Parcialmente funcional",(IF('BD1'!$AE38=3,"Parcialmente funcional",(IF('BD1'!$AE38=2,"Inoperativo",(IF('BD1'!$AE38=1,"Inoperativo","Crítico"))))))))))))))) -> Estable
A39: 141 | B39: Fibra Óptica | C39: ESCUELA | D39: PREESCOLAR | E39: 11DJN0329O - JOSEFA ORTIZ DE DOMINGUEZ | F39: BOULEVARD MARIANO ESCOBEDO S/N A UN COSTADO DE LA PRIMARIA EMILIA | G39: COLONIA KENNEDY | H39: LEÓN | I39: 21.11673 | J39: -101.70174 | K39: ok | L39: =HYPERLINK("https://www.google.com/maps?q=" & I39 & "," & J39, "Ver en Google Maps") -> Ver en Google Maps | M39: 1 | N39: 45940 | O39: =DAY('BD1'!$N39) -> 10 | P39: =MONTH('BD1'!$N39) -> 10 | Q39: =YEAR('BD1'!$N39) -> 2025 | R39: 1 | S39: si | T39: si | U39: si | V39: si | W39: si | X39: si | Y39: si | Z39: si | AA39: 35.4 | AB39: 52.47 | AC39: La conexión fue rápida y constante, la navegación fue fluida, no se observan anomalías, tiene buena señal | AD39: Rafael Amaral | AE39: =COUNTIF(S39:Z39, "si") -> 8 | AF39: =IF('BD1'!$AE39=8,"Estable",(IF('BD1'!$AE39=7,"Funcional con observaciones", (IF('BD1'!$AE39=6,"Funcional con observaciones",(IF('BD1'!$AE39=5,"Rendimiento bajo",(IF('BD1'!$AE39=4,"Parcialmente funcional",(IF('BD1'!$AE39=3,"Parcialmente funcional",(IF('BD1'!$AE39=2,"Inoperativo",(IF('BD1'!$AE39=1,"Inoperativo","Crítico"))))))))))))))) -> Estable
A40: 142 | B40: Fibra Óptica | C40: ESCUELA | D40: PREESCOLAR | E40: 11DJN0197N - ALVARO OBREGON | F40: DIEGO DE VELAZQUEZ NUM. 703 | G40: COLONIA JARDINES DEL ORIRNTE | H40: LEÓN | I40: 21.12765 | J40: -101.64816 | K40: ok | L40: =HYPERLINK("https://www.google.com/maps?q=" & I40 & "," & J40, "Ver en Google Maps") -> Ver en Google Maps | M40: 1 | N40: 45931 | O40: =DAY('BD1'!$N40) -> 1 | P40: =MONTH('BD1'!$N40) -> 10 | Q40: =YEAR('BD1'!$N40) -> 2025 | R40: 1 | S40: si | T40: si | U40: si | V40: si | W40: si | X40: si | Y40: si | Z40: si | AA40: 64.16 | AB40: 42.08 | AC40: La conexión fue rápida y constante, la navegación fue fluida, no se observan anomalías, tiene buena señal | AD40: José Mosqueda | AE40: =COUNTIF(S40:Z40, "si") -> 8 | AF40: =IF('BD1'!$AE40=8,"Estable",(IF('BD1'!$AE40=7,"Funcional con observaciones", (IF('BD1'!$AE40=6,"Funcional con observaciones",(IF('BD1'!$AE40=5,"Rendimiento bajo",(IF('BD1'!$AE40=4,"Parcialmente funcional",(IF('BD1'!$AE40=3,"Parcialmente funcional",(IF('BD1'!$AE40=2,"Inoperativo",(IF('BD1'!$AE40=1,"Inoperativo","Crítico"))))))))))))))) -> Estable
A41: 144 | B41: Fibra Óptica | C41: ESCUELA | D41: PREESCOLAR | E41: 11DJN0212P - CARMEN RAMOS DEL RIO | F41: CALLE TRES NUM. 56 BOULEVARD MIGUEL DE CERVANTES SAAVEDRA | G41: COLONIA CHULAVISTA | H41: LEÓN | I41: 21.12003 | J41: -101.70858 | K41: ok | L41: =HYPERLINK("https://www.google.com/maps?q=" & I41 & "," & J41, "Ver en Google Maps") -> Ver en Google Maps | M41: 1 | N41: 45933 | O41: =DAY('BD1'!$N41) -> 3 | P41: =MONTH('BD1'!$N41) -> 10 | Q41: =YEAR('BD1'!$N41) -> 2025 | R41: 1 | S41: si | T41: si | U41: si | V41: si | W41: si | X41: si | Y41: si | Z41: si | AA41: 35.56 | AB41: 22.9 | AC41: La conexión fue rápida y constante, la navegación fue fluida, no se observan anomalías, tiene buena señal | AD41: José Mosqueda | AE41: =COUNTIF(S41:Z41, "si") -> 8 | AF41: =IF('BD1'!$AE41=8,"Estable",(IF('BD1'!$AE41=7,"Funcional con observaciones", (IF('BD1'!$AE41=6,"Funcional con observaciones",(IF('BD1'!$AE41=5,"Rendimiento bajo",(IF('BD1'!$AE41=4,"Parcialmente funcional",(IF('BD1'!$AE41=3,"Parcialmente funcional",(IF('BD1'!$AE41=2,"Inoperativo",(IF('BD1'!$AE41=1,"Inoperativo","Crítico"))))))))))))))) -> Estable
A42: 146 | B42: Fibra Óptica | C42: ESCUELA | D42: PREESCOLAR | E42: 11DJN0216L - DANIEL DELGADILLO | F42: MURCIA BARCELONA S/N | G42: COLONIA VISTA HERMOSA SUR | H42: LEÓN | I42: 21.13731 | J42: -101.71594 | L42: =HYPERLINK("https://www.google.com/maps?q=" & I42 & "," & J42, "Ver en Google Maps") -> Ver en Google Maps | M42: 1
A43: 147 | B43: Fibra Óptica | C43: ESCUELA | D43: PREESCOLAR | E43: 11DJN0226S - PROFRA. SILVINA LARA PARTIDA | F43: LOS ANGELES NUM. 316 | G43: COLONIA LAS AMERICAS | H43: LEÓN | I43: 21.10872 | J43: -101.69521 | K43: ok | L43: =HYPERLINK("https://www.google.com/maps?q=" & I43 & "," & J43, "Ver en Google Maps") -> Ver en Google Maps | M43: 1 | N43: 45932 | O43: =DAY('BD1'!$N43) -> 2 | P43: =MONTH('BD1'!$N43) -> 10 | Q43: =YEAR('BD1'!$N43) -> 2025 | R43: 1 | S43: si | T43: si | U43: si | V43: si | W43: si | X43: si | Y43: si | Z43: si | AA43: 42.5 | AB43: 12.8 | AC43: La conexión fue rápida y constante, la navegación fue fluida, no se observan anomalías, tiene buena señal | AD43: Rafael Amaral | AE43: =COUNTIF(S43:Z43, "si") -> 8 | AF43: =IF('BD1'!$AE43=8,"Estable",(IF('BD1'!$AE43=7,"Funcional con observaciones", (IF('BD1'!$AE43=6,"Funcional con observaciones",(IF('BD1'!$AE43=5,"Rendimiento bajo",(IF('BD1'!$AE43=4,"Parcialmente funcional",(IF('BD1'!$AE43=3,"Parcialmente funcional",(IF('BD1'!$AE43=2,"Inoperativo",(IF('BD1'!$AE43=1,"Inoperativo","Crítico"))))))))))))))) -> Estable
A44: 148 | B44: Fibra Óptica | C44: ESCUELA | D44: PREESCOLAR | E44: 11DJN0227R - DR. JOSE DE JESUS GONZALEZ | F44: SEVILLA Y CATALUÑA S/N | G44: COLONIA SAN JUAN BOSCO | H44: LEÓN | I44: 21.13452 | J44: -101.70735 | K44: sin video | L44: =HYPERLINK("https://www.google.com/maps?q=" & I44 & "," & J44, "Ver en Google Maps") -> Ver en Google Maps | M44: 1 | N44: 45933 | O44: =DAY('BD1'!$N44) -> 3 | P44: =MONTH('BD1'!$N44) -> 10 | Q44: =YEAR('BD1'!$N44) -> 2025 | R44: 1 | S44: si | T44: si | U44: si | V44: si | W44: si | X44: si | Y44: si | Z44: si | AA44: 35.08 | AB44: 33.86 | AC44: La conexión fue rápida y constante, la navegación fue fluida, no se observan anomalías, tiene buena señal | AD44: José Mosqueda | AE44: =COUNTIF(S44:Z44, "si") -> 8 | AF44: =IF('BD1'!$AE44=8,"Estable",(IF('BD1'!$AE44=7,"Funcional con observaciones", (IF('BD1'!$AE44=6,"Funcional con observaciones",(IF('BD1'!$AE44=5,"Rendimiento bajo",(IF('BD1'!$AE44=4,"Parcialmente funcional",(IF('BD1'!$AE44=3,"Parcialmente funcional",(IF('BD1'!$AE44=2,"Inoperativo",(IF('BD1'!$AE44=1,"Inoperativo","Crítico"))))))))))))))) -> Estable
A45: 149 | B45: Fibra Óptica | C45: ESCUELA | D45: PREESCOLAR | E45: 11DJN0230E - MANUEL G TINOCO | F45: SANTA RITA NUM. 103 | G45: COLONIA SANTA RITA DE LOS NARANJOS | H45: LEÓN | I45: 21.10609 | J45: -101.70782 | L45: =HYPERLINK("https://www.google.com/maps?q=" & I45 & "," & J45, "Ver en Google Maps") -> Ver en Google Maps | M45: 2
A46: 163 | B46: Fibra Óptica | C46: ESCUELA | D46: PREESCOLAR | E46: 11DJN0327Q - MARIANO SILVA Y ACEVES | F46: PLAZA PALMERIN S/N | G46: COLONIA ARBOLEDAS | H46: LEÓN | I46: 21.10259 | J46: -101.66411 | K46: ok | L46: =HYPERLINK("https://www.google.com/maps?q=" & I46 & "," & J46, "Ver en Google Maps") -> Ver en Google Maps | M46: 2 | N46: 45934 | O46: =DAY('BD1'!$N46) -> 4 | P46: =MONTH('BD1'!$N46) -> 10 | Q46: =YEAR('BD1'!$N46) -> 2025 | R46: 1 | S46: si | T46: si | U46: si | V46: si | W46: si | X46: si | Y46: si | Z46: si | AA46: 36.41 | AB46: 37.73 | AC46: La conexión fue rápida y constante, la navegación fue fluida, no se observan anomalías, tiene buena señal | AD46: José Mosqueda | AE46: =COUNTIF(S46:Z46, "si") -> 8 | AF46: =IF('BD1'!$AE46=8,"Estable",(IF('BD1'!$AE46=7,"Funcional con observaciones", (IF('BD1'!$AE46=6,"Funcional con observaciones",(IF('BD1'!$AE46=5,"Rendimiento bajo",(IF('BD1'!$AE46=4,"Parcialmente funcional",(IF('BD1'!$AE46=3,"Parcialmente funcional",(IF('BD1'!$AE46=2,"Inoperativo",(IF('BD1'!$AE46=1,"Inoperativo","Crítico"))))))))))))))) -> Estable
A47: 164 | B47: Fibra Óptica | C47: ESCUELA | D47: PREESCOLAR | E47: 11DJN0331C - PROFRA. ROSAURA ZAPATA CANO | F47: LAGUNA DEL CARMEN S/N | G47: COLONIA LOMAS DE LA TRINIDAD | H47: LEÓN | I47: 21.1393 | J47: -101.69745 | K47: ok | L47: =HYPERLINK("https://www.google.com/maps?q=" & I47 & "," & J47, "Ver en Google Maps") -> Ver en Google Maps | M47: 2 | N47: 45933 | O47: =DAY('BD1'!$N47) -> 3 | P47: =MONTH('BD1'!$N47) -> 10 | Q47: =YEAR('BD1'!$N47) -> 2025 | R47: 1 | S47: si | T47: si | U47: si | V47: si | W47: si | X47: si | Y47: si | Z47: si | AA47: 27.35 | AB47: 28.55 | AC47: La conexión fue rápida y constante, la navegación fue fluida, no se observan anomalías, tiene buena señal | AD47: José Mosqueda | AE47: =COUNTIF(S47:Z47, "si") -> 8 | AF47: =IF('BD1'!$AE47=8,"Estable",(IF('BD1'!$AE47=7,"Funcional con observaciones", (IF('BD1'!$AE47=6,"Funcional con observaciones",(IF('BD1'!$AE47=5,"Rendimiento bajo",(IF('BD1'!$AE47=4,"Parcialmente funcional",(IF('BD1'!$AE47=3,"Parcialmente funcional",(IF('BD1'!$AE47=2,"Inoperativo",(IF('BD1'!$AE47=1,"Inoperativo","Crítico"))))))))))))))) -> Estable
A48: 165 | B48: Fibra Óptica | C48: ESCUELA | D48: PREESCOLAR | E48: 11DJN0334Z - DIEGO RIVERA | F48: MANTO SAGRADO NUM. 111 | G48: COLONIA JESUS DE NAZARET | H48: LEÓN | I48: 21.07942 | J48: -101.65515 | L48: =HYPERLINK("https://www.google.com/maps?q=" & I48 & "," & J48, "Ver en Google Maps") -> Ver en Google Maps | M48: 1
A49: 187 | B49: Fibra Óptica | C49: ESCUELA | D49: PREESCOLAR | E49: 11DJN0652M - EMILIO PORTES GIL | F49: SAN JUSTO S/N | G49: COLONIA LA PISCINA | H49: LEÓN | I49: 21.09562 | J49: -101.71724 | L49: =HYPERLINK("https://www.google.com/maps?q=" & I49 & "," & J49, "Ver en Google Maps") -> Ver en Google Maps | M49: 1
A50: 190 | B50: Fibra Óptica | C50: ESCUELA | D50: PREESCOLAR | E50: 11DJN0730Z - SOR JUANA INES DE LA CRUZ | F50: PROLONGACION LA LUZ S/N VIA DEL TREN | G50: COLONIA PROLONGACIÓN JUÁREZ | H50: LEÓN | I50: 21.093884 | J50: -101.69566 | L50: =HYPERLINK("https://www.google.com/maps?q=" & I50 & "," & J50, "Ver en Google Maps") -> Ver en Google Maps | M50: 1
A51: 191 | B51: Fibra Óptica | C51: ESCUELA | D51: PREESCOLAR | E51: 11DJN0731Z - PROFR. JOSE SOSTENES LIRA | F51: SANTA EMILIA NUM. 430 | G51: COLONIA CUMBRES DE LA PISCINA | H51: LEÓN | I51: 21.10941 | J51: -101.70592 | L51: =HYPERLINK("https://www.google.com/maps?q=" & I51 & "," & J51, "Ver en Google Maps") -> Ver en Google Maps | M51: 1
A52: 198 | B52: Fibra Óptica | C52: ESCUELA | D52: PREESCOLAR | E52: 11DJN0884C - VIDAL ALCOCER | F52: CALLE CERRO DE JEREZ NUMERO EXTERIOR: 1507 , COLONIA CERRITO DE J | G52: COLONIA CERRITO DE JEREZ | H52: LEÓN | I52: 21.087012 | J52: -101.63593 | L52: =HYPERLINK("https://www.google.com/maps?q=" & I52 & "," & J52, "Ver en Google Maps") -> Ver en Google Maps | M52: 1
A53: 199 | B53: Fibra Óptica | C53: ESCUELA | D53: PREESCOLAR | E53: 11DJN0887Z - NICOLAS RANGEL | F53: ANDADOR DE LA TRINCHERA NUMERO EXTERIOR: SN, COLONIA SAN CARLOS L | G53: COLONIA SAN CARLOS LA ROCHA | H53: LEÓN | I53: 21.070203 | J53: -101.58637 | L53: =HYPERLINK("https://www.google.com/maps?q=" & I53 & "," & J53, "Ver en Google Maps") -> Ver en Google Maps | M53: 1
A54: 200 | B54: Fibra Óptica | C54: ESCUELA | D54: PREESCOLAR | E54: 11DJN0888Z - MARIA CURIE | F54: BOULEVARD KAROL WOJTYLA NUMERO EXTERIOR: SN, FRACCIONAMIENTO VILL | G54: COLONIA VILLAS DE SAN NICOLAS | H54: LEÓN | I54: 21.11598 | J54: -101.58891 | K54: ok | L54: =HYPERLINK("https://www.google.com/maps?q=" & I54 & "," & J54, "Ver en Google Maps") -> Ver en Google Maps | M54: 1 | N54: 45931 | O54: =DAY('BD1'!$N54) -> 1 | P54: =MONTH('BD1'!$N54) -> 10 | Q54: =YEAR('BD1'!$N54) -> 2025 | R54: 1 | S54: si | T54: si | U54: si | V54: si | W54: si | X54: si | Y54: si | Z54: si | AA54: 68.24 | AB54: 61.19 | AC54: La conexión fue rápida y constante, la navegación fue fluida, no se observan anomalías, tiene buena señal | AD54: José Mosqueda | AE54: =COUNTIF(S54:Z54, "si") -> 8 | AF54: =IF('BD1'!$AE54=8,"Estable",(IF('BD1'!$AE54=7,"Funcional con observaciones", (IF('BD1'!$AE54=6,"Funcional con observaciones",(IF('BD1'!$AE54=5,"Rendimiento bajo",(IF('BD1'!$AE54=4,"Parcialmente funcional",(IF('BD1'!$AE54=3,"Parcialmente funcional",(IF('BD1'!$AE54=2,"Inoperativo",(IF('BD1'!$AE54=1,"Inoperativo","Crítico"))))))))))))))) -> Estable
A55: 202 | B55: Fibra Óptica | C55: ESCUELA | D55: PREESCOLAR | E55: 11DJN2398Y - CARMEN NORMA MONROY | F55: ISLA DE TODOS LOS SANTOS NUM. 104 | G55: COLONIA SATELITE | H55: LEÓN | I55: 21.11529 | J55: -101.72177 | K55: ok | L55: =HYPERLINK("https://www.google.com/maps?q=" & I55 & "," & J55, "Ver en Google Maps") -> Ver en Google Maps | M55: 1 | N55: 45933 | O55: =DAY('BD1'!$N55) -> 3 | P55: =MONTH('BD1'!$N55) -> 10 | Q55: =YEAR('BD1'!$N55) -> 2025 | R55: 1 | S55: si | T55: si | U55: si | V55: si | W55: si | X55: si | Y55: si | Z55: si | AA55: 51.05 | AB55: 60.61 | AC55: La conexión fue rápida y constante, la navegación fue fluida, no se observan anomalías, tiene buena señal | AD55: José Mosqueda | AE55: =COUNTIF(S55:Z55, "si") -> 8 | AF55: =IF('BD1'!$AE55=8,"Estable",(IF('BD1'!$AE55=7,"Funcional con observaciones", (IF('BD1'!$AE55=6,"Funcional con observaciones",(IF('BD1'!$AE55=5,"Rendimiento bajo",(IF('BD1'!$AE55=4,"Parcialmente funcional",(IF('BD1'!$AE55=3,"Parcialmente funcional",(IF('BD1'!$AE55=2,"Inoperativo",(IF('BD1'!$AE55=1,"Inoperativo","Crítico"))))))))))))))) -> Estable
A56: 203 | B56: Fibra Óptica | C56: ESCUELA | D56: PREESCOLAR | E56: 11DJN2355Z - FEDERICO FROEBEL | F56: GOLFO DE MEXICO NUM. 112 | G56: COLONIA SANTA MARIA DEL GRANJENO | H56: LEÓN | I56: 21.09208 | J56: -101.65699 | L56: =HYPERLINK("https://www.google.com/maps?q=" & I56 & "," & J56, "Ver en Google Maps") -> Ver en Google Maps | M56: 1
A57: 204 | B57: Fibra Óptica | C57: ESCUELA | D57: PREESCOLAR | E57: 11DJN0954H - GENERAL ALVARO OBREGON | F57: CALLE RODRIGUEZ NUMERO EXTERIOR: 114 , BARRIO GUADALUPE, CODIGO P | G57: COLONIA BARRIO GUADALUPE | H57: LEÓN | I57: 21.115172 | J57: -101.63907 | K57: ok | L57: =HYPERLINK("https://www.google.com/maps?q=" & I57 & "," & J57, "Ver en Google Maps") -> Ver en Google Maps | M57: 1 | N57: 45934 | O57: =DAY('BD1'!$N57) -> 4 | P57: =MONTH('BD1'!$N57) -> 10 | Q57: =YEAR('BD1'!$N57) -> 2025 | R57: 1 | S57: si | T57: si | U57: si | V57: si | W57: si | X57: si | Y57: si | Z57: si | AA57: 82.53 | AB57: 61.55 | AC57: La conexión fue rápida y constante, la navegación fue fluida, no se observan anomalías, tiene buena señal | AD57: José Mosqueda | AE57: =COUNTIF(S57:Z57, "si") -> 8 | AF57: =IF('BD1'!$AE57=8,"Estable",(IF('BD1'!$AE57=7,"Funcional con observaciones", (IF('BD1'!$AE57=6,"Funcional con observaciones",(IF('BD1'!$AE57=5,"Rendimiento bajo",(IF('BD1'!$AE57=4,"Parcialmente funcional",(IF('BD1'!$AE57=3,"Parcialmente funcional",(IF('BD1'!$AE57=2,"Inoperativo",(IF('BD1'!$AE57=1,"Inoperativo","Crítico"))))))))))))))) -> Estable
A58: 205 | B58: Fibra Óptica | C58: ESCUELA | D58: PREESCOLAR | E58: 11DJN0964O - JOHN DEWEY | F58: FELIX ROMERO NUM. 404 CARRETERA LEON-SAN FRANCIOSCO DEL RINCON | G58: COLONIA PERIODISTAS DE MEXICO | H58: LEÓN | I58: 21.09668 | J58: -101.74957 | L58: =HYPERLINK("https://www.google.com/maps?q=" & I58 & "," & J58, "Ver en Google Maps") -> Ver en Google Maps | M58: 1
A59: 206 | B59: Fibra Óptica | C59: ESCUELA | D59: PREESCOLAR | E59: 11DJN0965N - DIANA LAURA RIOJAS DE COLOSIO | F59: 14 DE MAYO S/N | G59: COLONIA MORELOS | H59: LEÓN | I59: 21.09499 | J59: -101.72034 | L59: =HYPERLINK("https://www.google.com/maps?q=" & I59 & "," & J59, "Ver en Google Maps") -> Ver en Google Maps | M59: 1
A60: 208 | B60: Fibra Óptica | C60: ESCUELA | D60: PREESCOLAR | E60: 11DJN1098U - JARDIN DE NIÑOS GUSTAVO DIAZ ORDAZ | F60: CALLE ARTICULO 27 NUMERO EXTERIOR: 102 , COLONIA LIBERTAD, CODIGO | G60: COLONIA LIBERTAD | H60: LEÓN | I60: 21.061246 | J60: -101.61919 | L60: =HYPERLINK("https://www.google.com/maps?q=" & I60 & "," & J60, "Ver en Google Maps") -> Ver en Google Maps | M60: 2
A61: 211 | B61: Fibra Óptica | C61: ESCUELA | D61: PRIMARIA | E61: 11DPR0219Z - PRIMARIA IV CENTENARIO | F61: RODRIGO DE VAZQUEZ S7N, COL LAS TROJES, LEON DE LOS ALDAMA | G61: COLONIA LAS TROJES LEON DE LOS ALDAMA | H61: LEÓN | I61: 21.13468 | J61: -101.66621 | K61: ok | L61: =HYPERLINK("https://www.google.com/maps?q=" & I61 & "," & J61, "Ver en Google Maps") -> Ver en Google Maps | M61: 1 | N61: 45929 | O61: =DAY('BD1'!$N61) -> 29 | P61: =MONTH('BD1'!$N61) -> 9 | Q61: =YEAR('BD1'!$N61) -> 2025 | R61: 1 | S61: si | T61: si | U61: si | V61: si | W61: si | X61: si | Y61: si | Z61: si | AA61: 42.42 | AB61: 40.68 | AC61: La conexión fue rápida y constante, la navegación fue fluida, no se observan anomalías, tiene buena señal | AD61: José Mosqueda | AE61: =COUNTIF(S61:Z61, "si") -> 8 | AF61: =IF('BD1'!$AE61=8,"Estable",(IF('BD1'!$AE61=7,"Funcional con observaciones", (IF('BD1'!$AE61=6,"Funcional con observaciones",(IF('BD1'!$AE61=5,"Rendimiento bajo",(IF('BD1'!$AE61=4,"Parcialmente funcional",(IF('BD1'!$AE61=3,"Parcialmente funcional",(IF('BD1'!$AE61=2,"Inoperativo",(IF('BD1'!$AE61=1,"Inoperativo","Crítico"))))))))))))))) -> Estable
A62: 212 | B62: Fibra Óptica | C62: ESCUELA | D62: PREESCOLAR | E62: 11DJN2347R - LUIS DE LA BRENA | F62: RINCONADA DE SAN PEDRO NUM. 119 | G62: COLONIA SAN PEDRO DE LOS HERNANDEZ | H62: LEÓN | I62: 21.12049 | J62: -101.63503 | K62: ok | L62: =HYPERLINK("https://www.google.com/maps?q=" & I62 & "," & J62, "Ver en Google Maps") -> Ver en Google Maps | M62: 1 | N62: 45934 | O62: =DAY('BD1'!$N62) -> 4 | P62: =MONTH('BD1'!$N62) -> 10 | Q62: =YEAR('BD1'!$N62) -> 2025 | R62: 1 | S62: no | T62: si | U62: si | V62: si | W62: si | X62: no | Y62: no | Z62: si | AA62: 35.03 | AB62: 30.96 | AC62: Hay mucha interrupción en la navegación | AD62: José Mosqueda | AE62: =COUNTIF(S62:Z62, "si") -> 5 | AF62: =IF('BD1'!$AE62=8,"Estable",(IF('BD1'!$AE62=7,"Funcional con observaciones", (IF('BD1'!$AE62=6,"Funcional con observaciones",(IF('BD1'!$AE62=5,"Rendimiento bajo",(IF('BD1'!$AE62=4,"Parcialmente funcional",(IF('BD1'!$AE62=3,"Parcialmente funcional",(IF('BD1'!$AE62=2,"Inoperativo",(IF('BD1'!$AE62=1,"Inoperativo","Crítico"))))))))))))))) -> Rendimiento bajo
A63: 213 | B63: Fibra Óptica | C63: ESCUELA | D63: PREESCOLAR | E63: 11DJN2350E - MARGARITA PAZ PAREDES | F63: BUGAMBILIAS ESQUINA CALENDULAS S/N I.M.S.S. JEREZ | G63: COLONIA JARDINES DE JEREZ 1ERA SECCION | H63: LEÓN | I63: 21.09616 | J63: -101.63831 | L63: =HYPERLINK("https://www.google.com/maps?q=" & I63 & "," & J63, "Ver en Google Maps") -> Ver en Google Maps | M63: 2
A64: 214 | B64: Fibra Óptica | C64: ESCUELA | D64: PREESCOLAR | E64: 11DJN2351D - MA. ROSARIO GUTIERREZ ESKILDSEN | F64: ETA NUM. 510 | G64: COLONIA SAN JOSE EL ALTO | H64: LEÓN | I64: 21.08449 | J64: -101.61864 | K64: ok | L64: =HYPERLINK("https://www.google.com/maps?q=" & I64 & "," & J64, "Ver en Google Maps") -> Ver en Google Maps | M64: 1 | N64: 45931 | O64: =DAY('BD1'!$N64) -> 1 | P64: =MONTH('BD1'!$N64) -> 10 | Q64: =YEAR('BD1'!$N64) -> 2025 | R64: 1 | S64: si | T64: si | U64: si | V64: si | W64: si | X64: si | Y64: si | Z64: si | AA64: 15.65 | AB64: 29.47 | AC64: La conexión fue rápida y constante, la navegación fue fluida, no se observan anomalías, tiene buena señal | AD64: José Mosqueda | AE64: =COUNTIF(S64:Z64, "si") -> 8 | AF64: =IF('BD1'!$AE64=8,"Estable",(IF('BD1'!$AE64=7,"Funcional con observaciones", (IF('BD1'!$AE64=6,"Funcional con observaciones",(IF('BD1'!$AE64=5,"Rendimiento bajo",(IF('BD1'!$AE64=4,"Parcialmente funcional",(IF('BD1'!$AE64=3,"Parcialmente funcional",(IF('BD1'!$AE64=2,"Inoperativo",(IF('BD1'!$AE64=1,"Inoperativo","Crítico"))))))))))))))) -> Estable
A65: 215 | B65: Fibra Óptica | C65: ESCUELA | D65: PREESCOLAR | E65: 11DJN2352C - GREGORIO TORRES QUINTERO | F65: SIERRA DE SAN PEDRO NUM. 121 | G65: COLONIA LAS HILAMAS | H65: LEÓN | I65: 21.10889 | J65: -101.72598 | K65: ok | L65: =HYPERLINK("https://www.google.com/maps?q=" & I65 & "," & J65, "Ver en Google Maps") -> Ver en Google Maps | M65: 1 | N65: 45933 | O65: =DAY('BD1'!$N65) -> 3 | P65: =MONTH('BD1'!$N65) -> 10 | Q65: =YEAR('BD1'!$N65) -> 2025 | R65: 1 | S65: si | T65: si | U65: si | V65: si | W65: si | X65: si | Y65: si | Z65: si | AA65: 60.26 | AB65: 12.22 | AC65: La conexión fue rápida y constante, la navegación fue fluida, no se observan anomalías, tiene buena señal | AD65: José Mosqueda | AE65: =COUNTIF(S65:Z65, "si") -> 8 | AF65: =IF('BD1'!$AE65=8,"Estable",(IF('BD1'!$AE65=7,"Funcional con observaciones", (IF('BD1'!$AE65=6,"Funcional con observaciones",(IF('BD1'!$AE65=5,"Rendimiento bajo",(IF('BD1'!$AE65=4,"Parcialmente funcional",(IF('BD1'!$AE65=3,"Parcialmente funcional",(IF('BD1'!$AE65=2,"Inoperativo",(IF('BD1'!$AE65=1,"Inoperativo","Crítico"))))))))))))))) -> Estable
A66: 216 | B66: Fibra Óptica | C66: ESCUELA | D66: PREESCOLAR | E66: 11DJN2356Z - ENRIQUE C REBSAMEN | F66: ARRAYAN Y MADRE SELVA S/N ESQUINA MADRE SELVA | G66: COLONIA JARDINES DE SAN PEDRO | H66: LEÓN | I66: 21.11085 | J66: -101.63195 | K66: ok | L66: =HYPERLINK("https://www.google.com/maps?q=" & I66 & "," & J66, "Ver en Google Maps") -> Ver en Google Maps | M66: 1 | N66: 45934 | O66: =DAY('BD1'!$N66) -> 4 | P66: =MONTH('BD1'!$N66) -> 10 | Q66: =YEAR('BD1'!$N66) -> 2025 | R66: 1 | S66: si | T66: si | U66: si | V66: si | W66: si | X66: si | Y66: si | Z66: si | AA66: 18.78 | AB66: 32.27 | AC66: La conexión fue rápida y constante, la navegación fue fluida, no se observan anomalías, tiene buena señal | AD66: José Mosqueda | AE66: =COUNTIF(S66:Z66, "si") -> 8 | AF66: =IF('BD1'!$AE66=8,"Estable",(IF('BD1'!$AE66=7,"Funcional con observaciones", (IF('BD1'!$AE66=6,"Funcional con observaciones",(IF('BD1'!$AE66=5,"Rendimiento bajo",(IF('BD1'!$AE66=4,"Parcialmente funcional",(IF('BD1'!$AE66=3,"Parcialmente funcional",(IF('BD1'!$AE66=2,"Inoperativo",(IF('BD1'!$AE66=1,"Inoperativo","Crítico"))))))))))))))) -> Estable
A67: 217 | B67: Fibra Óptica | C67: ESCUELA | D67: PREESCOLAR | E67: 11DJN2399X - LUIS CHAVEZ OROZCO | F67: ELISA NUM. 1503 | G67: COLONIA LAS PALMAS | H67: LEÓN | I67: 21.11504 | J67: -101.70041 | K67: sin video | L67: =HYPERLINK("https://www.google.com/maps?q=" & I67 & "," & J67, "Ver en Google Maps") -> Ver en Google Maps | M67: 1 | N67: 45940 | O67: =DAY('BD1'!$N67) -> 10 | P67: =MONTH('BD1'!$N67) -> 10 | Q67: =YEAR('BD1'!$N67) -> 2025 | R67: 1 | S67: si | T67: si | U67: si | V67: si | W67: si | X67: si | Y67: si | Z67: si | AA67: 35.91 | AB67: 8.89 | AC67: La conexión fue rápida y constante, la navegación fue fluida, no se observan anomalías, tiene buena señal | AD67: Rafael Amaral | AE67: =COUNTIF(S67:Z67, "si") -> 8 | AF67: =IF('BD1'!$AE67=8,"Estable",(IF('BD1'!$AE67=7,"Funcional con observaciones", (IF('BD1'!$AE67=6,"Funcional con observaciones",(IF('BD1'!$AE67=5,"Rendimiento bajo",(IF('BD1'!$AE67=4,"Parcialmente funcional",(IF('BD1'!$AE67=3,"Parcialmente funcional",(IF('BD1'!$AE67=2,"Inoperativo",(IF('BD1'!$AE67=1,"Inoperativo","Crítico"))))))))))))))) -> Estable
A68: 222 | B68: Fibra Óptica | C68: ESCUELA | D68: PREESCOLAR | E68: 11DJN2611Z - ANDRES DELGADO | F68: JOAQUIN MORENO S/N MALECON DEL RIO | G68: COLONIA RINCON DE LA FLORIDA | H68: LEÓN | I68: 21.14305 | J68: -101.67734 | K68: ok | L68: =HYPERLINK("https://www.google.com/maps?q=" & I68 & "," & J68, "Ver en Google Maps") -> Ver en Google Maps | M68: 1 | N68: 45929 | O68: =DAY('BD1'!$N68) -> 29 | P68: =MONTH('BD1'!$N68) -> 9 | Q68: =YEAR('BD1'!$N68) -> 2025 | R68: 1 | S68: si | T68: si | U68: si | V68: si | W68: si | X68: si | Y68: si | Z68: si | AA68: 23.36 | AB68: 32.07 | AC68: La conexión fue rápida y constante, la navegación fue fluida, no se observan anomalías, tiene buena señal | AD68: José Mosqueda | AE68: =COUNTIF(S68:Z68, "si") -> 8 | AF68: =IF('BD1'!$AE68=8,"Estable",(IF('BD1'!$AE68=7,"Funcional con observaciones", (IF('BD1'!$AE68=6,"Funcional con observaciones",(IF('BD1'!$AE68=5,"Rendimiento bajo",(IF('BD1'!$AE68=4,"Parcialmente funcional",(IF('BD1'!$AE68=3,"Parcialmente funcional",(IF('BD1'!$AE68=2,"Inoperativo",(IF('BD1'!$AE68=1,"Inoperativo","Crítico"))))))))))))))) -> Estable
A69: 224 | B69: Fibra Óptica | C69: ESCUELA | D69: PREESCOLAR | E69: 11DJN2627A - TLAMATINI | F69: MAR EGEO Y MAR MEDITERRANEO | G69: COLONIA INFONAVIT GRANADA | H69: LEÓN | I69: 21.14344 | J69: -101.70083 | K69: ok | L69: =HYPERLINK("https://www.google.com/maps?q=" & I69 & "," & J69, "Ver en Google Maps") -> Ver en Google Maps | M69: 1 | N69: 45930 | O69: =DAY('BD1'!$N69) -> 30 | P69: =MONTH('BD1'!$N69) -> 9 | Q69: =YEAR('BD1'!$N69) -> 2025 | R69: 1 | S69: si | T69: si | U69: si | V69: si | W69: si | X69: si | Y69: si | Z69: si | AA69: 66.3 | AB69: 22.12 | AC69: La conexión fue rápida y constante, la navegación fue fluida, no se observan anomalías, tiene buena señal | AD69: José Mosqueda | AE69: =COUNTIF(S69:Z69, "si") -> 8 | AF69: =IF('BD1'!$AE69=8,"Estable",(IF('BD1'!$AE69=7,"Funcional con observaciones", (IF('BD1'!$AE69=6,"Funcional con observaciones",(IF('BD1'!$AE69=5,"Rendimiento bajo",(IF('BD1'!$AE69=4,"Parcialmente funcional",(IF('BD1'!$AE69=3,"Parcialmente funcional",(IF('BD1'!$AE69=2,"Inoperativo",(IF('BD1'!$AE69=1,"Inoperativo","Crítico"))))))))))))))) -> Estable
A70: 230 | B70: Fibra Óptica | C70: ESCUELA | D70: PREESCOLAR | E70: 11DJN2770O - MARIA MONTESSORI | F70: COMUNIDAD SAN JUAN DE ABAJO PASANDO LA VIA DE FERROCARRIL | G70: COMUNIDAD SAN JUAN DE ABAJO | H70: LEÓN | I70: 21.05779 | J70: -101.63623 | L70: =HYPERLINK("https://www.google.com/maps?q=" & I70 & "," & J70, "Ver en Google Maps") -> Ver en Google Maps | M70: 1
A71: 231 | B71: Fibra Óptica | C71: ESCUELA | D71: PREESCOLAR | E71: 11DJN2774K - ALFRED ADLER | F71: CALLE HEGEL NUMERO EXTERIOR: 501 , FRACCIONAMIENTO CENTRO FAMILIA | G71: COLONIA LA SOLEDAD | H71: LEÓN | I71: 21.14008 | J71: -101.75378 | K71: ok | L71: =HYPERLINK("https://www.google.com/maps?q=" & I71 & "," & J71, "Ver en Google Maps") -> Ver en Google Maps | M71: 1 | N71: 45930 | O71: =DAY('BD1'!$N71) -> 30 | P71: =MONTH('BD1'!$N71) -> 9 | Q71: =YEAR('BD1'!$N71) -> 2025 | R71: 1 | S71: si | T71: si | U71: si | V71: si | W71: si | X71: si | Y71: si | Z71: no | AA71: 0 | AB71: 0 | AC71: No se pudo realizar el test de velocidad ya que la conexión es inestable, puede deberse a que el acces point está lejos de la calle, y no se nos permitió ingresar al plantel | AD71: Rafael Amaral | AE71: =COUNTIF(S71:Z71, "si") -> 7 | AF71: =IF('BD1'!$AE71=8,"Estable",(IF('BD1'!$AE71=7,"Funcional con observaciones", (IF('BD1'!$AE71=6,"Funcional con observaciones",(IF('BD1'!$AE71=5,"Rendimiento bajo",(IF('BD1'!$AE71=4,"Parcialmente funcional",(IF('BD1'!$AE71=3,"Parcialmente funcional",(IF('BD1'!$AE71=2,"Inoperativo",(IF('BD1'!$AE71=1,"Inoperativo","Crítico"))))))))))))))) -> Funcional con observaciones
A72: 233 | B72: Fibra Óptica | C72: ESCUELA | D72: PREESCOLAR | E72: 11DJN2808K - EMILIANO ZAPATA | F72: CALLE AQUILES SERDAN NUMERO EXTERIOR: SN, EJIDO LA JOYA, CODIGO P | G72: COMUNIDAD LA JOYA | H72: LEÓN | I72: 21.142942 | J72: -101.73759 | K72: ok | L72: =HYPERLINK("https://www.google.com/maps?q=" & I72 & "," & J72, "Ver en Google Maps") -> Ver en Google Maps | M72: 1 | N72: 45930 | O72: =DAY('BD1'!$N72) -> 30 | P72: =MONTH('BD1'!$N72) -> 9 | Q72: =YEAR('BD1'!$N72) -> 2025 | R72: 1 | S72: si | T72: si | U72: si | V72: si | W72: si | X72: si | Y72: si | Z72: si | AA72: 100.28 | AB72: 65.04 | AC72: La conexión fue rápida y constante, la navegación fue fluida, no se observan anomalías, tiene buena señal | AD72: José Mosqueda | AE72: =COUNTIF(S72:Z72, "si") -> 8 | AF72: =IF('BD1'!$AE72=8,"Estable",(IF('BD1'!$AE72=7,"Funcional con observaciones", (IF('BD1'!$AE72=6,"Funcional con observaciones",(IF('BD1'!$AE72=5,"Rendimiento bajo",(IF('BD1'!$AE72=4,"Parcialmente funcional",(IF('BD1'!$AE72=3,"Parcialmente funcional",(IF('BD1'!$AE72=2,"Inoperativo",(IF('BD1'!$AE72=1,"Inoperativo","Crítico"))))))))))))))) -> Estable
A73: 234 | B73: Fibra Óptica | C73: ESCUELA | D73: PREESCOLAR | E73: 11DJN2824B - FRANCISCO MARQUEZ | F73: CALLE CAMINO A LA PRESA DEL SALTO NUMERO EXTERIOR: SN, FRACCIONAM | G73: COLONIA SAN JOSE DEL POTRERO | H73: LEÓN | I73: 21.12926 | J73: -101.59872 | K73: ok | L73: =HYPERLINK("https://www.google.com/maps?q=" & I73 & "," & J73, "Ver en Google Maps") -> Ver en Google Maps | M73: 1 | N73: 45931 | O73: =DAY('BD1'!$N73) -> 1 | P73: =MONTH('BD1'!$N73) -> 10 | Q73: =YEAR('BD1'!$N73) -> 2025 | R73: 1 | S73: si | T73: si | U73: si | V73: si | W73: si | X73: si | Y73: si | Z73: si | AA73: 74.22 | AB73: 79.01 | AC73: La conexión fue rápida y constante, la navegación fue fluida, no se observan anomalías, tiene buena señal | AD73: José Mosqueda | AE73: =COUNTIF(S73:Z73, "si") -> 8 | AF73: =IF('BD1'!$AE73=8,"Estable",(IF('BD1'!$AE73=7,"Funcional con observaciones", (IF('BD1'!$AE73=6,"Funcional con observaciones",(IF('BD1'!$AE73=5,"Rendimiento bajo",(IF('BD1'!$AE73=4,"Parcialmente funcional",(IF('BD1'!$AE73=3,"Parcialmente funcional",(IF('BD1'!$AE73=2,"Inoperativo",(IF('BD1'!$AE73=1,"Inoperativo","Crítico"))))))))))))))) -> Estable
A74: 235 | B74: Fibra Óptica | C74: ESCUELA | D74: PREESCOLAR | E74: 11DJN2828Y - BELISARIO DOMINGUEZ | F74: AVENIDA PASEO DE LOS PAPAGAYOS NUMERO EXTERIOR: 201 , COLONIA SAN | G74: COLONIA SAN ISIDRO | H74: LEÓN | I74: 21.0926 | J74: -101.64813 | L74: =HYPERLINK("https://www.google.com/maps?q=" & I74 & "," & J74, "Ver en Google Maps") -> Ver en Google Maps | M74: 1
A75: 241 | B75: Fibra Óptica | C75: ESCUELA | D75: PREESCOLAR | E75: 11DJN2882S - NIÑOS HEROES | F75: CALLE PADRE ROBERTO GUERRA NUMERO EXTERIOR: SN, COLONIA LOS ANGEL | G75: COLONIA LOS ANGELES | H75: LEÓN | I75: 21.128907 | J75: -101.63899 | K75: ok | L75: =HYPERLINK("https://www.google.com/maps?q=" & I75 & "," & J75, "Ver en Google Maps") -> Ver en Google Maps | M75: 1 | N75: 45929 | O75: =DAY('BD1'!$N75) -> 29 | P75: =MONTH('BD1'!$N75) -> 9 | Q75: =YEAR('BD1'!$N75) -> 2025 | R75: 1 | S75: si | T75: si | U75: si | V75: si | W75: si | X75: si | Y75: si | Z75: si | AA75: 65.96 | AB75: 83.7 | AC75: La conexión fue rápida y constante, la navegación fue fluida, no se observan anomalías, tiene buena señal | AD75: José Mosqueda | AE75: =COUNTIF(S75:Z75, "si") -> 8 | AF75: =IF('BD1'!$AE75=8,"Estable",(IF('BD1'!$AE75=7,"Funcional con observaciones", (IF('BD1'!$AE75=6,"Funcional con observaciones",(IF('BD1'!$AE75=5,"Rendimiento bajo",(IF('BD1'!$AE75=4,"Parcialmente funcional",(IF('BD1'!$AE75=3,"Parcialmente funcional",(IF('BD1'!$AE75=2,"Inoperativo",(IF('BD1'!$AE75=1,"Inoperativo","Crítico"))))))))))))))) -> Estable
A76: 242 | B76: Fibra Óptica | C76: ESCUELA | D76: PREESCOLAR | E76: 11DJN2902P - JUAN ALDAMA | F76: OBSERVATORIO NUM. 102 UNIVERSIDAD DE LA SALLE | G76: COLONIA MIRADOR CAMPESTRE | H76: LEÓN | I76: 21.14747 | J76: -101.71567 | K76: ok | L76: =HYPERLINK("https://www.google.com/maps?q=" & I76 & "," & J76, "Ver en Google Maps") -> Ver en Google Maps | M76: 1 | N76: 45930 | O76: =DAY('BD1'!$N76) -> 30 | P76: =MONTH('BD1'!$N76) -> 9 | Q76: =YEAR('BD1'!$N76) -> 2025 | R76: 1 | S76: si | T76: si | U76: si | V76: si | W76: si | X76: si | Y76: si | Z76: si | AA76: 19.67 | AB76: 38.38 | AC76: La conexión fue rápida y constante, la navegación fue fluida, no se observan anomalías, tiene buena señal | AD76: José Mosqueda | AE76: =COUNTIF(S76:Z76, "si") -> 8 | AF76: =IF('BD1'!$AE76=8,"Estable",(IF('BD1'!$AE76=7,"Funcional con observaciones", (IF('BD1'!$AE76=6,"Funcional con observaciones",(IF('BD1'!$AE76=5,"Rendimiento bajo",(IF('BD1'!$AE76=4,"Parcialmente funcional",(IF('BD1'!$AE76=3,"Parcialmente funcional",(IF('BD1'!$AE76=2,"Inoperativo",(IF('BD1'!$AE76=1,"Inoperativo","Crítico"))))))))))))))) -> Estable
A77: 248 | B77: Fibra Óptica | C77: ESCUELA | D77: PREESCOLAR | E77: 11DJN3269K - DIEGO VELAZQUEZ | F77: CALLE CAMINO A SAN JOSE DEL POTRERO NUMERO EXTERIOR: SN, FRACCION | G77: COLONIA PEDREGAL DEL CARMEN | H77: LEÓN | I77: 21.11633 | J77: -101.6096 | K77: ok | L77: =HYPERLINK("https://www.google.com/maps?q=" & I77 & "," & J77, "Ver en Google Maps") -> Ver en Google Maps | M77: 1 | N77: 45931 | O77: =DAY('BD1'!$N77) -> 1 | P77: =MONTH('BD1'!$N77) -> 10 | Q77: =YEAR('BD1'!$N77) -> 2025 | R77: 1 | S77: si | T77: si | U77: si | V77: no | W77: si | X77: si | Y77: si | Z77: si | AA77: 43.63 | AB77: 16.91 | AC77: La conexión fue rápida hubo un pequeño lapso que no mostró de manera correcta el Youtube pero lo demás fue fluido, tiene buena señal | AD77: José Mosqueda | AE77: =COUNTIF(S77:Z77, "si") -> 7 | AF77: =IF('BD1'!$AE77=8,"Estable",(IF('BD1'!$AE77=7,"Funcional con observaciones", (IF('BD1'!$AE77=6,"Funcional con observaciones",(IF('BD1'!$AE77=5,"Rendimiento bajo",(IF('BD1'!$AE77=4,"Parcialmente funcional",(IF('BD1'!$AE77=3,"Parcialmente funcional",(IF('BD1'!$AE77=2,"Inoperativo",(IF('BD1'!$AE77=1,"Inoperativo","Crítico"))))))))))))))) -> Funcional con observaciones
A78: 252 | B78: Fibra Óptica | C78: ESCUELA | D78: PREESCOLAR | E78: 11DJN3656C - JUAN ENRIQUE PESTALOZZI | F78: BORGOÑA NUM. 129 VIBAR | G78: COLONIA VIBAR | H78: LEÓN | I78: 21.12973 | J78: -101.71687 | L78: =HYPERLINK("https://www.google.com/maps?q=" & I78 & "," & J78, "Ver en Google Maps") -> Ver en Google Maps | M78: 1
A79: 254 | B79: Fibra Óptica | C79: ESCUELA | D79: PREESCOLAR | E79: 11DJN3671V - CALMECAC | F79: JOSE DE JESUS LIRA NUM. 110 BOULEVARD MARIANO ESCOBEDO | G79: COLONIA LEON II | H79: LEÓN | I79: 21.11657 | J79: -101.73038 | K79: ok | L79: =HYPERLINK("https://www.google.com/maps?q=" & I79 & "," & J79, "Ver en Google Maps") -> Ver en Google Maps | M79: 1 | N79: 45930 | O79: =DAY('BD1'!$N79) -> 30 | P79: =MONTH('BD1'!$N79) -> 9 | Q79: =YEAR('BD1'!$N79) -> 2025 | R79: 1 | S79: si | T79: si | U79: si | V79: si | W79: si | X79: si | Y79: si | Z79: no | AA79: 11.03 | AB79: 33.51 | AC79: La conexión fue rápida y constante, la navegación fue fluida, no se observan anomalías, tiene buena señal pero es bajo el ancho de banda | AD79: José Mosqueda | AE79: =COUNTIF(S79:Z79, "si") -> 7 | AF79: =IF('BD1'!$AE79=8,"Estable",(IF('BD1'!$AE79=7,"Funcional con observaciones", (IF('BD1'!$AE79=6,"Funcional con observaciones",(IF('BD1'!$AE79=5,"Rendimiento bajo",(IF('BD1'!$AE79=4,"Parcialmente funcional",(IF('BD1'!$AE79=3,"Parcialmente funcional",(IF('BD1'!$AE79=2,"Inoperativo",(IF('BD1'!$AE79=1,"Inoperativo","Crítico"))))))))))))))) -> Funcional con observaciones
A80: 256 | B80: Fibra Óptica | C80: ESCUELA | D80: PREESCOLAR | E80: 11DJN3755C - JUAN AMOS COMENIO | F80: CALLE RIOLITA Y CALIZA NUMERO EXTERIOR: SN, COLONIA REAL DE LA JO | G80: COLONIA REAL DE LA JOYA | H80: LEÓN | I80: 21.1526 | J80: -101.75777 | K80: ok | L80: =HYPERLINK("https://www.google.com/maps?q=" & I80 & "," & J80, "Ver en Google Maps") -> Ver en Google Maps | M80: 1 | N80: 45930 | O80: =DAY('BD1'!$N80) -> 30 | P80: =MONTH('BD1'!$N80) -> 9 | Q80: =YEAR('BD1'!$N80) -> 2025 | R80: 1 | S80: si | T80: si | U80: si | V80: si | W80: si | X80: si | Y80: si | Z80: si | AA80: 14.84 | AB80: 36.17 | AC80: La conexión fue rápida y constante, la navegación fue fluida, no se observan anomalías, tiene buena señal | AD80: José Mosqueda | AE80: =COUNTIF(S80:Z80, "si") -> 8 | AF80: =IF('BD1'!$AE80=8,"Estable",(IF('BD1'!$AE80=7,"Funcional con observaciones", (IF('BD1'!$AE80=6,"Funcional con observaciones",(IF('BD1'!$AE80=5,"Rendimiento bajo",(IF('BD1'!$AE80=4,"Parcialmente funcional",(IF('BD1'!$AE80=3,"Parcialmente funcional",(IF('BD1'!$AE80=2,"Inoperativo",(IF('BD1'!$AE80=1,"Inoperativo","Crítico"))))))))))))))) -> Estable
A81: 257 | B81: Fibra Óptica | C81: OFICINA GUBERNAMENTAL | D81: N/A | E81: UNIDAD DE TELEVISION DE GUANAJUATO | F81: CALLE OAXACA 502, COLONIA ARBIDE, LEÓN, GTO | G81: COLONIA ARBIDE | H81: LEÓN | I81: 21.122704 | J81: -101.69342 | K81: ok | L81: =HYPERLINK("https://www.google.com/maps?q=" & I81 & "," & J81, "Ver en Google Maps") -> Ver en Google Maps | M81: 2 | N81: 45930 | O81: =DAY('BD1'!$N81) -> 30 | P81: =MONTH('BD1'!$N81) -> 9 | Q81: =YEAR('BD1'!$N81) -> 2025 | R81: 1 | S81: si | T81: si | U81: si | V81: si | W81: si | X81: si | Y81: si | Z81: si | AA81: 46.21 | AB81: 40.37 | AC81: La conexión fue rápida y constante, la navegación fue fluida, no se observan anomalías, tiene buena señal | AD81: José Mosqueda | AE81: =COUNTIF(S81:Z81, "si") -> 8 | AF81: =IF('BD1'!$AE81=8,"Estable",(IF('BD1'!$AE81=7,"Funcional con observaciones", (IF('BD1'!$AE81=6,"Funcional con observaciones",(IF('BD1'!$AE81=5,"Rendimiento bajo",(IF('BD1'!$AE81=4,"Parcialmente funcional",(IF('BD1'!$AE81=3,"Parcialmente funcional",(IF('BD1'!$AE81=2,"Inoperativo",(IF('BD1'!$AE81=1,"Inoperativo","Crítico"))))))))))))))) -> Estable
A82: 259 | B82: Fibra Óptica | C82: ESCUELA | D82: PREESCOLAR | E82: 11DJN3765J - JOSE VASCONCELOS | F82: CALLE MATISSE NUMERO EXTERIOR: 121 , COLONIA SAN MIGUEL DE RENTAR | G82: COLONIA SAN MIGUEL DE RENTERIA | H82: LEÓN | I82: 21.12249 | J82: -101.64601 | K82: ok | L82: =HYPERLINK("https://www.google.com/maps?q=" & I82 & "," & J82, "Ver en Google Maps") -> Ver en Google Maps | M82: 1 | N82: 45931 | O82: =DAY('BD1'!$N82) -> 1 | P82: =MONTH('BD1'!$N82) -> 10 | Q82: =YEAR('BD1'!$N82) -> 2025 | R82: 1 | S82: si | T82: si | U82: si | V82: si | W82: si | X82: si | Y82: si | Z82: si | AA82: 55.76 | AB82: 43.01 | AC82: La conexión fue rápida y constante, la navegación fue fluida, no se observan anomalías, tiene buena señal | AD82: José Mosqueda | AE82: =COUNTIF(S82:Z82, "si") -> 8 | AF82: =IF('BD1'!$AE82=8,"Estable",(IF('BD1'!$AE82=7,"Funcional con observaciones", (IF('BD1'!$AE82=6,"Funcional con observaciones",(IF('BD1'!$AE82=5,"Rendimiento bajo",(IF('BD1'!$AE82=4,"Parcialmente funcional",(IF('BD1'!$AE82=3,"Parcialmente funcional",(IF('BD1'!$AE82=2,"Inoperativo",(IF('BD1'!$AE82=1,"Inoperativo","Crítico"))))))))))))))) -> Estable
A83: 264 | B83: Fibra Óptica | C83: ESCUELA | D83: PREESCOLAR | E83: 11DJN4085K - MA. ESTHER VALTIERRA | F83: DE LA LIRA NUM. 130 | G83: COLONIA DELTA DE JEREZ | H83: LEÓN | I83: 21.08565 | J83: -101.62854 | L83: =HYPERLINK("https://www.google.com/maps?q=" & I83 & "," & J83, "Ver en Google Maps") -> Ver en Google Maps | M83: 1
A84: 265 | B84: Fibra Óptica | C84: ESCUELA | D84: PREESCOLAR | E84: 11DJN4087I - MIGUEL BERNAL JIMENEZ | F84: GRANJA ESTEFANIA NUM. 202 | G84: COLONIA GRANJENO IVEG | H84: LEÓN | I84: 21.07785 | J84: -101.65033 | L84: =HYPERLINK("https://www.google.com/maps?q=" & I84 & "," & J84, "Ver en Google Maps") -> Ver en Google Maps | M84: 1
A85: 266 | B85: Fibra Óptica | C85: ESCUELA | D85: PREESCOLAR | E85: 11DJN4088H - RAUL BOLAÑOS MARTINEZ | F85: QUIO S/N ANTIGUA CARRETERA A LAGOS DE MORENO | G85: COLONIA LA ERMITA | H85: LEÓN | I85: 21.15031 | J85: -101.73293 | K85: ok | L85: =HYPERLINK("https://www.google.com/maps?q=" & I85 & "," & J85, "Ver en Google Maps") -> Ver en Google Maps | M85: 1 | N85: 45930 | O85: =DAY('BD1'!$N85) -> 30 | P85: =MONTH('BD1'!$N85) -> 9 | Q85: =YEAR('BD1'!$N85) -> 2025 | R85: 1 | S85: si | T85: si | U85: si | V85: si | W85: si | X85: si | Y85: si | Z85: si | AA85: 63.86 | AB85: 30.63 | AC85: La conexión fue rápida y constante, la navegación fue fluida, no se observan anomalías, tiene buena señal | AD85: José Mosqueda | AE85: =COUNTIF(S85:Z85, "si") -> 8 | AF85: =IF('BD1'!$AE85=8,"Estable",(IF('BD1'!$AE85=7,"Funcional con observaciones", (IF('BD1'!$AE85=6,"Funcional con observaciones",(IF('BD1'!$AE85=5,"Rendimiento bajo",(IF('BD1'!$AE85=4,"Parcialmente funcional",(IF('BD1'!$AE85=3,"Parcialmente funcional",(IF('BD1'!$AE85=2,"Inoperativo",(IF('BD1'!$AE85=1,"Inoperativo","Crítico"))))))))))))))) -> Estable
A86: 267 | B86: Fibra Óptica | C86: ESCUELA | D86: PREESCOLAR | E86: 11DJN4109D - JUAN DE DIOS PEZA | F86: ALDEA NUM. 604 | G86: COLONIA LA MOREÑA | H86: LEÓN | I86: 21.07309 | J86: -101.64436 | L86: =HYPERLINK("https://www.google.com/maps?q=" & I86 & "," & J86, "Ver en Google Maps") -> Ver en Google Maps | M86: 1
A87: 269 | B87: Fibra Óptica | C87: ESCUELA | D87: PREESCOLAR | E87: 11DJN4121Z - OCTAVIO PAZ | F87: CALLE DE LA POSTURA NUMERO EXTERIOR: SN, FRACCIONAMIENTO NUEVO AM | G87: COLONIA NUEVO AMANECER | H87: LEÓN | I87: 21.11683 | J87: -101.6031 | K87: ok | L87: =HYPERLINK("https://www.google.com/maps?q=" & I87 & "," & J87, "Ver en Google Maps") -> Ver en Google Maps | M87: 1 | N87: 45931 | O87: =DAY('BD1'!$N87) -> 1 | P87: =MONTH('BD1'!$N87) -> 10 | Q87: =YEAR('BD1'!$N87) -> 2025 | R87: 1 | S87: si | T87: si | U87: si | V87: si | W87: si | X87: si | Y87: si | Z87: si | AA87: 99.43 | AB87: 73.41 | AC87: La conexión fue rápida y constante, la navegación fue fluida, no se observan anomalías, tiene buena señal | AD87: Rafael Amaral | AE87: =COUNTIF(S87:Z87, "si") -> 8 | AF87: =IF('BD1'!$AE87=8,"Estable",(IF('BD1'!$AE87=7,"Funcional con observaciones", (IF('BD1'!$AE87=6,"Funcional con observaciones",(IF('BD1'!$AE87=5,"Rendimiento bajo",(IF('BD1'!$AE87=4,"Parcialmente funcional",(IF('BD1'!$AE87=3,"Parcialmente funcional",(IF('BD1'!$AE87=2,"Inoperativo",(IF('BD1'!$AE87=1,"Inoperativo","Crítico"))))))))))))))) -> Estable
A88: 274 | B88: Fibra Óptica | C88: ESCUELA | D88: PREESCOLAR | E88: 11DJN4146H - LEV SEMENOVICH VIGOTSKY | F88: CALLE FRAY RICARDO NUMERO EXTERIOR: 202 , COLONIA AMPLIACION SAN | G88: COLONIA AMPLIACION SAN FRANCISCO | H88: LEÓN | I88: 21.096453 | J88: -101.59857 | K88: ok | L88: =HYPERLINK("https://www.google.com/maps?q=" & I88 & "," & J88, "Ver en Google Maps") -> Ver en Google Maps | M88: 1 | N88: 45931 | O88: =DAY('BD1'!$N88) -> 1 | P88: =MONTH('BD1'!$N88) -> 10 | Q88: =YEAR('BD1'!$N88) -> 2025 | R88: 1 | S88: si | T88: si | U88: si | V88: si | W88: si | X88: si | Y88: no | Z88: si | AA88: 20.2 | AB88: 9.1 | AC88: La conexión fue rápida y constante, la navegación fue fluida, no se observan anomalías, tiene buena señal solo que presentó perdida de paquetes puede deberse a la lejanía del Acces Point y no se nos permitio el ingreso al plantel | AD88: José Mosqueda | AE88: =COUNTIF(S88:Z88, "si") -> 7 | AF88: =IF('BD1'!$AE88=8,"Estable",(IF('BD1'!$AE88=7,"Funcional con observaciones", (IF('BD1'!$AE88=6,"Funcional con observaciones",(IF('BD1'!$AE88=5,"Rendimiento bajo",(IF('BD1'!$AE88=4,"Parcialmente funcional",(IF('BD1'!$AE88=3,"Parcialmente funcional",(IF('BD1'!$AE88=2,"Inoperativo",(IF('BD1'!$AE88=1,"Inoperativo","Crítico"))))))))))))))) -> Funcional con observaciones
A89: 275 | B89: Fibra Óptica | C89: ESCUELA | D89: PREESCOLAR | E89: 11DJN4148F - SALVADOR DIAZ MIRON | F89: FLOR DE HIELO S/N | G89: COLONIA CONVIVE | H89: LEÓN | I89: 21.12446 | J89: -101.74466 | K89: ok | L89: =HYPERLINK("https://www.google.com/maps?q=" & I89 & "," & J89, "Ver en Google Maps") -> Ver en Google Maps | M89: 1 | N89: 45930 | O89: =DAY('BD1'!$N89) -> 30 | P89: =MONTH('BD1'!$N89) -> 9 | Q89: =YEAR('BD1'!$N89) -> 2025 | R89: 1 | S89: si | T89: si | U89: si | V89: si | W89: si | X89: si | Y89: si | Z89: si | AA89: 27.74 | AB89: 11.76 | AC89: La conexión fue rápida y constante, la navegación fue fluida, no se observan anomalías, tiene buena señal | AD89: José Mosqueda | AE89: =COUNTIF(S89:Z89, "si") -> 8 | AF89: =IF('BD1'!$AE89=8,"Estable",(IF('BD1'!$AE89=7,"Funcional con observaciones", (IF('BD1'!$AE89=6,"Funcional con observaciones",(IF('BD1'!$AE89=5,"Rendimiento bajo",(IF('BD1'!$AE89=4,"Parcialmente funcional",(IF('BD1'!$AE89=3,"Parcialmente funcional",(IF('BD1'!$AE89=2,"Inoperativo",(IF('BD1'!$AE89=1,"Inoperativo","Crítico"))))))))))))))) -> Estable
A90: 280 | B90: Fibra Óptica | C90: ESCUELA | D90: SECUNDARIA | E90: 11ETV1034Y - TELESECUNDARIA NUM. 1034 | F90: Blvd Wigberto Jimenez Moreno Num Ext 704, Condominio Buenos Aires, Leon de los Aldama | G90: COLONIA CONDOMINIO BUENOS AIRES | H90: LEÓN | I90: 21.095533 | J90: -101.67177 | L90: =HYPERLINK("https://www.google.com/maps?q=" & I90 & "," & J90, "Ver en Google Maps") -> Ver en Google Maps | M90: 2
A91: 281 | B91: Fibra Óptica | C91: ESCUELA | D91: PREESCOLAR | E91: 11DJN4249D - MARIA GREVER | F91: BAHIA DEL SENA ESQUINA BAHIA PUERTO PRINCIPE S/N | G91: COLONIA DELTA 2000 | H91: LEÓN | I91: 21.07761 | J91: -101.62772 | L91: =HYPERLINK("https://www.google.com/maps?q=" & I91 & "," & J91, "Ver en Google Maps") -> Ver en Google Maps | M91: 1
A92: 283 | B92: Fibra Óptica | C92: ESCUELA | D92: PREESCOLAR | E92: 11DJN4287G - JOSE CHAVEZ MORADO | F92: ALTAR DE SAN JUAN S/N FRENTE A TEMPLO | G92: COLONIA VILLAS DE SAN JUAN | H92: LEÓN | I92: 21.09245 | J92: -101.59121 | L92: =HYPERLINK("https://www.google.com/maps?q=" & I92 & "," & J92, "Ver en Google Maps") -> Ver en Google Maps | M92: 1
A93: 285 | B93: Fibra Óptica | C93: ESCUELA | D93: PRIMARIA | E93: 11DPR1922M - VICENTE GUERRERO | F93: EJIDO POMPA | G93: COLONIA FRACCIONES DE HACIENDA LA POMPA | H93: LEÓN | I93: 21.08793 | J93: -101.69023 | L93: =HYPERLINK("https://www.google.com/maps?q=" & I93 & "," & J93, "Ver en Google Maps") -> Ver en Google Maps | M93: 1
A94: 286 | B94: Fibra Óptica | C94: ESCUELA | D94: PRIMARIA | E94: 11DPR0041C - GUSTAVO DIAZ ORDAZ | F94: NARDOS Y BUGAMBILIAS S/N | G94: COLONIA JARDINES DE JEREZ 1RA. SECCION | H94: LEÓN | I94: 21.09622 | J94: -101.63906 | L94: =HYPERLINK("https://www.google.com/maps?q=" & I94 & "," & J94, "Ver en Google Maps") -> Ver en Google Maps | M94: 1
A95: 287 | B95: Fibra Óptica | C95: ESCUELA | D95: PRIMARIA | E95: 11DPR0923E - HEROES DE CHAPULTEPEC | F95: CALLE FERNANDO MONTES DE OCA NUMERO EXTERIOR: 204 , COLONIA HEROE | G95: COLONIA HEROES DE CHAPULTEPEC | H95: LEÓN | I95: 21.14207 | J95: -101.67757 | K95: ok | L95: =HYPERLINK("https://www.google.com/maps?q=" & I95 & "," & J95, "Ver en Google Maps") -> Ver en Google Maps | M95: 1 | N95: 45929 | O95: =DAY('BD1'!$N95) -> 29 | P95: =MONTH('BD1'!$N95) -> 9 | Q95: =YEAR('BD1'!$N95) -> 2025 | R95: 1 | S95: si | T95: si | U95: si | V95: si | W95: si | X95: si | Y95: si | Z95: si | AA95: 65.36 | AB95: 76.68 | AC95: La conexión fue rápida y constante, la navegación fue fluida, no se observan anomalías, tiene buena señal | AD95: José Mosqueda | AE95: =COUNTIF(S95:Z95, "si") -> 8 | AF95: =IF('BD1'!$AE95=8,"Estable",(IF('BD1'!$AE95=7,"Funcional con observaciones", (IF('BD1'!$AE95=6,"Funcional con observaciones",(IF('BD1'!$AE95=5,"Rendimiento bajo",(IF('BD1'!$AE95=4,"Parcialmente funcional",(IF('BD1'!$AE95=3,"Parcialmente funcional",(IF('BD1'!$AE95=2,"Inoperativo",(IF('BD1'!$AE95=1,"Inoperativo","Crítico"))))))))))))))) -> Estable
A96: 295 | B96: Fibra Óptica | C96: ESCUELA | D96: PRIMARIA | E96: 11DPR0205W - JUAN ALDAMA | F96: OCEANO ATLANTICO NUM. 302 | G96: COLONIA LINDAVISTA | H96: LEÓN | I96: 21.144442 | J96: -101.7038 | K96: ok | L96: =HYPERLINK("https://www.google.com/maps?q=" & I96 & "," & J96, "Ver en Google Maps") -> Ver en Google Maps | M96: 1 | N96: 45933 | O96: =DAY('BD1'!$N96) -> 3 | P96: =MONTH('BD1'!$N96) -> 10 | Q96: =YEAR('BD1'!$N96) -> 2025 | R96: 1 | S96: si | T96: si | U96: si | V96: si | W96: si | X96: si | Y96: si | Z96: si | AA96: 16.99 | AB96: 33.48 | AC96: La conexión fue rápida y constante, la navegación fue fluida, no se observan anomalías, tiene buena señal | AD96: Rafael Amaral | AE96: =COUNTIF(S96:Z96, "si") -> 8 | AF96: =IF('BD1'!$AE96=8,"Estable",(IF('BD1'!$AE96=7,"Funcional con observaciones", (IF('BD1'!$AE96=6,"Funcional con observaciones",(IF('BD1'!$AE96=5,"Rendimiento bajo",(IF('BD1'!$AE96=4,"Parcialmente funcional",(IF('BD1'!$AE96=3,"Parcialmente funcional",(IF('BD1'!$AE96=2,"Inoperativo",(IF('BD1'!$AE96=1,"Inoperativo","Crítico"))))))))))))))) -> Estable
A97: 296 | B97: Fibra Óptica | C97: ESCUELA | D97: PRIMARIA | E97: 11DPR0276Q - VENUSTIANO CARRANZA | F97: BALTAZAR NUM. 103 | G97: COLONIA LA PISCINA | H97: LEÓN | I97: 21.09517 | J97: -101.71593 | L97: =HYPERLINK("https://www.google.com/maps?q=" & I97 & "," & J97, "Ver en Google Maps") -> Ver en Google Maps | M97: 1
A98: 298 | B98: Fibra Óptica | C98: ESCUELA | D98: PRIMARIA | E98: 11DPR0328F - J. JESUS MAYAGOITIA JAIME | F98: LUIS FREG NUM. 304-A | G98: COLONIA PLAZA DE TOROS | H98: LEÓN | I98: 21.1009 | J98: -101.69466 | K98: ok | L98: =HYPERLINK("https://www.google.com/maps?q=" & I98 & "," & J98, "Ver en Google Maps") -> Ver en Google Maps | M98: 2 | N98: 45932 | O98: =DAY('BD1'!$N98) -> 2 | P98: =MONTH('BD1'!$N98) -> 10 | Q98: =YEAR('BD1'!$N98) -> 2025 | R98: 1 | S98: si | T98: si | U98: si | V98: si | W98: si | X98: si | Y98: si | Z98: si | AA98: 101.82 | AB98: 69.64 | AC98: La conexión fue rápida y constante, la navegación fue fluida, no se observan anomalías, tiene buena señal | AD98: José Mosqueda | AE98: =COUNTIF(S98:Z98, "si") -> 8 | AF98: =IF('BD1'!$AE98=8,"Estable",(IF('BD1'!$AE98=7,"Funcional con observaciones", (IF('BD1'!$AE98=6,"Funcional con observaciones",(IF('BD1'!$AE98=5,"Rendimiento bajo",(IF('BD1'!$AE98=4,"Parcialmente funcional",(IF('BD1'!$AE98=3,"Parcialmente funcional",(IF('BD1'!$AE98=2,"Inoperativo",(IF('BD1'!$AE98=1,"Inoperativo","Crítico"))))))))))))))) -> Estable
A99: 305 | B99: Fibra Óptica | C99: ESCUELA | D99: PRIMARIA | E99: 11DPR0350H - IGNACIO ZARAGOZA | F99: CAMINO PANORAMA NUM. 10803 | G99: COLONIA VALLE DEL CAMPESTRE | H99: LEÓN | I99: 21.15585 | J99: -101.69033 | K99: ok | L99: =HYPERLINK("https://www.google.com/maps?q=" & I99 & "," & J99, "Ver en Google Maps") -> Ver en Google Maps | M99: 1 | N99: 45929 | O99: =DAY('BD1'!$N99) -> 29 | P99: =MONTH('BD1'!$N99) -> 9 | Q99: =YEAR('BD1'!$N99) -> 2025 | R99: 1 | S99: si | T99: si | U99: si | V99: no | W99: si | X99: si | Y99: no | Z99: si | AA99: 18.33 | AB99: 24.28 | AC99: La conexión es intermitente, puede deberse a que el acces point está lejos de la calle y no se nos permitió el ingreso al plantel | AD99: José Mosqueda | AE99: =COUNTIF(S99:Z99, "si") -> 6 | AF99: =IF('BD1'!$AE99=8,"Estable",(IF('BD1'!$AE99=7,"Funcional con observaciones", (IF('BD1'!$AE99=6,"Funcional con observaciones",(IF('BD1'!$AE99=5,"Rendimiento bajo",(IF('BD1'!$AE99=4,"Parcialmente funcional",(IF('BD1'!$AE99=3,"Parcialmente funcional",(IF('BD1'!$AE99=2,"Inoperativo",(IF('BD1'!$AE99=1,"Inoperativo","Crítico"))))))))))))))) -> Funcional con observaciones
A100: 307 | B100: Fibra Óptica | C100: ESCUELA | D100: PRIMARIA | E100: 11DPR1429K - CUAUHTEMOC | F100: NOGAL NUM. 127 | G100: COLONIA LAS ARBOLEDAS | H100: LEÓN | I100: 21.10349 | J100: -101.66767 | K100: ok | L100: =HYPERLINK("https://www.google.com/maps?q=" & I100 & "," & J100, "Ver en Google Maps") -> Ver en Google Maps | M100: 1 | N100: 45934 | O100: =DAY('BD1'!$N100) -> 4 | P100: =MONTH('BD1'!$N100) -> 10 | Q100: =YEAR('BD1'!$N100) -> 2025 | R100: 1 | S100: si | T100: si | U100: si | V100: si | W100: si | X100: si | Y100: si | Z100: si | AA100: 66.58 | AB100: 25.95 | AC100: La conexión fue rápida y constante, la navegación fue fluida, no se observan anomalías, tiene buena señal | AD100: José Mosqueda | AE100: =COUNTIF(S100:Z100, "si") -> 8 | AF100: =IF('BD1'!$AE100=8,"Estable",(IF('BD1'!$AE100=7,"Funcional con observaciones", (IF('BD1'!$AE100=6,"Funcional con observaciones",(IF('BD1'!$AE100=5,"Rendimiento bajo",(IF('BD1'!$AE100=4,"Parcialmente funcional",(IF('BD1'!$AE100=3,"Parcialmente funcional",(IF('BD1'!$AE100=2,"Inoperativo",(IF('BD1'!$AE100=1,"Inoperativo","Crítico"))))))))))))))) -> Estable
...

Sheet BD2
A1: Sitio | B1: Tipo de conexión | C1: Tipo de espacio | D1: Tipo | E1: Nombre | F1: Ubicación | G1: Colonia | H1: Municipio | I1: Latitud | J1: Longitud | K1: Visitado | L1: Liga | M1: Aps | N1: Fecha de rev | O1: Día | P1: Mes | Q1: Año | R1: Visita | S1: Conexión fácil | T1: Mensajero | U1: Facebook | V1: Youtube | W1: Maps | X1: Navegador | Y1: Nav Constante | Z1: Buen ancho de banda | AA1: Bajada | AB1: Subida | AC1: Observaciones | AD1: Supervisor | AE1: Calificación | AF1: Situación
A2: 1 | B2: Fibra Óptica | C2: PLAZA PÚBLICA | D2: N/A | E2: CRUZ DE CANTERA (JUNTO A LAS CANCHAS DEL MALECON) | F2: CRUZ DE CANTERA SANTA FE | G2: COLONIA SANTA FE | H2: LEÓN | I2: 21.127368 | J2: -101.67531 | K2: ok | L2: =HYPERLINK("https://www.google.com/maps?q=" & I2 & "," & J2, "Ver en Google Maps") -> Ver en Google Maps | M2: 1 | N2: 45954 | O2: =DAY('BD2'!$N2) -> 24 | P2: =MONTH('BD2'!$N2) -> 10 | Q2: =YEAR('BD2'!$N2) -> 2025 | R2: 2 | S2: si | T2: si | U2: si | V2: si | W2: si | X2: si | Y2: si | Z2: =IF('BD2'!$AA2>=14, "si", "no") -> si | AA2: 119 | AB2: 42.8 | AC2: La conexión fue rápida y constante, la navegación fue fluida, no se observan anomalías, tiene buena señal | AD2: José Mosqueda | AE2: =COUNTIF(S2:Z2, "si") -> 8 | AF2: =IF(AE2=8,"Estable",(IF(AE2=7,"Funcional con observaciones", (IF(AE2=6,"Funcional con observaciones",(IF(AE2=5,"Rendimiento bajo",(IF(AE2=4,"Parcialmente funcional",(IF(AE2=3,"Parcialmente funcional",(IF(AE2=2,"Inoperativo",(IF(AE2=1,"Inoperativo","Crítico"))))))))))))))) -> Estable
A3: 2 | B3: Fibra Óptica | C3: PLAZA PÚBLICA | D3: N/A | E3: JARDINES DE SAN SEBASTIAN | F3: JARDINES DE SAN SEBASTIAN II | G3: COLONIA SAN SEBASTIAN | H3: LEÓN | I3: 21.099483 | J3: -101.6999 | K3: ok | L3: =HYPERLINK("https://www.google.com/maps?q=" & I3 & "," & J3, "Ver en Google Maps") -> Ver en Google Maps | M3: 1 | N3: 45964 | O3: =DAY('BD2'!$N3) -> 3 | P3: =MONTH('BD2'!$N3) -> 11 | Q3: =YEAR('BD2'!$N3) -> 2025 | R3: 2 | S3: si | T3: si | U3: si | V3: si | W3: si | X3: si | Y3: si | Z3: =IF('BD2'!$AA3 < 14, "no", "si") -> si | AA3: 50.6 | AB3: 34.2 | AC3: La conexión fue rápida y constante, la navegación fue fluida, no se observan anomalías, tiene buena señal | AD3: José Mosqueda | AE3: =COUNTIF(S3:Z3, "si") -> 8 | AF3: =IF(AE3=8,"Estable",(IF(AE3=7,"Funcional con observaciones", (IF(AE3=6,"Funcional con observaciones",(IF(AE3=5,"Rendimiento bajo",(IF(AE3=4,"Parcialmente funcional",(IF(AE3=3,"Parcialmente funcional",(IF(AE3=2,"Inoperativo",(IF(AE3=1,"Inoperativo","Crítico"))))))))))))))) -> Estable
A4: 3 | B4: Fibra Óptica | C4: PLAZA PÚBLICA | D4: N/A | E4: PLAZA COMUNITARIA VILLA DE LAS FLORES | F4: HEROES DE LA INDEPENDENCIA VILLA DE LAS FLORES | G4: COLONIA VILLA DE LAS FLORES | H4: LEÓN | I4: 21.122248 | J4: -101.6506 | K4: ok | L4: =HYPERLINK("https://www.google.com/maps?q=" & I4 & "," & J4, "Ver en Google Maps") -> Ver en Google Maps | M4: 1 | N4: 45955 | O4: =DAY('BD2'!$N4) -> 25 | P4: =MONTH('BD2'!$N4) -> 10 | Q4: =YEAR('BD2'!$N4) -> 2025 | R4: 2 | S4: no | T4: no | U4: no | V4: no | W4: no | X4: no | Y4: no | Z4: =IF('BD2'!$AA4 < 14, "no", "si") -> no | AA4: 0 | AB4: 0 | AC4: No fue posible realizar el análisis por que no había señal | AD4: José Mosqueda | AE4: =COUNTIF(S4:Z4, "si") -> 0 | AF4: =IF(AE4=8,"Estable",(IF(AE4=7,"Funcional con observaciones", (IF(AE4=6,"Funcional con observaciones",(IF(AE4=5,"Rendimiento bajo",(IF(AE4=4,"Parcialmente funcional",(IF(AE4=3,"Parcialmente funcional",(IF(AE4=2,"Inoperativo",(IF(AE4=1,"Inoperativo","Crítico"))))))))))))))) -> Crítico
A5: 4 | B5: Fibra Óptica | C5: PLAZA PÚBLICA | D5: N/A | E5: PLAZA PUBLICA EL LUCERO | F5: MARFIX EL LUCERO II | G5: COLONIA EL LUCERO | H5: LEÓN | I5: 21.136565 | J5: -101.66825 | K5: ok | L5: =HYPERLINK("https://www.google.com/maps?q=" & I5 & "," & J5, "Ver en Google Maps") -> Ver en Google Maps | M5: 1 | N5: 45954 | O5: =DAY('BD2'!$N5) -> 24 | P5: =MONTH('BD2'!$N5) -> 10 | Q5: =YEAR('BD2'!$N5) -> 2025 | R5: 2 | S5: si | T5: si | U5: si | V5: si | W5: si | X5: si | Y5: si | Z5: =IF('BD2'!$AA5 < 14, "no", "si") -> si | AA5: 54.1 | AB5: 53 | AC5: La conexión fue rápida y constante, la navegación fue fluida, no se observan anomalías, tiene buena señal | AD5: José Mosqueda | AE5: =COUNTIF(S5:Z5, "si") -> 8 | AF5: =IF(AE5=8,"Estable",(IF(AE5=7,"Funcional con observaciones", (IF(AE5=6,"Funcional con observaciones",(IF(AE5=5,"Rendimiento bajo",(IF(AE5=4,"Parcialmente funcional",(IF(AE5=3,"Parcialmente funcional",(IF(AE5=2,"Inoperativo",(IF(AE5=1,"Inoperativo","Crítico"))))))))))))))) -> Estable
A6: 5 | B6: Fibra Óptica | C6: ESPACIO DEPORTIVO | D6: N/A | E6: AGUA AZUL | F6: DELTA AGUA AZUL | G6: COLONIA AGUA AZUL | H6: LEÓN | I6: 21.103264 | J6: -101.61151 | K6: ok | L6: =HYPERLINK("https://www.google.com/maps?q=" & I6 & "," & J6, "Ver en Google Maps") -> Ver en Google Maps | M6: 1 | N6: 45957 | O6: =DAY('BD2'!$N6) -> 27 | P6: =MONTH('BD2'!$N6) -> 10 | Q6: =YEAR('BD2'!$N6) -> 2025 | R6: 2 | S6: si | T6: si | U6: si | V6: si | W6: si | X6: si | Y6: si | Z6: =IF('BD2'!$AA6 < 14, "no", "si") -> si | AA6: 59.5 | AB6: 30.3 | AC6: La conexión fue rápida y constante, la navegación fue fluida, no se observan anomalías, tiene buena señal | AD6: José Mosqueda | AE6: =COUNTIF(S6:Z6, "si") -> 8 | AF6: =IF(AE6=8,"Estable",(IF(AE6=7,"Funcional con observaciones", (IF(AE6=6,"Funcional con observaciones",(IF(AE6=5,"Rendimiento bajo",(IF(AE6=4,"Parcialmente funcional",(IF(AE6=3,"Parcialmente funcional",(IF(AE6=2,"Inoperativo",(IF(AE6=1,"Inoperativo","Crítico"))))))))))))))) -> Estable
A7: 6 | B7: Fibra Óptica | C7: ESPACIO DEPORTIVO | D7: N/A | E7: LOS ANGELES | F7: VALLE DE LOS NOGALES ANGELES, LOS | G7: COLONIA LOS ANGELES | H7: LEÓN | I7: 21.131813 | J7: -101.64046 | K7: ok | L7: =HYPERLINK("https://www.google.com/maps?q=" & I7 & "," & J7, "Ver en Google Maps") -> Ver en Google Maps | M7: 1 | N7: 45955 | O7: =DAY('BD2'!$N7) -> 25 | P7: =MONTH('BD2'!$N7) -> 10 | Q7: =YEAR('BD2'!$N7) -> 2025 | R7: 2 | S7: si | T7: si | U7: si | V7: si | W7: si | X7: si | Y7: si | Z7: =IF('BD2'!$AA7 < 14, "no", "si") -> si | AA7: 43.3 | AB7: 22.3 | AC7: La conexión fue rápida y constante, la navegación fue fluida, no se observan anomalías, tiene buena señal | AD7: José Mosqueda | AE7: =COUNTIF(S7:Z7, "si") -> 8 | AF7: =IF(AE7=8,"Estable",(IF(AE7=7,"Funcional con observaciones", (IF(AE7=6,"Funcional con observaciones",(IF(AE7=5,"Rendimiento bajo",(IF(AE7=4,"Parcialmente funcional",(IF(AE7=3,"Parcialmente funcional",(IF(AE7=2,"Inoperativo",(IF(AE7=1,"Inoperativo","Crítico"))))))))))))))) -> Estable
A8: 7 | B8: Fibra Óptica | C8: ESPACIO DEPORTIVO | D8: N/A | E8: CENTRO DEPORTIVO LAS JOYAS | F8: BALCÓN DE LOS RUISEÑORES 208, BALCONES DE LA JOYA, 37355 LEÓN, GTO. | G8: COLONIA BALCONES DE LA JOYA | H8: LEÓN | I8: 21.12784 | J8: -101.74435 | K8: ok | L8: =HYPERLINK("https://www.google.com/maps?q=" & I8 & "," & J8, "Ver en Google Maps") -> Ver en Google Maps | M8: 1 | N8: 45960 | O8: =DAY('BD2'!$N8) -> 30 | P8: =MONTH('BD2'!$N8) -> 10 | Q8: =YEAR('BD2'!$N8) -> 2025 | R8: 2 | S8: no | T8: no | U8: no | V8: no | W8: no | X8: no | Y8: no | Z8: =IF('BD2'!$AA8 < 14, "no", "si") -> no | AA8: 0 | AB8: 0 | AC8: Sitio sin servicio, se visualiza el SSID pero no da salida a internet | AD8: José Mosqueda | AE8: =COUNTIF(S8:Z8, "si") -> 0 | AF8: =IF(AE8=8,"Estable",(IF(AE8=7,"Funcional con observaciones", (IF(AE8=6,"Funcional con observaciones",(IF(AE8=5,"Rendimiento bajo",(IF(AE8=4,"Parcialmente funcional",(IF(AE8=3,"Parcialmente funcional",(IF(AE8=2,"Inoperativo",(IF(AE8=1,"Inoperativo","Crítico"))))))))))))))) -> Crítico
A9: 8 | B9: Fibra Óptica | C9: ESPACIO DEPORTIVO | D9: N/A | E9: DEPORTIVA I (UNIDAD DEPORTIVA I) | F9: TABLERO DEPORTIVA I | G9: COLONIA LEÓN I | H9: LEÓN | I9: 21.145551 | J9: -101.65661 | K9: ok | L9: =HYPERLINK("https://www.google.com/maps?q=" & I9 & "," & J9, "Ver en Google Maps") -> Ver en Google Maps | M9: 1 | N9: 45955 | O9: =DAY('BD2'!$N9) -> 25 | P9: =MONTH('BD2'!$N9) -> 10 | Q9: =YEAR('BD2'!$N9) -> 2025 | R9: 2 | S9: si | T9: si | U9: si | V9: si | W9: si | X9: si | Y9: si | Z9: =IF('BD2'!$AA9 < 14, "no", "si") -> si | AA9: 27.7 | AB9: 8.21 | AC9: La conexión fue rápida y constante, la navegación fue fluida, no se observan anomalías, tiene buena señal | AD9: José Mosqueda | AE9: =COUNTIF(S9:Z9, "si") -> 8 | AF9: =IF(AE9=8,"Estable",(IF(AE9=7,"Funcional con observaciones", (IF(AE9=6,"Funcional con observaciones",(IF(AE9=5,"Rendimiento bajo",(IF(AE9=4,"Parcialmente funcional",(IF(AE9=3,"Parcialmente funcional",(IF(AE9=2,"Inoperativo",(IF(AE9=1,"Inoperativo","Crítico"))))))))))))))) -> Estable
A10: 9 | B10: Fibra Óptica | C10: ESPACIO DEPORTIVO | D10: N/A | E10: ECHEVESTE 2000 | F10: NABO ECHEVESTE 2000 | G10: COLONIA ECHEVESTE 2000 | H10: LEÓN | I10: 21.179691 | J10: -101.67001 | K10: ok | L10: =HYPERLINK("https://www.google.com/maps?q=" & I10 & "," & J10, "Ver en Google Maps") -> Ver en Google Maps | M10: 1 | N10: 45952 | O10: =DAY('BD2'!$N10) -> 22 | P10: =MONTH('BD2'!$N10) -> 10 | Q10: =YEAR('BD2'!$N10) -> 2025 | R10: 2 | S10: si | T10: si | U10: si | V10: si | W10: si | X10: si | Y10: si | Z10: =IF('BD2'!$AA10 < 14, "no", "si") -> si | AA10: 70.7 | AB10: 7.15 | AC10: La conexión fue rápida y constante, la navegación fue fluida, no se observan anomalías, tiene buena señal | AD10: José Mosqueda | AE10: =COUNTIF(S10:Z10, "si") -> 8 | AF10: =IF(AE10=8,"Estable",(IF(AE10=7,"Funcional con observaciones", (IF(AE10=6,"Funcional con observaciones",(IF(AE10=5,"Rendimiento bajo",(IF(AE10=4,"Parcialmente funcional",(IF(AE10=3,"Parcialmente funcional",(IF(AE10=2,"Inoperativo",(IF(AE10=1,"Inoperativo","Crítico"))))))))))))))) -> Estable
A11: 10 | B11: Fibra Óptica | C11: ESPACIO DEPORTIVO | D11: N/A | E11: ECHEVESTE | F11: HERMENEGILDO BUSTOS HACIENDA ECHEVESTE | G11: COLONIA HACIENDA ECHEVESTE | H11: LEÓN | I11: 21.187876 | J11: -101.66685 | K11: ok | L11: =HYPERLINK("https://www.google.com/maps?q=" & I11 & "," & J11, "Ver en Google Maps") -> Ver en Google Maps | M11: 1 | N11: 45952 | O11: =DAY('BD2'!$N11) -> 22 | P11: =MONTH('BD2'!$N11) -> 10 | Q11: =YEAR('BD2'!$N11) -> 2025 | R11: 2 | S11: si | T11: si | U11: si | V11: si | W11: si | X11: si | Y11: si | Z11: =IF('BD2'!$AA11 < 14, "no", "si") -> si | AA11: 48 | AB11: 16.1 | AC11: La conexión fue rápida y constante, la navegación fue fluida, no se observan anomalías, tiene buena señal | AD11: José Mosqueda | AE11: =COUNTIF(S11:Z11, "si") -> 8 | AF11: =IF(AE11=8,"Estable",(IF(AE11=7,"Funcional con observaciones", (IF(AE11=6,"Funcional con observaciones",(IF(AE11=5,"Rendimiento bajo",(IF(AE11=4,"Parcialmente funcional",(IF(AE11=3,"Parcialmente funcional",(IF(AE11=2,"Inoperativo",(IF(AE11=1,"Inoperativo","Crítico"))))))))))))))) -> Estable
A12: 11 | B12: Fibra Óptica | C12: ESPACIO DEPORTIVO | D12: N/A | E12: PARQUE IV CENTENARIO | F12: MONTE DE LAS CRUCES HIDALGO | G12: COLONIA HIDALGO | H12: LEÓN | I12: 21.143558 | J12: -101.66958 | K12: ok | L12: =HYPERLINK("https://www.google.com/maps?q=" & I12 & "," & J12, "Ver en Google Maps") -> Ver en Google Maps | M12: 1 | N12: 45955 | O12: =DAY('BD2'!$N12) -> 25 | P12: =MONTH('BD2'!$N12) -> 10 | Q12: =YEAR('BD2'!$N12) -> 2025 | R12: 2 | S12: si | T12: si | U12: si | V12: si | W12: si | X12: si | Y12: si | Z12: =IF('BD2'!$AA12 < 14, "no", "si") -> si | AA12: 37.8 | AB12: 54.4 | AC12: La conexión fue rápida y constante, la navegación fue fluida, no se observan anomalías, tiene buena señal | AD12: José Mosqueda | AE12: =COUNTIF(S12:Z12, "si") -> 8 | AF12: =IF(AE12=8,"Estable",(IF(AE12=7,"Funcional con observaciones", (IF(AE12=6,"Funcional con observaciones",(IF(AE12=5,"Rendimiento bajo",(IF(AE12=4,"Parcialmente funcional",(IF(AE12=3,"Parcialmente funcional",(IF(AE12=2,"Inoperativo",(IF(AE12=1,"Inoperativo","Crítico"))))))))))))))) -> Estable
A13: 12 | B13: Fibra Óptica | C13: ESPACIO DEPORTIVO | D13: N/A | E13: PARQUE EXTREMO LAS HILAMAS | F13: MARIANO ESCOBEDO LOMAS DE LAS HILAMAS | G13: COLONIA LOMAS DE LAS HILAMAS | H13: LEÓN | I13: 21.110986 | J13: -101.72374 | K13: ok | L13: =HYPERLINK("https://www.google.com/maps?q=" & I13 & "," & J13, "Ver en Google Maps") -> Ver en Google Maps | M13: 2 | N13: 45964 | O13: =DAY('BD2'!$N13) -> 3 | P13: =MONTH('BD2'!$N13) -> 11 | Q13: =YEAR('BD2'!$N13) -> 2025 | R13: 2 | S13: si | T13: si | U13: si | V13: si | W13: si | X13: si | Y13: si | Z13: =IF('BD2'!$AA13 < 14, "no", "si") -> si | AA13: 120 | AB13: 39.9 | AC13: La conexión fue rápida y constante, la navegación fue fluida, no se observan anomalías, tiene buena señal | AD13: José Mosqueda | AE13: =COUNTIF(S13:Z13, "si") -> 8 | AF13: =IF(AE13=8,"Estable",(IF(AE13=7,"Funcional con observaciones", (IF(AE13=6,"Funcional con observaciones",(IF(AE13=5,"Rendimiento bajo",(IF(AE13=4,"Parcialmente funcional",(IF(AE13=3,"Parcialmente funcional",(IF(AE13=2,"Inoperativo",(IF(AE13=1,"Inoperativo","Crítico"))))))))))))))) -> Estable
A14: 13a | B14: Fibra Óptica | C14: ESPACIO DEPORTIVO | D14: N/A | E14: PARQUE DEL ARBOL | F14: TORRES LANDA, JUAN JOSE SAN NICOLAS | G14: COLONIA SAN NICOLAS | H14: LEÓN | I14: 21.102383 | J14: -101.67667 | K14: ok | L14: =HYPERLINK("https://www.google.com/maps?q=" & I14 & "," & J14, "Ver en Google Maps") -> Ver en Google Maps | M14: 3 | N14: 45964 | O14: =DAY('BD2'!$N14) -> 3 | P14: =MONTH('BD2'!$N14) -> 11 | Q14: =YEAR('BD2'!$N14) -> 2025 | R14: 2 | S14: si | T14: si | U14: si | V14: si | W14: si | X14: si | Y14: si | Z14: =IF('BD2'!$AA14 < 14, "no", "si") -> si | AA14: 74.5 | AB14: 39.1 | AC14: La conexión fue rápida y constante, la navegación fue fluida, no se observan anomalías, tiene buena señal | AD14: José Mosqueda | AE14: =COUNTIF(S14:Z14, "si") -> 8 | AF14: =IF(AE14=8,"Estable",(IF(AE14=7,"Funcional con observaciones", (IF(AE14=6,"Funcional con observaciones",(IF(AE14=5,"Rendimiento bajo",(IF(AE14=4,"Parcialmente funcional",(IF(AE14=3,"Parcialmente funcional",(IF(AE14=2,"Inoperativo",(IF(AE14=1,"Inoperativo","Crítico"))))))))))))))) -> Estable
A15: 13b | B15: Fibra Óptica | C15: ESPACIO DEPORTIVO | D15: N/A | E15: PARQUE DEL ARBOL | F15: TORRES LANDA, JUAN JOSE SAN NICOLAS | G15: COLONIA SAN NICOLAS | H15: LEÓN | I15: 21.103049 | J15: -101.67521 | K15: ok | L15: =HYPERLINK("https://www.google.com/maps?q=" & I15 & "," & J15, "Ver en Google Maps") -> Ver en Google Maps | M15: 3 | N15: 45964 | O15: =DAY('BD2'!$N15) -> 3 | P15: =MONTH('BD2'!$N15) -> 11 | Q15: =YEAR('BD2'!$N15) -> 2025 | R15: 2 | S15: si | T15: si | U15: si | V15: si | W15: si | X15: si | Y15: si | Z15: =IF('BD2'!$AA15 < 14, "no", "si") -> si | AA15: 40.8 | AB15: 35.3 | AC15: La conexión fue rápida y constante, la navegación fue fluida, no se observan anomalías, tiene buena señal | AD15: José Mosqueda | AE15: =COUNTIF(S15:Z15, "si") -> 8 | AF15: =IF(AE15=8,"Estable",(IF(AE15=7,"Funcional con observaciones", (IF(AE15=6,"Funcional con observaciones",(IF(AE15=5,"Rendimiento bajo",(IF(AE15=4,"Parcialmente funcional",(IF(AE15=3,"Parcialmente funcional",(IF(AE15=2,"Inoperativo",(IF(AE15=1,"Inoperativo","Crítico"))))))))))))))) -> Estable
A16: 14 | B16: Fibra Óptica | C16: ESPACIO DEPORTIVO | D16: N/A | E16: MINIDEPORTIVA LOMA DORADA | F16: BLVD. MINERAL DE LA JOYA TORRES DORADAS | G16: COLONIA LOMA DORADA | H16: LEÓN | I16: 21.137276 | J16: -101.76616 | K16: ok | L16: =HYPERLINK("https://www.google.com/maps?q=" & I16 & "," & J16, "Ver en Google Maps") -> Ver en Google Maps | M16: 1 | N16: 45960 | O16: =DAY('BD2'!$N16) -> 30 | P16: =MONTH('BD2'!$N16) -> 10 | Q16: =YEAR('BD2'!$N16) -> 2025 | R16: 2 | S16: si | T16: si | U16: si | V16: si | W16: si | X16: si | Y16: si | Z16: =IF('BD2'!$AA16 < 14, "no", "si") -> si | AA16: 108 | AB16: 34.1 | AC16: La conexión fue rápida y constante, la navegación fue fluida, no se observan anomalías, tiene buena señal | AD16: José Mosqueda | AE16: =COUNTIF(S16:Z16, "si") -> 8 | AF16: =IF(AE16=8,"Estable",(IF(AE16=7,"Funcional con observaciones", (IF(AE16=6,"Funcional con observaciones",(IF(AE16=5,"Rendimiento bajo",(IF(AE16=4,"Parcialmente funcional",(IF(AE16=3,"Parcialmente funcional",(IF(AE16=2,"Inoperativo",(IF(AE16=1,"Inoperativo","Crítico"))))))))))))))) -> Estable
A17: 15 | B17: Fibra Óptica | C17: ESPACIO DEPORTIVO | D17: N/A | E17: VALLE DE SEÑORA I | F17: AVOGADRO VALLE DE SEÑORA | G17: COLONIA VALLE DE SEÑORA | H17: LEÓN | I17: 21.15992 | J17: -101.65658 | K17: ok | L17: =HYPERLINK("https://www.google.com/maps?q=" & I17 & "," & J17, "Ver en Google Maps") -> Ver en Google Maps | M17: 1 | N17: 45955 | O17: =DAY('BD2'!$N17) -> 25 | P17: =MONTH('BD2'!$N17) -> 10 | Q17: =YEAR('BD2'!$N17) -> 2025 | R17: 2 | S17: si | T17: si | U17: si | V17: si | W17: si | X17: si | Y17: si | Z17: =IF('BD2'!$AA17 < 14, "no", "si") -> si | AA17: 111 | AB17: 44.2 | AC17: La conexión fue rápida y constante, la navegación fue fluida, no se observan anomalías, tiene buena señal | AD17: José Mosqueda | AE17: =COUNTIF(S17:Z17, "si") -> 8 | AF17: =IF(AE17=8,"Estable",(IF(AE17=7,"Funcional con observaciones", (IF(AE17=6,"Funcional con observaciones",(IF(AE17=5,"Rendimiento bajo",(IF(AE17=4,"Parcialmente funcional",(IF(AE17=3,"Parcialmente funcional",(IF(AE17=2,"Inoperativo",(IF(AE17=1,"Inoperativo","Crítico"))))))))))))))) -> Estable
A18: 16 | B18: Fibra Óptica | C18: PRESIDENCIA | D18: N/A | E18: PRESIDENCIA MUNICIPAL DE LEÓN DE LOS ALDAMA | F18: PLAZA PRINCIPAL | G18: COLONIA CENTRO | H18: LEÓN | I18: 21.12176 | J18: -101.68234 | K18: ok | L18: =HYPERLINK("https://www.google.com/maps?q=" & I18 & "," & J18, "Ver en Google Maps") -> Ver en Google Maps | M18: 3 | N18: 45954 | O18: =DAY('BD2'!$N18) -> 24 | P18: =MONTH('BD2'!$N18) -> 10 | Q18: =YEAR('BD2'!$N18) -> 2025 | R18: 2 | S18: si | T18: si | U18: si | V18: si | W18: si | X18: si | Y18: si | Z18: =IF('BD2'!$AA18 < 14, "no", "si") -> si | AA18: 16.3 | AB18: 3.73 | AC18: La conexión fue rápida y constante, la navegación fue fluida, no se observan anomalías, tiene buena señal | AD18: José Mosqueda | AE18: =COUNTIF(S18:Z18, "si") -> 8 | AF18: =IF(AE18=8,"Estable",(IF(AE18=7,"Funcional con observaciones", (IF(AE18=6,"Funcional con observaciones",(IF(AE18=5,"Rendimiento bajo",(IF(AE18=4,"Parcialmente funcional",(IF(AE18=3,"Parcialmente funcional",(IF(AE18=2,"Inoperativo",(IF(AE18=1,"Inoperativo","Crítico"))))))))))))))) -> Estable
A19: 88 | B19: Fibra Óptica | C19: CENTRO DE INVESTIGACIÓN | D19: N/A | E19: HUB-I CASA DEL EMPRENDEDOR LEÓN | F19: CALLE JULIÁN DE OBREGÓN 245, OBREGÓN, 37320 LEÓN DE LOS ALDAMA, GTO. | G19: COLONIA LA MARTINICA | H19: LEÓN | I19: 21.129923 | J19: -101.68584 | L19: =HYPERLINK("https://www.google.com/maps?q=" & I19 & "," & J19, "Ver en Google Maps") -> Ver en Google Maps | M19: 2
A20: 89 | B20: Fibra Óptica | C20: ESCUELA | D20: SECUNDARIA | E20: 11EPR0645S -SECUNDARIA ANEXA NORMAL OFICIAL | F20: MERCURIO S/N, EL LUCERO, 37249, LEON DE LOS ALDAMA | G20: COLONIA EL LUCERO | H20: LEÓN | I20: 21.13566 | J20: -101.66829 | K20: ok | L20: =HYPERLINK("https://www.google.com/maps?q=" & I20 & "," & J20, "Ver en Google Maps") -> Ver en Google Maps | M20: 1 | N20: 45954 | O20: =DAY('BD2'!$N20) -> 24 | P20: =MONTH('BD2'!$N20) -> 10 | Q20: =YEAR('BD2'!$N20) -> 2025 | R20: 2 | S20: si | T20: si | U20: si | V20: si | W20: si | X20: si | Y20: si | Z20: =IF('BD2'!$AA20 < 14, "no", "si") -> si | AA20: 43 | AB20: 16.4 | AC20: La conexión fue rápida y constante, la navegación fue fluida, no se observan anomalías, tiene buena señal | AD20: José Mosqueda | AE20: =COUNTIF(S20:Z20, "si") -> 8 | AF20: =IF(AE20=8,"Estable",(IF(AE20=7,"Funcional con observaciones", (IF(AE20=6,"Funcional con observaciones",(IF(AE20=5,"Rendimiento bajo",(IF(AE20=4,"Parcialmente funcional",(IF(AE20=3,"Parcialmente funcional",(IF(AE20=2,"Inoperativo",(IF(AE20=1,"Inoperativo","Crítico"))))))))))))))) -> Estable
A21: 92 | B21: Fibra Óptica | C21: ESCUELA | D21: PREESCOLAR | E21: 11DJN4405E - OVIDIO DECROLY | F21: CALLE CHIMALPOPOCA NUMERO EXTERIOR: 102 , COLONIA AZTECAS, CODIGO | G21: COLONIA AZTECAS | H21: LEÓN | I21: 21.10199 | J21: -101.65482 | K21: ok | L21: =HYPERLINK("https://www.google.com/maps?q=" & I21 & "," & J21, "Ver en Google Maps") -> Ver en Google Maps | M21: 1 | N21: 45960 | O21: =DAY('BD2'!$N21) -> 30 | P21: =MONTH('BD2'!$N21) -> 10 | Q21: =YEAR('BD2'!$N21) -> 2025 | R21: 2 | S21: si | T21: si | U21: si | V21: si | W21: si | X21: si | Y21: si | Z21: =IF('BD2'!$AA21 < 14, "no", "si") -> si | AA21: 59.7 | AB21: 8.25 | AC21: La conexión fue rápida y constante, la navegación fue fluida, no se observan anomalías, tiene buena señal | AD21: José Mosqueda | AE21: =COUNTIF(S21:Z21, "si") -> 8 | AF21: =IF(AE21=8,"Estable",(IF(AE21=7,"Funcional con observaciones", (IF(AE21=6,"Funcional con observaciones",(IF(AE21=5,"Rendimiento bajo",(IF(AE21=4,"Parcialmente funcional",(IF(AE21=3,"Parcialmente funcional",(IF(AE21=2,"Inoperativo",(IF(AE21=1,"Inoperativo","Crítico"))))))))))))))) -> Estable
A22: 96 | B22: Fibra Óptica | C22: ESCUELA | D22: SECUNDARIA | E22: 11DES0015Y - SECUNDARIA GENERAL DIEGO RIVERA | F22: AVENIDA PANORAMA Y VALLE DE OLIVO S/N | G22: COLONIA PANORAMA | H22: LEÓN | I22: 21.15465 | J22: -101.69157 | K22: ok | L22: =HYPERLINK("https://www.google.com/maps?q=" & I22 & "," & J22, "Ver en Google Maps") -> Ver en Google Maps | M22: 2 | N22: 45952 | O22: =DAY('BD2'!$N22) -> 22 | P22: =MONTH('BD2'!$N22) -> 10 | Q22: =YEAR('BD2'!$N22) -> 2025 | R22: 2 | S22: si | T22: si | U22: si | V22: si | W22: si | X22: si | Y22: si | Z22: =IF('BD2'!$AA22 < 14, "no", "si") -> si | AA22: 113 | AB22: 51.1 | AC22: La conexión fue rápida y constante, la navegación fue fluida, no se observan anomalías, tiene buena señal | AD22: José Mosqueda | AE22: =COUNTIF(S22:Z22, "si") -> 8 | AF22: =IF(AE22=8,"Estable",(IF(AE22=7,"Funcional con observaciones", (IF(AE22=6,"Funcional con observaciones",(IF(AE22=5,"Rendimiento bajo",(IF(AE22=4,"Parcialmente funcional",(IF(AE22=3,"Parcialmente funcional",(IF(AE22=2,"Inoperativo",(IF(AE22=1,"Inoperativo","Crítico"))))))))))))))) -> Estable
A23: 101 | B23: Fibra Óptica | C23: ESCUELA | D23: PREESCOLAR | E23: 11DJN0269Q - DR. D. FRANCISCO LEAL | F23: CALLE ALICIA NUMERO EXTERIOR: 305 , COLONIA ORIENTAL, CODIGO POST | G23: COLONIA ORIENTAL | H23: LEÓN | I23: 21.106586 | J23: -101.65309 | K23: ok | L23: =HYPERLINK("https://www.google.com/maps?q=" & I23 & "," & J23, "Ver en Google Maps") -> Ver en Google Maps | M23: 1 | N23: 45960 | O23: =DAY('BD2'!$N23) -> 30 | P23: =MONTH('BD2'!$N23) -> 10 | Q23: =YEAR('BD2'!$N23) -> 2025 | R23: 2 | S23: si | T23: si | U23: si | V23: si | W23: si | X23: si | Y23: si | Z23: =IF('BD2'!$AA23 < 14, "no", "si") -> si | AA23: 33.5 | AB23: 5.55 | AC23: La conexión fue rápida pero presentó pequeños cortes | AD23: José Mosqueda | AE23: =COUNTIF(S23:Z23, "si") -> 8 | AF23: =IF(AE23=8,"Estable",(IF(AE23=7,"Funcional con observaciones", (IF(AE23=6,"Funcional con observaciones",(IF(AE23=5,"Rendimiento bajo",(IF(AE23=4,"Parcialmente funcional",(IF(AE23=3,"Parcialmente funcional",(IF(AE23=2,"Inoperativo",(IF(AE23=1,"Inoperativo","Crítico"))))))))))))))) -> Estable
A24: 102 | B24: Fibra Óptica | C24: ESCUELA | D24: SECUNDARIA | E24: 11DES0028B - SECUNDARIA GENERAL HERMANOS FLORES MAGON | F24: CARRETERA LEON, SAN FRANCISCOSN KILOMETRO 1.5 | G24: COLONIA PORTALES DE SAN SEBASTIAN | H24: LEÓN | I24: 21.10182 | J24: -101.70554 | K24: ok | L24: =HYPERLINK("https://www.google.com/maps?q=" & I24 & "," & J24, "Ver en Google Maps") -> Ver en Google Maps | M24: 2 | N24: 45964 | O24: =DAY('BD2'!$N24) -> 3 | P24: =MONTH('BD2'!$N24) -> 11 | Q24: =YEAR('BD2'!$N24) -> 2025 | R24: 2 | S24: si | T24: si | U24: si | V24: si | W24: si | X24: si | Y24: si | Z24: =IF('BD2'!$AA24 < 14, "no", "si") -> no | AA24: 3.19 | AB24: 3.42 | AC24: La conexión fue rápida y constante, la navegación fue fluida, no se observan anomalías, tiene buena señal, pero el ancho de banda es muy bajo | AD24: Rafael Amaral | AE24: =COUNTIF(S24:Z24, "si") -> 7 | AF24: =IF(AE24=8,"Estable",(IF(AE24=7,"Funcional con observaciones", (IF(AE24=6,"Funcional con observaciones",(IF(AE24=5,"Rendimiento bajo",(IF(AE24=4,"Parcialmente funcional",(IF(AE24=3,"Parcialmente funcional",(IF(AE24=2,"Inoperativo",(IF(AE24=1,"Inoperativo","Crítico"))))))))))))))) -> Funcional con observaciones
A25: 106 | B25: Fibra Óptica | C25: ESCUELA | D25: SECUNDARIA | E25: 11DES0061J - SECUNDARIA GENERAL EMPERADOR CUAUHTEMOC | F25: BOULEVARD MANUEL DE AUSTRI Y CAMPECHE S/N | G25: COLONIA CHAPALITA | H25: LEÓN | I25: 21.12576 | J25: -101.70523 | L25: =HYPERLINK("https://www.google.com/maps?q=" & I25 & "," & J25, "Ver en Google Maps") -> Ver en Google Maps | M25: 2
A26: 107 | B26: Fibra Óptica | C26: ESCUELA | D26: SECUNDARIA | E26: 11DES0072P - SECUNDARIA GENERAL N° 7 "MARGARITA PAZ PAREDES" | F26: SEVILLA NUM. 2201 SEGUNDA SECCION PILETAS | G26: COLONIA PILETAS SEGUNDA SECCION | H26: LEÓN | I26: 21.1406 | J26: -101.70609 | K26: ok | L26: =HYPERLINK("https://www.google.com/maps?q=" & I26 & "," & J26, "Ver en Google Maps") -> Ver en Google Maps | M26: 2 | N26: 45958 | O26: =DAY('BD2'!$N26) -> 28 | P26: =MONTH('BD2'!$N26) -> 10 | Q26: =YEAR('BD2'!$N26) -> 2025 | R26: 2 | S26: si | T26: si | U26: si | V26: si | W26: si | X26: si | Y26: si | Z26: =IF('BD2'!$AA26 < 14, "no", "si") -> si | AA26: 14.7 | AB26: 8.69 | AC26: La conexión fue rápida y constante, la navegación fue fluida, no se observan anomalías, tiene buena señal | AD26: Rafael Amaral | AE26: =COUNTIF(S26:Z26, "si") -> 8 | AF26: =IF(AE26=8,"Estable",(IF(AE26=7,"Funcional con observaciones", (IF(AE26=6,"Funcional con observaciones",(IF(AE26=5,"Rendimiento bajo",(IF(AE26=4,"Parcialmente funcional",(IF(AE26=3,"Parcialmente funcional",(IF(AE26=2,"Inoperativo",(IF(AE26=1,"Inoperativo","Crítico"))))))))))))))) -> Estable
A27: 108 | B27: Fibra Óptica | C27: ESCUELA | D27: SECUNDARIA | E27: 11DES0080Y - FRANCISCO RAMIREZ MATA | F27: BOULEVARD SAN PEDRO NUM. SN Y LAUREL | G27: COLONIA JARDIN DE JEREZ SEGUNDA SECCION | H27: LEÓN | I27: 21.09137 | J27: -101.64844 | L27: =HYPERLINK("https://www.google.com/maps?q=" & I27 & "," & J27, "Ver en Google Maps") -> Ver en Google Maps | M27: 2
A28: 109 | B28: Fibra Óptica | C28: ESCUELA | D28: SECUNDARIA | E28: 11DES0084U - SECUNDARIA GENERAL HILARIO MEDINA | F28: BOULEVARD FRANCISCO VILLA Y EGIPTO S/N | G28: COLONIA LOS ANGELES | H28: LEÓN | I28: 21.13391 | J28: -101.64409 | K28: ok | L28: =HYPERLINK("https://www.google.com/maps?q=" & I28 & "," & J28, "Ver en Google Maps") -> Ver en Google Maps | M28: 2 | N28: 45955 | O28: =DAY('BD2'!$N28) -> 25 | P28: =MONTH('BD2'!$N28) -> 10 | Q28: =YEAR('BD2'!$N28) -> 2025 | R28: 2 | S28: si | T28: si | U28: si | V28: si | W28: si | X28: si | Y28: si | Z28: =IF('BD2'!$AA28 < 14, "no", "si") -> si | AA28: 14 | AB28: 36.2 | AC28: La conexión fue rápida y constante, la navegación fue fluida, tiene buena señal | AD28: José Mosqueda | AE28: =COUNTIF(S28:Z28, "si") -> 8 | AF28: =IF(AE28=8,"Estable",(IF(AE28=7,"Funcional con observaciones", (IF(AE28=6,"Funcional con observaciones",(IF(AE28=5,"Rendimiento bajo",(IF(AE28=4,"Parcialmente funcional",(IF(AE28=3,"Parcialmente funcional",(IF(AE28=2,"Inoperativo",(IF(AE28=1,"Inoperativo","Crítico"))))))))))))))) -> Estable
A29: 112 | B29: Fibra Óptica | C29: ESCUELA | D29: SECUNDARIA | E29: 11DES0090E - ESCUELA SECUNDARIA N° 11"JUAN J.VARELA MAYORGA" | F29: SOFIA ALVAREZ NUM. 1503 | G29: COLONIA LOMAS DE LOS OLIVOS | H29: LEÓN | I29: 21.11342 | J29: -101.70892 | K29: ok | L29: =HYPERLINK("https://www.google.com/maps?q=" & I29 & "," & J29, "Ver en Google Maps") -> Ver en Google Maps | M29: 2 | N29: 45965 | O29: =DAY('BD2'!$N29) -> 4 | P29: =MONTH('BD2'!$N29) -> 11 | Q29: =YEAR('BD2'!$N29) -> 2025 | R29: 2 | S29: si | T29: si | U29: si | V29: si | W29: si | X29: si | Y29: si | Z29: =IF('BD2'!$AA29 < 14, "no", "si") -> si | AA29: 38.9 | AB29: 21 | AC29: La conexión fue rápida y constante, la navegación fue fluida, no se observan anomalías, tiene buena señal | AD29: Rafael Amaral | AE29: =COUNTIF(S29:Z29, "si") -> 8 | AF29: =IF(AE29=8,"Estable",(IF(AE29=7,"Funcional con observaciones", (IF(AE29=6,"Funcional con observaciones",(IF(AE29=5,"Rendimiento bajo",(IF(AE29=4,"Parcialmente funcional",(IF(AE29=3,"Parcialmente funcional",(IF(AE29=2,"Inoperativo",(IF(AE29=1,"Inoperativo","Crítico"))))))))))))))) -> Estable
A30: 114 | B30: Fibra Óptica | C30: ESCUELA | D30: SECUNDARIA | E30: 11DES0097Y - PEDRO MORENO | F30: JOSEFINA CAMARENA NUM. 901 | G30: COLONIA LEON II | H30: LEÓN | I30: 21.10845 | J30: -101.7283 | K30: ok | L30: =HYPERLINK("https://www.google.com/maps?q=" & I30 & "," & J30, "Ver en Google Maps") -> Ver en Google Maps | M30: 2 | N30: 45964 | O30: =DAY('BD2'!$N30) -> 3 | P30: =MONTH('BD2'!$N30) -> 11 | Q30: =YEAR('BD2'!$N30) -> 2025 | R30: 2 | S30: no | T30: no | U30: no | V30: no | W30: no | X30: no | Y30: no | Z30: =IF('BD2'!$AA30 < 14, "no", "si") -> no | AA30: 0 | AB30: 0 | AC30: No se pudo realizar el análisis el Acces Point se encuentra muy lejos y no se nos permitió el acceso al plantel | AD30: José Mosqueda | AE30: =COUNTIF(S30:Z30, "si") -> 0 | AF30: =IF(AE30=8,"Estable",(IF(AE30=7,"Funcional con observaciones", (IF(AE30=6,"Funcional con observaciones",(IF(AE30=5,"Rendimiento bajo",(IF(AE30=4,"Parcialmente funcional",(IF(AE30=3,"Parcialmente funcional",(IF(AE30=2,"Inoperativo",(IF(AE30=1,"Inoperativo","Crítico"))))))))))))))) -> Crítico
A31: 115 | B31: Fibra Óptica | C31: ESCUELA | D31: SECUNDARIA | E31: 11DES0099W - FRANCISCO PICHARDO | F31: CERRO DE LA BUFA ESQUINA VILLA DE REYES NUM. SN | G31: COLONIA LOMAS DE JEREZ | H31: LEÓN | I31: 21.08157 | J31: -101.63813 | L31: =HYPERLINK("https://www.google.com/maps?q=" & I31 & "," & J31, "Ver en Google Maps") -> Ver en Google Maps | M31: 2
A32: 116 | B32: Fibra Óptica | C32: ESCUELA | D32: SECUNDARIA | E32: 11DES0102T - SECUNDARIA GENERAL SOR JUANA INES DE LA CRUZ | F32: BOULEVARD EPSILON NUM. 1105 | G32: COLONIA VALLE VERDE | H32: LEÓN | I32: 21.08009 | J32: -101.62151 | L32: =HYPERLINK("https://www.google.com/maps?q=" & I32 & "," & J32, "Ver en Google Maps") -> Ver en Google Maps | M32: 2
A33: 117 | B33: Fibra Óptica | C33: ESCUELA | D33: SECUNDARIA | E33: 11DES0103S - GUADALUPE PEDROZA PIÑA | F33: CALLE AURORA DE SAN JUAN NUMERO EXTERIOR: SN, FRACCIONAMIENTO VIL | G33: COLONIA VILLAS DE SAN JUAN | H33: LEÓN | I33: 21.09255 | J33: -101.59189 | L33: =HYPERLINK("https://www.google.com/maps?q=" & I33 & "," & J33, "Ver en Google Maps") -> Ver en Google Maps | M33: 2
A34: 120 | B34: Fibra Óptica | C34: ESCUELA | D34: PREESCOLAR | E34: 11DJN0030G - MANUEL LOPEZ COTILLA | F34: BURGOS Y GALICIA S/N Y GALICIA S/N | G34: COLONIA ESPAÑA | H34: LEÓN | I34: 21.13291 | J34: -101.70179 | L34: =HYPERLINK("https://www.google.com/maps?q=" & I34 & "," & J34, "Ver en Google Maps") -> Ver en Google Maps | M34: 1
A35: 123 | B35: Fibra Óptica | C35: ESCUELA | D35: PREESCOLAR | E35: 11DJN0046H - OSCAR GONZALEZ BLACKALLER | F35: INMACULADA NUM. 108 | G35: COLONIA ESPAÑITA | H35: LEÓN | I35: 21.12063 | J35: -101.65833 | K35: ok | L35: =HYPERLINK("https://www.google.com/maps?q=" & I35 & "," & J35, "Ver en Google Maps") -> Ver en Google Maps | M35: 1 | N35: 45955 | O35: =DAY('BD2'!$N35) -> 25 | P35: =MONTH('BD2'!$N35) -> 10 | Q35: =YEAR('BD2'!$N35) -> 2025 | R35: 2 | S35: si | T35: si | U35: si | V35: si | W35: si | X35: si | Y35: si | Z35: =IF('BD2'!$AA35 < 14, "no", "si") -> si | AA35: 91.6 | AB35: 52 | AC35: La conexión fue rápida y constante, la navegación fue fluida, no se observan anomalías, tiene buena señal | AD35: Rafael Amaral | AE35: =COUNTIF(S35:Z35, "si") -> 8 | AF35: =IF(AE35=8,"Estable",(IF(AE35=7,"Funcional con observaciones", (IF(AE35=6,"Funcional con observaciones",(IF(AE35=5,"Rendimiento bajo",(IF(AE35=4,"Parcialmente funcional",(IF(AE35=3,"Parcialmente funcional",(IF(AE35=2,"Inoperativo",(IF(AE35=1,"Inoperativo","Crítico"))))))))))))))) -> Estable
A36: 128 | B36: Fibra Óptica | C36: ESCUELA | D36: PREESCOLAR | E36: 11DJN0060A - ZORAIDA PINEDA | F36: CALLE MANANTIAL NUMERO EXTERIOR: 203 , COLONIA FUTURAMA MONTERREY | G36: COLONIA FUTURAMA MONTERREY | H36: LEÓN | I36: 21.14996 | J36: -101.68824 | K36: ok | L36: =HYPERLINK("https://www.google.com/maps?q=" & I36 & "," & J36, "Ver en Google Maps") -> Ver en Google Maps | M36: 1 | N36: 45958 | O36: =DAY('BD2'!$N36) -> 28 | P36: =MONTH('BD2'!$N36) -> 10 | Q36: =YEAR('BD2'!$N36) -> 2025 | R36: 2 | S36: si | T36: si | U36: si | V36: si | W36: si | X36: si | Y36: si | Z36: =IF('BD2'!$AA36 < 14, "no", "si") -> si | AA36: 74.7 | AB36: 43.4 | AC36: La conexión fue rápida y constante, la navegación fue fluida, no se observan anomalías, tiene buena señal | AD36: José Mosqueda | AE36: =COUNTIF(S36:Z36, "si") -> 8 | AF36: =IF(AE36=8,"Estable",(IF(AE36=7,"Funcional con observaciones", (IF(AE36=6,"Funcional con observaciones",(IF(AE36=5,"Rendimiento bajo",(IF(AE36=4,"Parcialmente funcional",(IF(AE36=3,"Parcialmente funcional",(IF(AE36=2,"Inoperativo",(IF(AE36=1,"Inoperativo","Crítico"))))))))))))))) -> Estable
A37: 131 | B37: Fibra Óptica | C37: ESCUELA | D37: PREESCOLAR | E37: 11DJN0078Z - MANUEL DOBLADO | F37: CUITLAHUAC Y CHIMALPOPOCA S/N ESQUINA CHIMALPOPOCA | G37: COLONIA AZTECA | H37: LEÓN | I37: 21.10105 | J37: -101.65532 | K37: ok | L37: =HYPERLINK("https://www.google.com/maps?q=" & I37 & "," & J37, "Ver en Google Maps") -> Ver en Google Maps | M37: 1 | N37: 45960 | O37: =DAY('BD2'!$N37) -> 30 | P37: =MONTH('BD2'!$N37) -> 10 | Q37: =YEAR('BD2'!$N37) -> 2025 | R37: 2 | S37: si | T37: si | U37: si | V37: si | W37: si | X37: si | Y37: si | Z37: =IF('BD2'!$AA37 < 14, "no", "si") -> si | AA37: 119 | AB37: 56.3 | AC37: La conexión fue rápida y constante, la navegación fue fluida, no se observan anomalías, tiene buena señal | AD37: José Mosqueda | AE37: =COUNTIF(S37:Z37, "si") -> 8 | AF37: =IF(AE37=8,"Estable",(IF(AE37=7,"Funcional con observaciones", (IF(AE37=6,"Funcional con observaciones",(IF(AE37=5,"Rendimiento bajo",(IF(AE37=4,"Parcialmente funcional",(IF(AE37=3,"Parcialmente funcional",(IF(AE37=2,"Inoperativo",(IF(AE37=1,"Inoperativo","Crítico"))))))))))))))) -> Estable
A38: 136 | B38: Fibra Óptica | C38: ESCUELA | D38: PREESCOLAR | E38: 11DJN0114O - NICOLAS RANGEL | F38: PROLONGACION LA MERCED NUM. 1239 | G38: COLONIA SAN SEBASTIAN | H38: LEÓN | I38: 21.10363 | J38: -101.7011 | K38: ok | L38: =HYPERLINK("https://www.google.com/maps?q=" & I38 & "," & J38, "Ver en Google Maps") -> Ver en Google Maps | M38: 1 | N38: 45964 | O38: =DAY('BD2'!$N38) -> 3 | P38: =MONTH('BD2'!$N38) -> 11 | Q38: =YEAR('BD2'!$N38) -> 2025 | R38: 2 | S38: si | T38: si | U38: si | V38: si | W38: si | X38: si | Y38: si | Z38: =IF('BD2'!$AA38 < 14, "no", "si") -> si | AA38: 110 | AB38: 111 | AC38: La conexión fue rápida y constante, la navegación fue fluida, no se observan anomalías, tiene buena señal | AD38: Rafael Amaral | AE38: =COUNTIF(S38:Z38, "si") -> 8 | AF38: =IF(AE38=8,"Estable",(IF(AE38=7,"Funcional con observaciones", (IF(AE38=6,"Funcional con observaciones",(IF(AE38=5,"Rendimiento bajo",(IF(AE38=4,"Parcialmente funcional",(IF(AE38=3,"Parcialmente funcional",(IF(AE38=2,"Inoperativo",(IF(AE38=1,"Inoperativo","Crítico"))))))))))))))) -> Estable
A39: 141 | B39: Fibra Óptica | C39: ESCUELA | D39: PREESCOLAR | E39: 11DJN0329O - JOSEFA ORTIZ DE DOMINGUEZ | F39: BOULEVARD MARIANO ESCOBEDO S/N A UN COSTADO DE LA PRIMARIA EMILIA | G39: COLONIA KENNEDY | H39: LEÓN | I39: 21.11673 | J39: -101.70174 | K39: ok | L39: =HYPERLINK("https://www.google.com/maps?q=" & I39 & "," & J39, "Ver en Google Maps") -> Ver en Google Maps | M39: 1 | N39: 45965 | O39: =DAY('BD2'!$N39) -> 4 | P39: =MONTH('BD2'!$N39) -> 11 | Q39: =YEAR('BD2'!$N39) -> 2025 | R39: 2 | S39: si | T39: si | U39: si | V39: si | W39: si | X39: si | Y39: si | Z39: =IF('BD2'!$AA39 < 14, "no", "si") -> si | AA39: 91.2 | AB39: 49.3 | AC39: La conexión fue rápida y constante, la navegación fue fluida, no se observan anomalías, tiene buena señal | AD39: Rafael Amaral | AE39: =COUNTIF(S39:Z39, "si") -> 8 | AF39: =IF(AE39=8,"Estable",(IF(AE39=7,"Funcional con observaciones", (IF(AE39=6,"Funcional con observaciones",(IF(AE39=5,"Rendimiento bajo",(IF(AE39=4,"Parcialmente funcional",(IF(AE39=3,"Parcialmente funcional",(IF(AE39=2,"Inoperativo",(IF(AE39=1,"Inoperativo","Crítico"))))))))))))))) -> Estable
A40: 142 | B40: Fibra Óptica | C40: ESCUELA | D40: PREESCOLAR | E40: 11DJN0197N - ALVARO OBREGON | F40: DIEGO DE VELAZQUEZ NUM. 703 | G40: COLONIA JARDINES DEL ORIRNTE | H40: LEÓN | I40: 21.12765 | J40: -101.64816 | K40: ok | L40: =HYPERLINK("https://www.google.com/maps?q=" & I40 & "," & J40, "Ver en Google Maps") -> Ver en Google Maps | M40: 1 | N40: 45957 | O40: =DAY('BD2'!$N40) -> 27 | P40: =MONTH('BD2'!$N40) -> 10 | Q40: =YEAR('BD2'!$N40) -> 2025 | R40: 2 | S40: si | T40: si | U40: si | V40: si | W40: si | X40: si | Y40: si | Z40: =IF('BD2'!$AA40 < 14, "no", "si") -> si | AA40: 98.2 | AB40: 78.6 | AC40: La conexión fue rápida y constante, la navegación fue fluida, no se observan anomalías, tiene buena señal | AD40: José Mosqueda | AE40: =COUNTIF(S40:Z40, "si") -> 8 | AF40: =IF(AE40=8,"Estable",(IF(AE40=7,"Funcional con observaciones", (IF(AE40=6,"Funcional con observaciones",(IF(AE40=5,"Rendimiento bajo",(IF(AE40=4,"Parcialmente funcional",(IF(AE40=3,"Parcialmente funcional",(IF(AE40=2,"Inoperativo",(IF(AE40=1,"Inoperativo","Crítico"))))))))))))))) -> Estable
A41: 144 | B41: Fibra Óptica | C41: ESCUELA | D41: PREESCOLAR | E41: 11DJN0212P - CARMEN RAMOS DEL RIO | F41: CALLE TRES NUM. 56 BOULEVARD MIGUEL DE CERVANTES SAAVEDRA | G41: COLONIA CHULAVISTA | H41: LEÓN | I41: 21.12003 | J41: -101.70858 | K41: ok | L41: =HYPERLINK("https://www.google.com/maps?q=" & I41 & "," & J41, "Ver en Google Maps") -> Ver en Google Maps | M41: 1 | N41: 45964 | O41: =DAY('BD2'!$N41) -> 3 | P41: =MONTH('BD2'!$N41) -> 11 | Q41: =YEAR('BD2'!$N41) -> 2025 | R41: 2 | S41: si | T41: si | U41: si | V41: si | W41: si | X41: si | Y41: si | Z41: =IF('BD2'!$AA41 < 14, "no", "si") -> si | AA41: 73.1 | AB41: 26.5 | AC41: La conexión fue rápida y constante, la navegación fue fluida, no se observan anomalías, tiene buena señal | AD41: José Mosqueda | AE41: =COUNTIF(S41:Z41, "si") -> 8 | AF41: =IF(AE41=8,"Estable",(IF(AE41=7,"Funcional con observaciones", (IF(AE41=6,"Funcional con observaciones",(IF(AE41=5,"Rendimiento bajo",(IF(AE41=4,"Parcialmente funcional",(IF(AE41=3,"Parcialmente funcional",(IF(AE41=2,"Inoperativo",(IF(AE41=1,"Inoperativo","Crítico"))))))))))))))) -> Estable
A42: 146 | B42: Fibra Óptica | C42: ESCUELA | D42: PREESCOLAR | E42: 11DJN0216L - DANIEL DELGADILLO | F42: MURCIA BARCELONA S/N | G42: COLONIA VISTA HERMOSA SUR | H42: LEÓN | I42: 21.13731 | J42: -101.71594 | L42: =HYPERLINK("https://www.google.com/maps?q=" & I42 & "," & J42, "Ver en Google Maps") -> Ver en Google Maps | M42: 1
A43: 147 | B43: Fibra Óptica | C43: ESCUELA | D43: PREESCOLAR | E43: 11DJN0226S - PROFRA. SILVINA LARA PARTIDA | F43: LOS ANGELES NUM. 316 | G43: COLONIA LAS AMERICAS | H43: LEÓN | I43: 21.10872 | J43: -101.69521 | K43: ok | L43: =HYPERLINK("https://www.google.com/maps?q=" & I43 & "," & J43, "Ver en Google Maps") -> Ver en Google Maps | M43: 1 | N43: 45965 | O43: =DAY('BD2'!$N43) -> 4 | P43: =MONTH('BD2'!$N43) -> 11 | Q43: =YEAR('BD2'!$N43) -> 2025 | R43: 2 | S43: si | T43: si | U43: si | V43: si | W43: si | X43: si | Y43: si | Z43: =IF('BD2'!$AA43 < 14, "no", "si") -> si | AA43: 45.9 | AB43: 12.1 | AC43: La conexión fue rápida y constante, la navegación fue fluida, no se observan anomalías, tiene buena señal | AD43: Rafael Amaral | AE43: =COUNTIF(S43:Z43, "si") -> 8 | AF43: =IF(AE43=8,"Estable",(IF(AE43=7,"Funcional con observaciones", (IF(AE43=6,"Funcional con observaciones",(IF(AE43=5,"Rendimiento bajo",(IF(AE43=4,"Parcialmente funcional",(IF(AE43=3,"Parcialmente funcional",(IF(AE43=2,"Inoperativo",(IF(AE43=1,"Inoperativo","Crítico"))))))))))))))) -> Estable
A44: 148 | B44: Fibra Óptica | C44: ESCUELA | D44: PREESCOLAR | E44: 11DJN0227R - DR. JOSE DE JESUS GONZALEZ | F44: SEVILLA Y CATALUÑA S/N | G44: COLONIA SAN JUAN BOSCO | H44: LEÓN | I44: 21.13452 | J44: -101.70735 | K44: sin video | L44: =HYPERLINK("https://www.google.com/maps?q=" & I44 & "," & J44, "Ver en Google Maps") -> Ver en Google Maps | M44: 1 | O44: =DAY('BD2'!$N44) -> 0 | P44: =MONTH('BD2'!$N44) -> 1 | Q44: =YEAR('BD2'!$N44) -> 1900 | R44: 2 | Z44: =IF('BD2'!$AA44 < 14, "no", "si") -> no | AC44: La conexión fue rápida y constante, la navegación fue fluida, no se observan anomalías, tiene buena señal | AD44: José Mosqueda | AE44: =COUNTIF(S44:Z44, "si") -> 0 | AF44: =IF(AE44=8,"Estable",(IF(AE44=7,"Funcional con observaciones", (IF(AE44=6,"Funcional con observaciones",(IF(AE44=5,"Rendimiento bajo",(IF(AE44=4,"Parcialmente funcional",(IF(AE44=3,"Parcialmente funcional",(IF(AE44=2,"Inoperativo",(IF(AE44=1,"Inoperativo","Crítico"))))))))))))))) -> Crítico
A45: 149 | B45: Fibra Óptica | C45: ESCUELA | D45: PREESCOLAR | E45: 11DJN0230E - MANUEL G TINOCO | F45: SANTA RITA NUM. 103 | G45: COLONIA SANTA RITA DE LOS NARANJOS | H45: LEÓN | I45: 21.10609 | J45: -101.70782 | L45: =HYPERLINK("https://www.google.com/maps?q=" & I45 & "," & J45, "Ver en Google Maps") -> Ver en Google Maps | M45: 2
A46: 163 | B46: Fibra Óptica | C46: ESCUELA | D46: PREESCOLAR | E46: 11DJN0327Q - MARIANO SILVA Y ACEVES | F46: PLAZA PALMERIN S/N | G46: COLONIA ARBOLEDAS | H46: LEÓN | I46: 21.10259 | J46: -101.66411 | K46: ok | L46: =HYPERLINK("https://www.google.com/maps?q=" & I46 & "," & J46, "Ver en Google Maps") -> Ver en Google Maps | M46: 2 | N46: 45964 | O46: =DAY('BD2'!$N46) -> 3 | P46: =MONTH('BD2'!$N46) -> 11 | Q46: =YEAR('BD2'!$N46) -> 2025 | R46: 2 | S46: si | T46: si | U46: si | V46: si | W46: si | X46: si | Y46: si | Z46: =IF('BD2'!$AA46 < 14, "no", "si") -> si | AA46: 93.7 | AB46: 67 | AC46: La conexión fue rápida y constante, la navegación fue fluida, no se observan anomalías, tiene buena señal | AD46: José Mosqueda | AE46: =COUNTIF(S46:Z46, "si") -> 8 | AF46: =IF(AE46=8,"Estable",(IF(AE46=7,"Funcional con observaciones", (IF(AE46=6,"Funcional con observaciones",(IF(AE46=5,"Rendimiento bajo",(IF(AE46=4,"Parcialmente funcional",(IF(AE46=3,"Parcialmente funcional",(IF(AE46=2,"Inoperativo",(IF(AE46=1,"Inoperativo","Crítico"))))))))))))))) -> Estable
A47: 164 | B47: Fibra Óptica | C47: ESCUELA | D47: PREESCOLAR | E47: 11DJN0331C - PROFRA. ROSAURA ZAPATA CANO | F47: LAGUNA DEL CARMEN S/N | G47: COLONIA LOMAS DE LA TRINIDAD | H47: LEÓN | I47: 21.1393 | J47: -101.69745 | K47: ok | L47: =HYPERLINK("https://www.google.com/maps?q=" & I47 & "," & J47, "Ver en Google Maps") -> Ver en Google Maps | M47: 2 | N47: 45958 | O47: =DAY('BD2'!$N47) -> 28 | P47: =MONTH('BD2'!$N47) -> 10 | Q47: =YEAR('BD2'!$N47) -> 2025 | R47: 2 | S47: si | T47: si | U47: si | V47: si | W47: si | X47: si | Y47: si | Z47: =IF('BD2'!$AA47 < 14, "no", "si") -> si | AA47: 34.5 | AB47: 22.2 | AC47: La conexión fue rápida y constante, la navegación fue fluida, no se observan anomalías, tiene buena señal | AD47: José Mosqueda | AE47: =COUNTIF(S47:Z47, "si") -> 8 | AF47: =IF(AE47=8,"Estable",(IF(AE47=7,"Funcional con observaciones", (IF(AE47=6,"Funcional con observaciones",(IF(AE47=5,"Rendimiento bajo",(IF(AE47=4,"Parcialmente funcional",(IF(AE47=3,"Parcialmente funcional",(IF(AE47=2,"Inoperativo",(IF(AE47=1,"Inoperativo","Crítico"))))))))))))))) -> Estable
A48: 165 | B48: Fibra Óptica | C48: ESCUELA | D48: PREESCOLAR | E48: 11DJN0334Z - DIEGO RIVERA | F48: MANTO SAGRADO NUM. 111 | G48: COLONIA JESUS DE NAZARET | H48: LEÓN | I48: 21.07942 | J48: -101.65515 | L48: =HYPERLINK("https://www.google.com/maps?q=" & I48 & "," & J48, "Ver en Google Maps") -> Ver en Google Maps | M48: 1
A49: 187 | B49: Fibra Óptica | C49: ESCUELA | D49: PREESCOLAR | E49: 11DJN0652M - EMILIO PORTES GIL | F49: SAN JUSTO S/N | G49: COLONIA LA PISCINA | H49: LEÓN | I49: 21.09562 | J49: -101.71724 | L49: =HYPERLINK("https://www.google.com/maps?q=" & I49 & "," & J49, "Ver en Google Maps") -> Ver en Google Maps | M49: 1
A50: 190 | B50: Fibra Óptica | C50: ESCUELA | D50: PREESCOLAR | E50: 11DJN0730Z - SOR JUANA INES DE LA CRUZ | F50: PROLONGACION LA LUZ S/N VIA DEL TREN | G50: COLONIA PROLONGACIÓN JUÁREZ | H50: LEÓN | I50: 21.093884 | J50: -101.69566 | L50: =HYPERLINK("https://www.google.com/maps?q=" & I50 & "," & J50, "Ver en Google Maps") -> Ver en Google Maps | M50: 1
A51: 191 | B51: Fibra Óptica | C51: ESCUELA | D51: PREESCOLAR | E51: 11DJN0731Z - PROFR. JOSE SOSTENES LIRA | F51: SANTA EMILIA NUM. 430 | G51: COLONIA CUMBRES DE LA PISCINA | H51: LEÓN | I51: 21.10941 | J51: -101.70592 | L51: =HYPERLINK("https://www.google.com/maps?q=" & I51 & "," & J51, "Ver en Google Maps") -> Ver en Google Maps | M51: 1
A52: 198 | B52: Fibra Óptica | C52: ESCUELA | D52: PREESCOLAR | E52: 11DJN0884C - VIDAL ALCOCER | F52: CALLE CERRO DE JEREZ NUMERO EXTERIOR: 1507 , COLONIA CERRITO DE J | G52: COLONIA CERRITO DE JEREZ | H52: LEÓN | I52: 21.087012 | J52: -101.63593 | L52: =HYPERLINK("https://www.google.com/maps?q=" & I52 & "," & J52, "Ver en Google Maps") -> Ver en Google Maps | M52: 1
A53: 199 | B53: Fibra Óptica | C53: ESCUELA | D53: PREESCOLAR | E53: 11DJN0887Z - NICOLAS RANGEL | F53: ANDADOR DE LA TRINCHERA NUMERO EXTERIOR: SN, COLONIA SAN CARLOS L | G53: COLONIA SAN CARLOS LA ROCHA | H53: LEÓN | I53: 21.070203 | J53: -101.58637 | L53: =HYPERLINK("https://www.google.com/maps?q=" & I53 & "," & J53, "Ver en Google Maps") -> Ver en Google Maps | M53: 1
A54: 200 | B54: Fibra Óptica | C54: ESCUELA | D54: PREESCOLAR | E54: 11DJN0888Z - MARIA CURIE | F54: BOULEVARD KAROL WOJTYLA NUMERO EXTERIOR: SN, FRACCIONAMIENTO VILL | G54: COLONIA VILLAS DE SAN NICOLAS | H54: LEÓN | I54: 21.11598 | J54: -101.58891 | K54: ok | L54: =HYPERLINK("https://www.google.com/maps?q=" & I54 & "," & J54, "Ver en Google Maps") -> Ver en Google Maps | M54: 1 | N54: 45957 | O54: =DAY('BD2'!$N54) -> 27 | P54: =MONTH('BD2'!$N54) -> 10 | Q54: =YEAR('BD2'!$N54) -> 2025 | R54: 2 | S54: si | T54: si | U54: si | V54: si | W54: si | X54: si | Y54: si | Z54: =IF('BD2'!$AA54 < 14, "no", "si") -> si | AA54: 83.7 | AB54: 31.2 | AC54: La conexión fue rápida y constante, la navegación fue fluida, no se observan anomalías, tiene buena señal | AD54: José Mosqueda | AE54: =COUNTIF(S54:Z54, "si") -> 8 | AF54: =IF(AE54=8,"Estable",(IF(AE54=7,"Funcional con observaciones", (IF(AE54=6,"Funcional con observaciones",(IF(AE54=5,"Rendimiento bajo",(IF(AE54=4,"Parcialmente funcional",(IF(AE54=3,"Parcialmente funcional",(IF(AE54=2,"Inoperativo",(IF(AE54=1,"Inoperativo","Crítico"))))))))))))))) -> Estable
A55: 202 | B55: Fibra Óptica | C55: ESCUELA | D55: PREESCOLAR | E55: 11DJN2398Y - CARMEN NORMA MONROY | F55: ISLA DE TODOS LOS SANTOS NUM. 104 | G55: COLONIA SATELITE | H55: LEÓN | I55: 21.11529 | J55: -101.72177 | K55: ok | L55: =HYPERLINK("https://www.google.com/maps?q=" & I55 & "," & J55, "Ver en Google Maps") -> Ver en Google Maps | M55: 1 | N55: 45964 | O55: =DAY('BD2'!$N55) -> 3 | P55: =MONTH('BD2'!$N55) -> 11 | Q55: =YEAR('BD2'!$N55) -> 2025 | R55: 2 | S55: si | T55: si | U55: si | V55: si | W55: si | X55: si | Y55: no | Z55: =IF('BD2'!$AA55 < 14, "no", "si") -> si | AA55: 98.1 | AB55: 36.8 | AC55: La conexión fue rápida y constante, la navegación fue fluida, no se observan anomalías, tiene buena señal | AD55: José Mosqueda | AE55: =COUNTIF(S55:Z55, "si") -> 7 | AF55: =IF(AE55=8,"Estable",(IF(AE55=7,"Funcional con observaciones", (IF(AE55=6,"Funcional con observaciones",(IF(AE55=5,"Rendimiento bajo",(IF(AE55=4,"Parcialmente funcional",(IF(AE55=3,"Parcialmente funcional",(IF(AE55=2,"Inoperativo",(IF(AE55=1,"Inoperativo","Crítico"))))))))))))))) -> Funcional con observaciones
A56: 203 | B56: Fibra Óptica | C56: ESCUELA | D56: PREESCOLAR | E56: 11DJN2355Z - FEDERICO FROEBEL | F56: GOLFO DE MEXICO NUM. 112 | G56: COLONIA SANTA MARIA DEL GRANJENO | H56: LEÓN | I56: 21.09208 | J56: -101.65699 | L56: =HYPERLINK("https://www.google.com/maps?q=" & I56 & "," & J56, "Ver en Google Maps") -> Ver en Google Maps | M56: 1
